Workbook
Name dateColumn_Reminder_1612459588747: Customers!$J$1

Sheet Product2
A1: =#REF! -> #REF! | B1: =#REF! -> #REF! | C1: =#REF! -> #REF! | D1: =#REF! -> #REF! | E1: =#REF! -> #REF! | F1: =#REF! -> #REF! | G1: =#REF! -> #REF! | H1: =#REF! -> #REF! | ... S1: =#REF! -> #REF! | T1: Custom Paper | AE1: UV Crystal | AF1: UV Flat | AG1: =#REF! -> #REF! | AH1: =#REF! -> #REF! | AI1: =#REF! -> #REF! | AJ1: =#REF! -> #REF! | AK1: =#REF! -> #REF! | AL1: =#REF! -> #REF! | AM1: =#REF! -> #REF! | AN1: Plain | AO1: Gumming Full | AP1: Gumming Top Bottom | AQ1: Gumming 4 Sides | AR1: Dangler Making | AS1: Dangler With Rivet | AT1: Dangler With Rivet and Elastic | AU1: Half Cut Front | AV1: Half Cut Back | AW1: Cutting | AX1: Plain | AY1: Custom Gumming | AZ1: Carry Bag Single Pasting | BA1: Carry Bag Double Pasting | BE1: =Quotation!A29 -> Offset | BF1: =Quotation!B29 -> Packaging | BG1: =Quotation!B31 -> Custom Paper | BH1: =Quotation!B32 -> Varnish | BI1: =Quotation!C34 -> Carry Bag Single Pasting | BJ1: =Quotation!C35 -> Plain | BK1: =Quotation!B35 -> Plain | BL1: =Quotation!A34 -> New Job | BO1: =Quotation!B31 -> Custom Paper | BS1: =Quotation!B31 -> Custom Paper | BZ1: =Quotation!C31 -> Custom | CD1: =Quotation!D31 -> GSM
A2: =#REF! -> #REF! | B2: =#REF! -> #REF! | C2: =#REF! -> #REF! | D2: =#REF! -> #REF! | E2: =#REF! -> #REF! | F2: =#REF! -> #REF! | G2: =Quotation!C31 -> Custom | H2: =Quotation!E30 -> 500 | I2: =#REF! -> #REF! | J2: =#REF! -> #REF! | K2: =J2 -> #REF! | L2: =J2 -> #REF! | M2: =J2 -> #REF! | N2: =J2 -> #REF! | O2: =#REF! -> #REF! | P2: =#REF! -> #REF! | Q2: =#REF! -> #REF! | R2: =#REF! -> #REF! | S2: =#REF! -> #REF! | T2: =#REF! -> #REF! | AE2: =#REF! -> #REF! | AF2: =#REF! -> #REF! | AG2: =#REF! -> #REF! | AH2: =#REF! -> #REF! | AI2: =#REF! -> #REF! | AJ2: =#REF! -> #REF! | AK2: =#REF! -> #REF! | AL2: =#REF! -> #REF! | AM2: =#REF! -> #REF! | AN2: 0 | AO2: =#REF! -> #REF! | AP2: =#REF! -> #REF! | AQ2: =#REF! -> #REF! | AR2: =#REF! -> #REF! | AS2: =#REF! -> #REF! | AT2: =#REF! -> #REF! | AU2: =#REF! -> #REF! | AV2: =#REF! -> #REF! | AW2: =#REF! -> #REF! | AX2: 0 | AY2: =#REF! -> #REF! | AZ2: =#REF! -> #REF! | BA2: =#REF! -> #REF! | BS2: =IF(BS1="","","and BS = '"&BS1&"'") -> and BS = 'Custom Paper' | BZ2: =IF(BZ1="","","and BX = '"&BZ1&"'") -> and BX = 'Custom' | CD2: =IF(CD1="","","and CD = '"&CD1&"'") -> and CD = 'GSM'
A3: =A1 -> #REF! | B3: =B1 -> #REF! | C3: =C1 -> #REF! | D3: =D1 -> #REF! | E3: =E1 -> #REF! | F3: =F1 -> #REF! | G3: =G1 -> #REF! | H3: =H1 -> #REF! | ... S3: =S1 -> #REF! | T3: Custom Paper | AE3: UV Crystal | AF3: UV Flat | AG3: =AG1 -> #REF! | AH3: =AH1 -> #REF! | AI3: =AI1 -> #REF! | AJ3: =AJ1 -> #REF! | AK3: =AK1 -> #REF! | AL3: =AL1 -> #REF! | AM3: =AM1 -> #REF! | AN3: =AN1 -> Plain | AO3: Gumming Full | AP3: Gumming Top Bottom | AQ3: Gumming 4 Sides | AR3: Dangler Making | AS3: Dangler With Rivet | AT3: Dangler With Rivet and Elastic | AU3: Half Cut Front | AV3: Half Cut Back | AW3: Cutting | AX3: Plain | AY3: Custom Gumming | AZ3: Carry Bag Single Pasting | BA3: Carry Bag Double Pasting | BE3: =IF(BE1="","","and A = '"&BE1&"'") -> and A = 'Offset' | BF3: =IF(BF1="","","and B = '"&BF1&"'") -> and B = 'Packaging' | BG3: =IF(BF1="","","and M = '"&BF1&"'") -> and M = 'Packaging' | BH3: =IF(BF1="","","and BF = '"&BF1&"'") -> and BF = 'Packaging' | BI3: =IF(BG1="","","and AY = '"&BG1&"'") -> and AY = 'Custom Paper' | BJ3: =IF(BH1="","","and BC = '"&BH1&"'") -> and BC = 'Varnish' | BK3: =IF(BI1="","","and AW = '"&BI1&"'") -> and AW = 'Carry Bag Single Pasting' | BL3: =IF(BJ1="","","and AU = '"&BJ1&"'") -> and AU = 'Plain' | BM3: =IF(BK1="","","and BC = '"&BK1&"'") -> and BC = 'Plain' | BN3: =IF(BL1="","","and BA = '"&BL1&"'") -> and BA = 'New Job' | BO3: =IF(BO1="","","and AW = '"&BO1&"'") -> and AW = 'Custom Paper' | BS3: =CONCATENATE("select * where 1=1",BS2) -> select * where 1=1and BS = 'Custom Paper' | BZ3: =CONCATENATE("select * where 1=1",BZ2) -> select * where 1=1and BX = 'Custom' | CD3: =CONCATENATE("select * where 1=1",CD2) -> select * where 1=1and CD = 'GSM'
A4: =#REF! -> #REF! | B4: =#REF! -> #REF! | C4: =#REF! -> #REF! | D4: =#REF! -> #REF! | E4: =#REF! -> #REF! | F4: =#REF! -> #REF! | G4: =G2 -> Custom | H4: =Quotation!E31 -> 35000 | I4: =#REF! -> #REF! | J4: =#REF! -> #REF! | K4: =J4 -> #REF! | L4: =J4 -> #REF! | M4: =J4 -> #REF! | N4: =J4 -> #REF! | O4: =#REF! -> #REF! | P4: =#REF! -> #REF! | Q4: =#REF! -> #REF! | R4: =#REF! -> #REF! | S4: =#REF! -> #REF! | T4: =#REF! -> #REF! | AE4: =#REF! -> #REF! | AF4: =#REF! -> #REF! | AG4: =#REF! -> #REF! | AH4: =#REF! -> #REF! | AI4: =#REF! -> #REF! | AJ4: =#REF! -> #REF! | AK4: =#REF! -> #REF! | AL4: =#REF! -> #REF! | AM4: =#REF! -> #REF! | AN4: 0 | AO4: =#REF! -> #REF! | AP4: =#REF! -> #REF! | AQ4: =#REF! -> #REF! | AR4: =#REF! -> #REF! | AS4: =#REF! -> #REF! | AT4: =#REF! -> #REF! | AU4: =#REF! -> #REF! | AV4: =#REF! -> #REF! | AW4: =#REF! -> #REF! | AX4: 0 | AY4: =#REF! -> #REF! | AZ4: =#REF! -> #REF! | BA4: =#REF! -> #REF! | BE4: =CONCATENATE("select * where 1=1",BE3) -> select * where 1=1and A = 'Offset' | BF4: =CONCATENATE("select * where 1=1",BF3) -> select * where 1=1and B = 'Packaging' | BG4: =CONCATENATE("select * where 1=1",BG3) -> select * where 1=1and M = 'Packaging' | BH4: =CONCATENATE("select * where 1=1",BH3) -> select * where 1=1and BF = 'Packaging' | BI4: =CONCATENATE("select * where 1=1",BI3) -> select * where 1=1and AY = 'Custom Paper' | BJ4: =CONCATENATE("select * where 1=1",BJ3) -> select * where 1=1and BC = 'Varnish' | BK4: =CONCATENATE("select * where 1=1",BK3) -> select * where 1=1and AW = 'Carry Bag Single Pasting' | BL4: =CONCATENATE("select * where 1=1",BL3) -> select * where 1=1and AU = 'Plain' | ... BO4: =CONCATENATE("select * where 1=1",BO3) -> select * where 1=1and AW = 'Custom Paper' | BX4: N/A | BY4: N/A | CD4: GSM | CE4: =Quotation!D32 -> 170
A5: =A1 -> #REF! | B5: =B1 -> #REF! | C5: =C1 -> #REF! | D5: =D1 -> #REF! | E5: =E1 -> #REF! | F5: =F1 -> #REF! | G5: =G1 -> #REF! | H5: =H1 -> #REF! | ... S5: =S1 -> #REF! | T5: Custom Paper | AE5: UV Crystal | AF5: UV Flat | AG5: =AG1 -> #REF! | AH5: =AH1 -> #REF! | AI5: =AI1 -> #REF! | AJ5: =AJ1 -> #REF! | AK5: =AK1 -> #REF! | AL5: =AL1 -> #REF! | AM5: =AM1 -> #REF! | AN5: =AN1 -> Plain | AO5: Gumming Full | AP5: Gumming Top Bottom | AQ5: Gumming 4 Sides | AR5: Dangler Making | AS5: Dangler With Rivet | AT5: Dangler With Rivet and Elastic | AU5: Half Cut Front | AV5: Half Cut Back | AW5: Cutting | AX5: Plain | AY5: Custom Gumming | AZ5: Carry Bag Single Pasting | BA5: Carry Bag Double Pasting | BD5: All | BJ5: Plain | BP5: Plain | BQ5: N/A | BS5: SBS | BT5: ITC | BU5: 230 GSM | BV5: =#REF! -> #REF! | BW5: =IFERROR(__xludf.DUMMYFUNCTION("QUERY(BS5:BV60,BS3)"),"Custom Paper") -> Custom Paper | BX5: =IFERROR(__xludf.DUMMYFUNCTION("""COMPUTED_VALUE"""),"Custom") -> Custom | BZ5: =IFERROR(__xludf.DUMMYFUNCTION("""COMPUTED_VALUE"""),75) -> 75 | CA5: =IFERROR(__xludf.DUMMYFUNCTION("(QUERY(BX5:BZ42,BZ3))"),"Custom") -> Custom | CC5: =IFERROR(__xludf.DUMMYFUNCTION("""COMPUTED_VALUE"""),75) -> 75 | CD5: =BY5 -> 0 | CE5: =CD5 -> 0 | CF5: =IFERROR(__xludf.DUMMYFUNCTION("QUERY(CD4:CE42,CD3)"),"GSM") -> GSM | CG5: =IFERROR(__xludf.DUMMYFUNCTION("""COMPUTED_VALUE"""),"170") -> 170
A6: =#REF! -> #REF! | B6: =#REF! -> #REF! | C6: =#REF! -> #REF! | D6: =#REF! -> #REF! | E6: =#REF! -> #REF! | F6: =#REF! -> #REF! | G6: =G2 -> Custom | H6: =Quotation!E32 -> 0 | I6: =#REF! -> #REF! | J6: =#REF! -> #REF! | K6: =J6 -> #REF! | L6: =J6 -> #REF! | M6: =J6 -> #REF! | N6: =J6 -> #REF! | O6: =#REF! -> #REF! | P6: =#REF! -> #REF! | Q6: =#REF! -> #REF! | R6: =#REF! -> #REF! | S6: =#REF! -> #REF! | T6: =#REF! -> #REF! | AE6: =#REF! -> #REF! | AF6: =#REF! -> #REF! | AG6: =#REF! -> #REF! | AH6: =#REF! -> #REF! | AI6: =#REF! -> #REF! | AJ6: =#REF! -> #REF! | AK6: =#REF! -> #REF! | AL6: =#REF! -> #REF! | AM6: =#REF! -> #REF! | AN6: 0 | AO6: =#REF! -> #REF! | AP6: =#REF! -> #REF! | AQ6: =#REF! -> #REF! | AR6: =#REF! -> #REF! | AS6: =#REF! -> #REF! | AT6: =#REF! -> #REF! | AU6: =#REF! -> #REF! | AV6: =#REF! -> #REF! | AW6: =#REF! -> #REF! | AX6: 0 | AY6: =#REF! -> #REF! | AZ6: =#REF! -> #REF! | BA6: =#REF! -> #REF! | BC6: =IFERROR(__xludf.DUMMYFUNCTION("UNIQUE(QUERY(Item!M1:N2457,BG4))"),"Packaging") -> Packaging | BD6: =IFERROR(__xludf.DUMMYFUNCTION("""COMPUTED_VALUE"""),"Agarbatti") -> Agarbatti | BE6: =IFERROR(__xludf.DUMMYFUNCTION("UNIQUE(QUERY(Item!A2:B2457,BE4))"),"Offset") -> Offset | BF6: =IFERROR(__xludf.DUMMYFUNCTION("""COMPUTED_VALUE"""),"Packaging") -> Packaging | BG6: =IFERROR(__xludf.DUMMYFUNCTION("UNIQUE(QUERY(Item!A2:L2457,BF4))"),"Offset") -> Offset | BH6: =IFERROR(__xludf.DUMMYFUNCTION("""COMPUTED_VALUE"""),"Packaging") -> Packaging | BI6: =IFERROR(__xludf.DUMMYFUNCTION("""COMPUTED_VALUE"""),"SBS") -> SBS | BJ6: =IFERROR(__xludf.DUMMYFUNCTION("""COMPUTED_VALUE"""),"Carry Bag Single Pasting") -> Carry Bag Single Pasting | BK6: =IFERROR(__xludf.DUMMYFUNCTION("""COMPUTED_VALUE"""),"Lamination Thermal") -> Lamination Thermal | BL6: =IFERROR(__xludf.DUMMYFUNCTION("""COMPUTED_VALUE"""),"Single Colour") -> Single Colour | BM6: =IFERROR(__xludf.DUMMYFUNCTION("""COMPUTED_VALUE"""),1) -> 1 | BN6: =IFERROR(__xludf.DUMMYFUNCTION("""COMPUTED_VALUE"""),1926) -> 1926 | BO6: =IFERROR(__xludf.DUMMYFUNCTION("""COMPUTED_VALUE"""),"New Job") -> New Job | BP6: =IFERROR(__xludf.DUMMYFUNCTION("""COMPUTED_VALUE"""),"Leafing") -> Leafing | BQ6: =IFERROR(__xludf.DUMMYFUNCTION("""COMPUTED_VALUE"""),"Yes") -> Yes | BR6: =IFERROR(__xludf.DUMMYFUNCTION("""COMPUTED_VALUE"""),"Normal") -> Normal | BS6: SBS | BT6: Century | BU6: 250 GSM | BV6: =#REF! -> #REF! | CD6: =BY6 -> 0 | CE6: =CD6 -> 0
A7: Type | B7: =Quotation!A29 -> Offset | F7: =IF(B8="","","and Q = '"&B8&"'") -> and Q = 'Packaging' | AV7: =#REF! -> #REF! | BC7: =IFERROR(__xludf.DUMMYFUNCTION("""COMPUTED_VALUE"""),"Packaging") -> Packaging | BD7: =IFERROR(__xludf.DUMMYFUNCTION("""COMPUTED_VALUE"""),"Apparel") -> Apparel | BE7: =IFERROR(__xludf.DUMMYFUNCTION("""COMPUTED_VALUE"""),"Offset") -> Offset | BF7: =IFERROR(__xludf.DUMMYFUNCTION("""COMPUTED_VALUE"""),"Commercial") -> Commercial | BG7: =IFERROR(__xludf.DUMMYFUNCTION("""COMPUTED_VALUE"""),"Offset") -> Offset | BH7: =IFERROR(__xludf.DUMMYFUNCTION("""COMPUTED_VALUE"""),"Packaging") -> Packaging | BI7: =IFERROR(__xludf.DUMMYFUNCTION("""COMPUTED_VALUE"""),"WhiteBack") -> WhiteBack | BJ7: =IFERROR(__xludf.DUMMYFUNCTION("""COMPUTED_VALUE"""),"Carry Bag Double Pasting") -> Carry Bag Double Pasting | BK7: =IFERROR(__xludf.DUMMYFUNCTION("""COMPUTED_VALUE"""),"Lamination Normal Gloss") -> Lamination Normal Gloss | BL7: =IFERROR(__xludf.DUMMYFUNCTION("""COMPUTED_VALUE"""),"Double Colour") -> Double Colour | BM7: =IFERROR(__xludf.DUMMYFUNCTION("""COMPUTED_VALUE"""),2) -> 2 | BN7: =IFERROR(__xludf.DUMMYFUNCTION("""COMPUTED_VALUE"""),2029) -> 2029 | BO7: =IFERROR(__xludf.DUMMYFUNCTION("""COMPUTED_VALUE"""),"Repeat Job") -> Repeat Job | BP7: =IFERROR(__xludf.DUMMYFUNCTION("""COMPUTED_VALUE"""),"Leafing") -> Leafing | BQ7: =IFERROR(__xludf.DUMMYFUNCTION("""COMPUTED_VALUE"""),"N/A") -> N/A | BR7: =IFERROR(__xludf.DUMMYFUNCTION("""COMPUTED_VALUE"""),"Normal") -> Normal | BS7: SBS | BT7: Normal | BU7: 280 GSM | BV7: =#REF! -> #REF! | CD7: =BY7 -> 0 | CE7: =CD7 -> 0
A8: Sub Type | B8: =Quotation!B29 -> Packaging | F8: =IF(B7="","","and P = '"&B7&"'") -> and P = 'Offset' | BC8: =IFERROR(__xludf.DUMMYFUNCTION("""COMPUTED_VALUE"""),"Packaging") -> Packaging | BD8: =IFERROR(__xludf.DUMMYFUNCTION("""COMPUTED_VALUE"""),"Artsbury") -> Artsbury | BE8: =IFERROR(__xludf.DUMMYFUNCTION("""COMPUTED_VALUE"""),"Offset") -> Offset | BF8: =IFERROR(__xludf.DUMMYFUNCTION("""COMPUTED_VALUE"""),"Booklet") -> Booklet | BG8: =IFERROR(__xludf.DUMMYFUNCTION("""COMPUTED_VALUE"""),"Offset") -> Offset | BH8: =IFERROR(__xludf.DUMMYFUNCTION("""COMPUTED_VALUE"""),"Packaging") -> Packaging | BI8: =IFERROR(__xludf.DUMMYFUNCTION("""COMPUTED_VALUE"""),"GreyBack") -> GreyBack | BJ8: =IFERROR(__xludf.DUMMYFUNCTION("""COMPUTED_VALUE"""),"Plain") -> Plain | BK8: =IFERROR(__xludf.DUMMYFUNCTION("""COMPUTED_VALUE"""),"Lamination Normal Matt") -> Lamination Normal Matt | BL8: =IFERROR(__xludf.DUMMYFUNCTION("""COMPUTED_VALUE"""),"Four Colour") -> Four Colour | BM8: =IFERROR(__xludf.DUMMYFUNCTION("""COMPUTED_VALUE"""),4) -> 4 | BN8: =IFERROR(__xludf.DUMMYFUNCTION("""COMPUTED_VALUE"""),2840) -> 2840 | BO8: =IFERROR(__xludf.DUMMYFUNCTION("""COMPUTED_VALUE"""),"New Job") -> New Job | BP8: =IFERROR(__xludf.DUMMYFUNCTION("""COMPUTED_VALUE"""),"Leafing") -> Leafing | BQ8: =IFERROR(__xludf.DUMMYFUNCTION("""COMPUTED_VALUE"""),"Yes") -> Yes | BR8: =IFERROR(__xludf.DUMMYFUNCTION("""COMPUTED_VALUE"""),"Normal") -> Normal | BS8: SBS | BT8: Custom | BU8: 300 GSM | BV8: =Quotation!$C$29 -> 75 | CD8: =BY8 -> 0 | CE8: =CD8 -> 0
A9: Select Category | B9: =Quotation!A30 -> Food | D9: =IF(B12="All","","and B = '"&B12&"'") -> and B = '' | F9: =IF(B9="All","","and B = '"&B9&"'") -> and B = 'Food' | BC9: =IFERROR(__xludf.DUMMYFUNCTION("""COMPUTED_VALUE"""),"Packaging") -> Packaging | BD9: =IFERROR(__xludf.DUMMYFUNCTION("""COMPUTED_VALUE"""),"Aryan") -> Aryan | BG9: =IFERROR(__xludf.DUMMYFUNCTION("""COMPUTED_VALUE"""),"Offset") -> Offset | BH9: =IFERROR(__xludf.DUMMYFUNCTION("""COMPUTED_VALUE"""),"Packaging") -> Packaging | BI9: =IFERROR(__xludf.DUMMYFUNCTION("""COMPUTED_VALUE"""),"Duplex") -> Duplex | BJ9: =IFERROR(__xludf.DUMMYFUNCTION("""COMPUTED_VALUE"""),"Plain") -> Plain | BK9: =IFERROR(__xludf.DUMMYFUNCTION("""COMPUTED_VALUE"""),"Varnish") -> Varnish | BL9: =IFERROR(__xludf.DUMMYFUNCTION("""COMPUTED_VALUE"""),"Four + One Colour") -> Four + One Colour | BM9: =IFERROR(__xludf.DUMMYFUNCTION("""COMPUTED_VALUE"""),6.75) -> 6.75 | BN9: =IFERROR(__xludf.DUMMYFUNCTION("""COMPUTED_VALUE"""),1926) -> 1926 | BO9: =IFERROR(__xludf.DUMMYFUNCTION("""COMPUTED_VALUE"""),"Repeat Job") -> Repeat Job | BP9: =IFERROR(__xludf.DUMMYFUNCTION("""COMPUTED_VALUE"""),"Leafing") -> Leafing | BQ9: =IFERROR(__xludf.DUMMYFUNCTION("""COMPUTED_VALUE"""),"N/A") -> N/A | BR9: =IFERROR(__xludf.DUMMYFUNCTION("""COMPUTED_VALUE"""),"Normal") -> Normal | BS9: SBS | BT9: Custom | BU9: 330 GSM | BV9: =$BV$8 -> 75 | CD9: =BY9 -> 0 | CE9: =CD9 -> 0
B10: =Quotation!A31 -> Wrap | D10: =IF(B10="","","and T = '"&B10&"'") -> and T = 'Wrap' | F10: =IF(B10="","","and C = '"&B10&"'") -> and C = 'Wrap' | I10: =CONCATENATE("select * where 1=1",F9,F10,F11) -> select * where 1=1and B = 'Food'and C = 'Wrap'and D = '240*64*160 mm | 9.5*2.5*6.25 inch' | BC10: =IFERROR(__xludf.DUMMYFUNCTION("""COMPUTED_VALUE"""),"Packaging") -> Packaging | BD10: =IFERROR(__xludf.DUMMYFUNCTION("""COMPUTED_VALUE"""),"Atta") -> Atta | BG10: =IFERROR(__xludf.DUMMYFUNCTION("""COMPUTED_VALUE"""),"Offset") -> Offset | BH10: =IFERROR(__xludf.DUMMYFUNCTION("""COMPUTED_VALUE"""),"Packaging") -> Packaging | BI10: =IFERROR(__xludf.DUMMYFUNCTION("""COMPUTED_VALUE"""),"Custom Paper") -> Custom Paper | BJ10: =IFERROR(__xludf.DUMMYFUNCTION("""COMPUTED_VALUE"""),"Plain") -> Plain | BK10: =IFERROR(__xludf.DUMMYFUNCTION("""COMPUTED_VALUE"""),"UV Hybrid") -> UV Hybrid | BL10: =IFERROR(__xludf.DUMMYFUNCTION("""COMPUTED_VALUE"""),"Four + Two Colour") -> Four + Two Colour | BM10: =IFERROR(__xludf.DUMMYFUNCTION("""COMPUTED_VALUE"""),7.75) -> 7.75 | BN10: =IFERROR(__xludf.DUMMYFUNCTION("""COMPUTED_VALUE"""),1926) -> 1926 | BO10: =IFERROR(__xludf.DUMMYFUNCTION("""COMPUTED_VALUE"""),"New Job") -> New Job | BP10: =IFERROR(__xludf.DUMMYFUNCTION("""COMPUTED_VALUE"""),"Leafing") -> Leafing | BQ10: =IFERROR(__xludf.DUMMYFUNCTION("""COMPUTED_VALUE"""),"Yes") -> Yes | BR10: =IFERROR(__xludf.DUMMYFUNCTION("""COMPUTED_VALUE"""),"Normal") -> Normal | BS10: WhiteBack | BT10: Khanna | BU10: 230 GSM | BV10: =#REF! -> #REF! | CD10: =BY10 -> 0 | CE10: =CD10 -> 0
A11: Select Size | B11: =Quotation!B30 -> 240*64*160 mm | 9.5*2.5*6.25 inch | D11: =IF(B11="","","and AM = '"&B11&"'") -> and AM = '240*64*160 mm | 9.5*2.5*6.25 inch' | F11: =IF(B11="","","and D = '"&B11&"'") -> and D = '240*64*160 mm | 9.5*2.5*6.25 inch' | I11: =CONCATENATE("select * where 1=1",F10) -> select * where 1=1and C = 'Wrap' | BC11: =IFERROR(__xludf.DUMMYFUNCTION("""COMPUTED_VALUE"""),"Packaging") -> Packaging | BD11: =IFERROR(__xludf.DUMMYFUNCTION("""COMPUTED_VALUE"""),"Bakery") -> Bakery | BG11: =IFERROR(__xludf.DUMMYFUNCTION("""COMPUTED_VALUE"""),"Offset") -> Offset | BH11: =IFERROR(__xludf.DUMMYFUNCTION("""COMPUTED_VALUE"""),"Packaging") -> Packaging | BI11: =IFERROR(__xludf.DUMMYFUNCTION("""COMPUTED_VALUE"""),"Other Type") -> Other Type | BJ11: =IFERROR(__xludf.DUMMYFUNCTION("""COMPUTED_VALUE"""),"Plain") -> Plain | BK11: =IFERROR(__xludf.DUMMYFUNCTION("""COMPUTED_VALUE"""),"UV Flat") -> UV Flat | BL11: =IFERROR(__xludf.DUMMYFUNCTION("""COMPUTED_VALUE"""),"Four + Four Colour") -> Four + Four Colour | BM11: =IFERROR(__xludf.DUMMYFUNCTION("""COMPUTED_VALUE"""),9.75) -> 9.75 | BN11: =IFERROR(__xludf.DUMMYFUNCTION("""COMPUTED_VALUE"""),1926) -> 1926 | BO11: =IFERROR(__xludf.DUMMYFUNCTION("""COMPUTED_VALUE"""),"Repeat Job") -> Repeat Job | BP11: =IFERROR(__xludf.DUMMYFUNCTION("""COMPUTED_VALUE"""),"Leafing") -> Leafing | BQ11: =IFERROR(__xludf.DUMMYFUNCTION("""COMPUTED_VALUE"""),"N/A") -> N/A | BR11: =IFERROR(__xludf.DUMMYFUNCTION("""COMPUTED_VALUE"""),"Normal") -> Normal | BS11: WhiteBack | BT11: Sinar Mas | BU11: 250 GSM | BV11: =#REF! -> #REF! | CD11: =BY11 -> 0 | CE11: =CD11 -> 0
D12: =CONCATENATE("select * where 1=1",D11) -> select * where 1=1and AM = '240*64*160 mm | 9.5*2.5*6.25 inch' | F12: =CONCATENATE("select * where 1=1",F9,F8,F7) -> select * where 1=1and B = 'Food'and P = 'Offset'and Q = 'Packaging' | I12: =CONCATENATE("select * where 1=1",F11,F10) -> select * where 1=1and D = '240*64*160 mm | 9.5*2.5*6.25 inch'and C = 'Wrap' | BC12: =IFERROR(__xludf.DUMMYFUNCTION("""COMPUTED_VALUE"""),"Packaging") -> Packaging | BD12: =IFERROR(__xludf.DUMMYFUNCTION("""COMPUTED_VALUE"""),"Bakery Online") -> Bakery Online | BG12: =IFERROR(__xludf.DUMMYFUNCTION("""COMPUTED_VALUE"""),"Offset") -> Offset | BH12: =IFERROR(__xludf.DUMMYFUNCTION("""COMPUTED_VALUE"""),"Packaging") -> Packaging | BI12: =IFERROR(__xludf.DUMMYFUNCTION("""COMPUTED_VALUE"""),"Other Type") -> Other Type | BJ12: =IFERROR(__xludf.DUMMYFUNCTION("""COMPUTED_VALUE"""),"Plain") -> Plain | BK12: =IFERROR(__xludf.DUMMYFUNCTION("""COMPUTED_VALUE"""),"Spot UV") -> Spot UV | BL12: =IFERROR(__xludf.DUMMYFUNCTION("""COMPUTED_VALUE"""),"Without Print") -> Without Print | BM12: =IFERROR(__xludf.DUMMYFUNCTION("""COMPUTED_VALUE"""),0) -> 0 | BN12: =IFERROR(__xludf.DUMMYFUNCTION("""COMPUTED_VALUE"""),1926) -> 1926 | BO12: =IFERROR(__xludf.DUMMYFUNCTION("""COMPUTED_VALUE"""),"New Job") -> New Job | BP12: =IFERROR(__xludf.DUMMYFUNCTION("""COMPUTED_VALUE"""),"Leafing") -> Leafing | BQ12: =IFERROR(__xludf.DUMMYFUNCTION("""COMPUTED_VALUE"""),"Yes") -> Yes | BR12: =IFERROR(__xludf.DUMMYFUNCTION("""COMPUTED_VALUE"""),"Normal") -> Normal | BS12: WhiteBack | BT12: Normal | BU12: 280 GSM | BV12: =#REF! -> #REF! | CD12: =BY12 -> 0 | CE12: =CD12 -> 0
A13: =IFERROR(__xludf.DUMMYFUNCTION("QUERY(AJ15:AY2457,$D$12,0)"),"#N/A") -> #N/A | BC13: =IFERROR(__xludf.DUMMYFUNCTION("""COMPUTED_VALUE"""),"Packaging") -> Packaging | BD13: =IFERROR(__xludf.DUMMYFUNCTION("""COMPUTED_VALUE"""),"Beverages") -> Beverages | BG13: =IFERROR(__xludf.DUMMYFUNCTION("""COMPUTED_VALUE"""),"Offset") -> Offset | BH13: =IFERROR(__xludf.DUMMYFUNCTION("""COMPUTED_VALUE"""),"Packaging") -> Packaging | BI13: =IFERROR(__xludf.DUMMYFUNCTION("""COMPUTED_VALUE"""),"Other Type") -> Other Type | BJ13: =IFERROR(__xludf.DUMMYFUNCTION("""COMPUTED_VALUE"""),"Plain") -> Plain | BK13: =IFERROR(__xludf.DUMMYFUNCTION("""COMPUTED_VALUE"""),"UV Crystal") -> UV Crystal | BL13: =IFERROR(__xludf.DUMMYFUNCTION("""COMPUTED_VALUE"""),"Without Print") -> Without Print | BM13: =IFERROR(__xludf.DUMMYFUNCTION("""COMPUTED_VALUE"""),0) -> 0 | BN13: =IFERROR(__xludf.DUMMYFUNCTION("""COMPUTED_VALUE"""),1926) -> 1926 | BO13: =IFERROR(__xludf.DUMMYFUNCTION("""COMPUTED_VALUE"""),"Repeat Job") -> Repeat Job | BP13: =IFERROR(__xludf.DUMMYFUNCTION("""COMPUTED_VALUE"""),"Leafing") -> Leafing | BQ13: =IFERROR(__xludf.DUMMYFUNCTION("""COMPUTED_VALUE"""),"N/A") -> N/A | BR13: =IFERROR(__xludf.DUMMYFUNCTION("""COMPUTED_VALUE"""),"Normal") -> Normal | BS13: WhiteBack | BT13: Custom | BU13: 300 GSM | BV13: =$BV$9 -> 75 | CD13: =BY13 -> 0 | CE13: =CD13 -> 0
A14: Product Code | B14: Category | C14: Sub Category | D14: Specifications | E14: No. of Ups | F14: Machine | G14: Sheet W | H14: Sheet H | I14: Designing | J14: Gumming Per Sheet | K14: Leafing / Embossing | L14: Window | M14: Pasting | N14: Double Charges | O14: Price Per Sheet | AJ14: Product Code | AK14: Category | AL14: Sub Category | AM14: Specifications | AN14: No. of Ups | AO14: Machine | AP14: Sheet W | AQ14: Sheet H | AR14: Designing | AS14: Gumming Per Sheet | AT14: Leafing / Embossing | AU14: Window | AV14: Pasting | AW14: Double Charges | AX14: Price Per Sheet | BB14: Print | BC14: =IFERROR(__xludf.DUMMYFUNCTION("""COMPUTED_VALUE"""),"Packaging") -> Packaging | BD14: =IFERROR(__xludf.DUMMYFUNCTION("""COMPUTED_VALUE"""),"BO") -> BO | BG14: =IFERROR(__xludf.DUMMYFUNCTION("""COMPUTED_VALUE"""),"Offset") -> Offset | BH14: =IFERROR(__xludf.DUMMYFUNCTION("""COMPUTED_VALUE"""),"Packaging") -> Packaging | BI14: =IFERROR(__xludf.DUMMYFUNCTION("""COMPUTED_VALUE"""),"Other Type") -> Other Type | BJ14: =IFERROR(__xludf.DUMMYFUNCTION("""COMPUTED_VALUE"""),"Plain") -> Plain | BK14: =IFERROR(__xludf.DUMMYFUNCTION("""COMPUTED_VALUE"""),"Plain") -> Plain | BL14: =IFERROR(__xludf.DUMMYFUNCTION("""COMPUTED_VALUE"""),"Without Print") -> Without Print | BM14: =IFERROR(__xludf.DUMMYFUNCTION("""COMPUTED_VALUE"""),0) -> 0 | BN14: =IFERROR(__xludf.DUMMYFUNCTION("""COMPUTED_VALUE"""),1926) -> 1926 | BP14: =IFERROR(__xludf.DUMMYFUNCTION("""COMPUTED_VALUE"""),"Leafing") -> Leafing | BQ14: =IFERROR(__xludf.DUMMYFUNCTION("""COMPUTED_VALUE"""),"N/A") -> N/A | BR14: =IFERROR(__xludf.DUMMYFUNCTION("""COMPUTED_VALUE"""),"Normal") -> Normal | BS14: WhiteBack | BT14: Custom | BU14: 330 GSM | BV14: =$BV$9 -> 75 | CD14: =BY14 -> 0 | CE14: =CD14 -> 0
B15: All | C15: =B10 -> Wrap | D15: Custom Size | E15: =Product6!E2 -> 0 | F15: =Product6!F2 -> 0 | G15: =Product6!W16 -> 0 | H15: =Product6!X16 -> 0 | I15: 100 | N15: 1 | O15: =Product6!Y16 -> 0 | AJ15: =IFERROR(__xludf.DUMMYFUNCTION("ifna(QUERY(A15:O2457,$I$11))"),"") | AK15: =IFERROR(__xludf.DUMMYFUNCTION("""COMPUTED_VALUE"""),"All") -> All | AL15: =IFERROR(__xludf.DUMMYFUNCTION("""COMPUTED_VALUE"""),"Wrap") -> Wrap | AM15: =IFERROR(__xludf.DUMMYFUNCTION("""COMPUTED_VALUE"""),"Custom Size") -> Custom Size | AN15: =IFERROR(__xludf.DUMMYFUNCTION("""COMPUTED_VALUE"""),"") | AO15: =IFERROR(__xludf.DUMMYFUNCTION("""COMPUTED_VALUE"""),"") | AP15: =IFERROR(__xludf.DUMMYFUNCTION("""COMPUTED_VALUE"""),"") | AQ15: =IFERROR(__xludf.DUMMYFUNCTION("""COMPUTED_VALUE"""),"") | AR15: =IFERROR(__xludf.DUMMYFUNCTION("""COMPUTED_VALUE"""),"100") -> 100 | AS15: =IFERROR(__xludf.DUMMYFUNCTION("""COMPUTED_VALUE"""),"") | AT15: =IFERROR(__xludf.DUMMYFUNCTION("""COMPUTED_VALUE"""),"") | AU15: =IFERROR(__xludf.DUMMYFUNCTION("""COMPUTED_VALUE"""),"") | AV15: =IFERROR(__xludf.DUMMYFUNCTION("""COMPUTED_VALUE"""),"") | AW15: =IFERROR(__xludf.DUMMYFUNCTION("""COMPUTED_VALUE"""),"1") -> 1 | AX15: =IFERROR(__xludf.DUMMYFUNCTION("""COMPUTED_VALUE"""),"") | BB15: {=INDEX(#REF!,MATCH(Quotation!B33,#REF!,FALSE),1)} -> #REF! | BC15: =IFERROR(__xludf.DUMMYFUNCTION("""COMPUTED_VALUE"""),"Packaging") -> Packaging | BD15: =IFERROR(__xludf.DUMMYFUNCTION("""COMPUTED_VALUE"""),"Boult") -> Boult | BS15: WhiteBack | BT15: Custom | BU15: 350 GSM | BV15: =$BV$9 -> 75 | CD15: =BY15 -> 0 | CE15: =CD15 -> 0
A16: =IFERROR(__xludf.DUMMYFUNCTION("QUERY(ALLDATA!$A2:$Q2457,$F$12)"),"https://drive.google.com/open?id=1RCVTOA7UAiI06kh64ajGkxHXq7kK4A7v&authuser=jay.agg%40gmail.com&usp=drive_fs") -> https://drive.google.com/open?id=1RCVTOA7UAiI06kh64ajGkxHXq7kK4A7v&authuser=jay.agg%40gmail.com&usp=drive_fs | B16: =IFERROR(__xludf.DUMMYFUNCTION("""COMPUTED_VALUE"""),"Food") -> Food | C16: =IFERROR(__xludf.DUMMYFUNCTION("""COMPUTED_VALUE"""),"Wrap") -> Wrap | D16: =IFERROR(__xludf.DUMMYFUNCTION("""COMPUTED_VALUE"""),"15*74*217 mm") -> 15*74*217 mm | E16: =IFERROR(__xludf.DUMMYFUNCTION("""COMPUTED_VALUE"""),4) -> 4 | F16: =IFERROR(__xludf.DUMMYFUNCTION("""COMPUTED_VALUE"""),1926) -> 1926 | G16: =IFERROR(__xludf.DUMMYFUNCTION("""COMPUTED_VALUE"""),18) -> 18 | H16: =IFERROR(__xludf.DUMMYFUNCTION("""COMPUTED_VALUE"""),23) -> 23 | I16: =IFERROR(__xludf.DUMMYFUNCTION("""COMPUTED_VALUE"""),100) -> 100 | M16: =IFERROR(__xludf.DUMMYFUNCTION("""COMPUTED_VALUE"""),0.1) -> 0.1 | N16: =IFERROR(__xludf.DUMMYFUNCTION("""COMPUTED_VALUE"""),1) -> 1 | P16: =IFERROR(__xludf.DUMMYFUNCTION("""COMPUTED_VALUE"""),"Offset") -> Offset | Q16: =IFERROR(__xludf.DUMMYFUNCTION("""COMPUTED_VALUE"""),"Packaging") -> Packaging | AJ16: =IFERROR(__xludf.DUMMYFUNCTION("""COMPUTED_VALUE"""),"https://drive.google.com/open?id=1RCVTOA7UAiI06kh64ajGkxHXq7kK4A7v&authuser=jay.agg%40gmail.com&usp=drive_fs") -> https://drive.google.com/open?id=1RCVTOA7UAiI06kh64ajGkxHXq7kK4A7v&authuser=jay.agg%40gmail.com&usp=drive_fs | AK16: =IFERROR(__xludf.DUMMYFUNCTION("""COMPUTED_VALUE"""),"Food") -> Food | AL16: =IFERROR(__xludf.DUMMYFUNCTION("""COMPUTED_VALUE"""),"Wrap") -> Wrap | AM16: =IFERROR(__xludf.DUMMYFUNCTION("""COMPUTED_VALUE"""),"15*74*217 mm") -> 15*74*217 mm | AN16: =IFERROR(__xludf.DUMMYFUNCTION("""COMPUTED_VALUE"""),4) -> 4 | AO16: =IFERROR(__xludf.DUMMYFUNCTION("""COMPUTED_VALUE"""),1926) -> 1926 | AP16: =IFERROR(__xludf.DUMMYFUNCTION("""COMPUTED_VALUE"""),18) -> 18 | AQ16: =IFERROR(__xludf.DUMMYFUNCTION("""COMPUTED_VALUE"""),23) -> 23 | AR16: =IFERROR(__xludf.DUMMYFUNCTION("""COMPUTED_VALUE"""),100) -> 100 | AV16: =IFERROR(__xludf.DUMMYFUNCTION("""COMPUTED_VALUE"""),0.1) -> 0.1 | AW16: =IFERROR(__xludf.DUMMYFUNCTION("""COMPUTED_VALUE"""),1) -> 1 | BC16: =IFERROR(__xludf.DUMMYFUNCTION("""COMPUTED_VALUE"""),"Packaging") -> Packaging | BD16: =IFERROR(__xludf.DUMMYFUNCTION("""COMPUTED_VALUE"""),"Camera") -> Camera | BS16: GreyBack | BT16: Khanna | BU16: 230 GSM | BV16: =#REF! -> #REF! | CD16: =BY16 -> 0 | CE16: =CD16 -> 0
A17: =IFERROR(__xludf.DUMMYFUNCTION("""COMPUTED_VALUE"""),"https://drive.google.com/open?id=1RFhjQczaMAqJxxKHOOgWIUcetju9JHbB&authuser=jay.agg%40gmail.com&usp=drive_fs") -> https://drive.google.com/open?id=1RFhjQczaMAqJxxKHOOgWIUcetju9JHbB&authuser=jay.agg%40gmail.com&usp=drive_fs | B17: =IFERROR(__xludf.DUMMYFUNCTION("""COMPUTED_VALUE"""),"Food") -> Food | C17: =IFERROR(__xludf.DUMMYFUNCTION("""COMPUTED_VALUE"""),"Amla Candy") -> Amla Candy | D17: =IFERROR(__xludf.DUMMYFUNCTION("""COMPUTED_VALUE"""),"2.5*4.2*4.9 inch LB") -> 2.5*4.2*4.9 inch LB | E17: =IFERROR(__xludf.DUMMYFUNCTION("""COMPUTED_VALUE"""),4) -> 4 | F17: =IFERROR(__xludf.DUMMYFUNCTION("""COMPUTED_VALUE"""),2029) -> 2029 | G17: =IFERROR(__xludf.DUMMYFUNCTION("""COMPUTED_VALUE"""),20) -> 20 | H17: =IFERROR(__xludf.DUMMYFUNCTION("""COMPUTED_VALUE"""),28) -> 28 | I17: =IFERROR(__xludf.DUMMYFUNCTION("""COMPUTED_VALUE"""),100) -> 100 | M17: =IFERROR(__xludf.DUMMYFUNCTION("""COMPUTED_VALUE"""),0.16) -> 0.16 | N17: =IFERROR(__xludf.DUMMYFUNCTION("""COMPUTED_VALUE"""),1) -> 1 | P17: =IFERROR(__xludf.DUMMYFUNCTION("""COMPUTED_VALUE"""),"Offset") -> Offset | Q17: =IFERROR(__xludf.DUMMYFUNCTION("""COMPUTED_VALUE"""),"Packaging") -> Packaging | AJ17: =IFERROR(__xludf.DUMMYFUNCTION("""COMPUTED_VALUE"""),"https://drive.google.com/open?id=1S0JoeVa-x8xAselnMXu64Vmh1ngS_Cud&authuser=jay.agg%40gmail.com&usp=drive_fs") -> https://drive.google.com/open?id=1S0JoeVa-x8xAselnMXu64Vmh1ngS_Cud&authuser=jay.agg%40gmail.com&usp=drive_fs | AK17: =IFERROR(__xludf.DUMMYFUNCTION("""COMPUTED_VALUE"""),"Food") -> Food | AL17: =IFERROR(__xludf.DUMMYFUNCTION("""COMPUTED_VALUE"""),"Wrap") -> Wrap | AM17: =IFERROR(__xludf.DUMMYFUNCTION("""COMPUTED_VALUE"""),"97*255 mm | 3.8*10 inch") -> 97*255 mm | 3.8*10 inch | AN17: =IFERROR(__xludf.DUMMYFUNCTION("""COMPUTED_VALUE"""),4) -> 4 | AO17: =IFERROR(__xludf.DUMMYFUNCTION("""COMPUTED_VALUE"""),2029) -> 2029 | AP17: =IFERROR(__xludf.DUMMYFUNCTION("""COMPUTED_VALUE"""),18) -> 18 | AQ17: =IFERROR(__xludf.DUMMYFUNCTION("""COMPUTED_VALUE"""),25) -> 25 | AR17: =IFERROR(__xludf.DUMMYFUNCTION("""COMPUTED_VALUE"""),100) -> 100 | AV17: =IFERROR(__xludf.DUMMYFUNCTION("""COMPUTED_VALUE"""),0.12) -> 0.12 | AW17: =IFERROR(__xludf.DUMMYFUNCTION("""COMPUTED_VALUE"""),1) -> 1 | BC17: =IFERROR(__xludf.DUMMYFUNCTION("""COMPUTED_VALUE"""),"Packaging") -> Packaging | BD17: =IFERROR(__xludf.DUMMYFUNCTION("""COMPUTED_VALUE"""),"Candle") -> Candle | BS17: GreyBack | BT17: Sinar Mas | BU17: 250 GSM | BV17: =#REF! -> #REF! | CD17: =BY17 -> 0 | CE17: =CD17 -> 0
A18: =IFERROR(__xludf.DUMMYFUNCTION("""COMPUTED_VALUE"""),"https://drive.google.com/open?id=1R-6x1155ykPUIHal2qHhsGUOhJ93l5nv&authuser=jay.agg%40gmail.com&usp=drive_fs") -> https://drive.google.com/open?id=1R-6x1155ykPUIHal2qHhsGUOhJ93l5nv&authuser=jay.agg%40gmail.com&usp=drive_fs | B18: =IFERROR(__xludf.DUMMYFUNCTION("""COMPUTED_VALUE"""),"Food") -> Food | C18: =IFERROR(__xludf.DUMMYFUNCTION("""COMPUTED_VALUE"""),"Dry Fruit") -> Dry Fruit | D18: =IFERROR(__xludf.DUMMYFUNCTION("""COMPUTED_VALUE"""),"125*65*225 mm") -> 125*65*225 mm | E18: =IFERROR(__xludf.DUMMYFUNCTION("""COMPUTED_VALUE"""),2) -> 2 | F18: =IFERROR(__xludf.DUMMYFUNCTION("""COMPUTED_VALUE"""),1926) -> 1926 | G18: =IFERROR(__xludf.DUMMYFUNCTION("""COMPUTED_VALUE"""),18) -> 18 | H18: =IFERROR(__xludf.DUMMYFUNCTION("""COMPUTED_VALUE"""),24) -> 24 | I18: =IFERROR(__xludf.DUMMYFUNCTION("""COMPUTED_VALUE"""),100) -> 100 | M18: =IFERROR(__xludf.DUMMYFUNCTION("""COMPUTED_VALUE"""),0.16) -> 0.16 | N18: =IFERROR(__xludf.DUMMYFUNCTION("""COMPUTED_VALUE"""),1) -> 1 | P18: =IFERROR(__xludf.DUMMYFUNCTION("""COMPUTED_VALUE"""),"Offset") -> Offset | Q18: =IFERROR(__xludf.DUMMYFUNCTION("""COMPUTED_VALUE"""),"Packaging") -> Packaging | BC18: =IFERROR(__xludf.DUMMYFUNCTION("""COMPUTED_VALUE"""),"Packaging") -> Packaging | BD18: =IFERROR(__xludf.DUMMYFUNCTION("""COMPUTED_VALUE"""),"Carry Bag") -> Carry Bag | BS18: GreyBack | BT18: Normal | BU18: 280 GSM | BV18: =#REF! -> #REF! | CD18: =BY18 -> 0 | CE18: =CD18 -> 0
A19: =IFERROR(__xludf.DUMMYFUNCTION("""COMPUTED_VALUE"""),"https://drive.google.com/open?id=1QvJB9MhtDcXsNtKIflALdqXkVyq8VOgJ&authuser=jay.agg%40gmail.com&usp=drive_fs") -> https://drive.google.com/open?id=1QvJB9MhtDcXsNtKIflALdqXkVyq8VOgJ&authuser=jay.agg%40gmail.com&usp=drive_fs | B19: =IFERROR(__xludf.DUMMYFUNCTION("""COMPUTED_VALUE"""),"Food") -> Food | C19: =IFERROR(__xludf.DUMMYFUNCTION("""COMPUTED_VALUE"""),"Dry Fruit") -> Dry Fruit | D19: =IFERROR(__xludf.DUMMYFUNCTION("""COMPUTED_VALUE"""),"102*38*152 | 4*6*1.5 inch LB") -> 102*38*152 | 4*6*1.5 inch LB | E19: =IFERROR(__xludf.DUMMYFUNCTION("""COMPUTED_VALUE"""),4) -> 4 | F19: =IFERROR(__xludf.DUMMYFUNCTION("""COMPUTED_VALUE"""),1926) -> 1926 | G19: =IFERROR(__xludf.DUMMYFUNCTION("""COMPUTED_VALUE"""),18) -> 18 | H19: =IFERROR(__xludf.DUMMYFUNCTION("""COMPUTED_VALUE"""),23) -> 23 | I19: =IFERROR(__xludf.DUMMYFUNCTION("""COMPUTED_VALUE"""),100) -> 100 | M19: =IFERROR(__xludf.DUMMYFUNCTION("""COMPUTED_VALUE"""),0.16) -> 0.16 | N19: =IFERROR(__xludf.DUMMYFUNCTION("""COMPUTED_VALUE"""),1) -> 1 | P19: =IFERROR(__xludf.DUMMYFUNCTION("""COMPUTED_VALUE"""),"Offset") -> Offset | Q19: =IFERROR(__xludf.DUMMYFUNCTION("""COMPUTED_VALUE"""),"Packaging") -> Packaging | BC19: =IFERROR(__xludf.DUMMYFUNCTION("""COMPUTED_VALUE"""),"Packaging") -> Packaging | BD19: =IFERROR(__xludf.DUMMYFUNCTION("""COMPUTED_VALUE"""),"Cerene") -> Cerene | BS19: GreyBack | BT19: Custom | BU19: 300 GSM | BV19: =$BV$9 -> 75 | CD19: =BY19 -> 0 | CE19: =CD19 -> 0
A20: =IFERROR(__xludf.DUMMYFUNCTION("""COMPUTED_VALUE"""),"https://drive.google.com/open?id=1Qvbr4-fdTQ4l4YcjYooE-rNrrYyvW8zx&authuser=jay.agg%40gmail.com&usp=drive_fs") -> https://drive.google.com/open?id=1Qvbr4-fdTQ4l4YcjYooE-rNrrYyvW8zx&authuser=jay.agg%40gmail.com&usp=drive_fs | B20: =IFERROR(__xludf.DUMMYFUNCTION("""COMPUTED_VALUE"""),"Food") -> Food | C20: =IFERROR(__xludf.DUMMYFUNCTION("""COMPUTED_VALUE"""),"Dry Fruit") -> Dry Fruit | D20: =IFERROR(__xludf.DUMMYFUNCTION("""COMPUTED_VALUE"""),"127*38*203 mm | 5*8*1.5 inch LB") -> 127*38*203 mm | 5*8*1.5 inch LB | E20: =IFERROR(__xludf.DUMMYFUNCTION("""COMPUTED_VALUE"""),2) -> 2 | F20: =IFERROR(__xludf.DUMMYFUNCTION("""COMPUTED_VALUE"""),1926) -> 1926 | G20: =IFERROR(__xludf.DUMMYFUNCTION("""COMPUTED_VALUE"""),14) -> 14 | H20: =IFERROR(__xludf.DUMMYFUNCTION("""COMPUTED_VALUE"""),22) -> 22 | I20: =IFERROR(__xludf.DUMMYFUNCTION("""COMPUTED_VALUE"""),100) -> 100 | M20: =IFERROR(__xludf.DUMMYFUNCTION("""COMPUTED_VALUE"""),0.16) -> 0.16 | N20: =IFERROR(__xludf.DUMMYFUNCTION("""COMPUTED_VALUE"""),1) -> 1 | P20: =IFERROR(__xludf.DUMMYFUNCTION("""COMPUTED_VALUE"""),"Offset") -> Offset | Q20: =IFERROR(__xludf.DUMMYFUNCTION("""COMPUTED_VALUE"""),"Packaging") -> Packaging | BC20: =IFERROR(__xludf.DUMMYFUNCTION("""COMPUTED_VALUE"""),"Packaging") -> Packaging | BD20: =IFERROR(__xludf.DUMMYFUNCTION("""COMPUTED_VALUE"""),"Computer Accessories") -> Computer Accessories | BS20: GreyBack | BT20: Custom | BU20: 330 GSM | BV20: =$BV$9 -> 75 | CD20: =BY20 -> 0 | CE20: =CD20 -> 0
A21: =IFERROR(__xludf.DUMMYFUNCTION("""COMPUTED_VALUE"""),"https://drive.google.com/open?id=1Qwbp_CBztdhd4Oo6pQJ3VR0q6w7viL0j&authuser=jay.agg%40gmail.com&usp=drive_fs") -> https://drive.google.com/open?id=1Qwbp_CBztdhd4Oo6pQJ3VR0q6w7viL0j&authuser=jay.agg%40gmail.com&usp=drive_fs | B21: =IFERROR(__xludf.DUMMYFUNCTION("""COMPUTED_VALUE"""),"Food") -> Food | C21: =IFERROR(__xludf.DUMMYFUNCTION("""COMPUTED_VALUE"""),"Dry Fruit") -> Dry Fruit | D21: =IFERROR(__xludf.DUMMYFUNCTION("""COMPUTED_VALUE"""),"140*38*216 mm | 5.5*8.5*1.5 inch LB") -> 140*38*216 mm | 5.5*8.5*1.5 inch LB | E21: =IFERROR(__xludf.DUMMYFUNCTION("""COMPUTED_VALUE"""),2) -> 2 | F21: =IFERROR(__xludf.DUMMYFUNCTION("""COMPUTED_VALUE"""),1926) -> 1926 | G21: =IFERROR(__xludf.DUMMYFUNCTION("""COMPUTED_VALUE"""),15) -> 15 | H21: =IFERROR(__xludf.DUMMYFUNCTION("""COMPUTED_VALUE"""),25) -> 25 | I21: =IFERROR(__xludf.DUMMYFUNCTION("""COMPUTED_VALUE"""),100) -> 100 | M21: =IFERROR(__xludf.DUMMYFUNCTION("""COMPUTED_VALUE"""),0.16) -> 0.16 | N21: =IFERROR(__xludf.DUMMYFUNCTION("""COMPUTED_VALUE"""),1) -> 1 | P21: =IFERROR(__xludf.DUMMYFUNCTION("""COMPUTED_VALUE"""),"Offset") -> Offset | Q21: =IFERROR(__xludf.DUMMYFUNCTION("""COMPUTED_VALUE"""),"Packaging") -> Packaging | BC21: =IFERROR(__xludf.DUMMYFUNCTION("""COMPUTED_VALUE"""),"Packaging") -> Packaging | BD21: =IFERROR(__xludf.DUMMYFUNCTION("""COMPUTED_VALUE"""),"Cones") -> Cones | BS21: GreyBack | BT21: Custom | BU21: 350 GSM | BV21: =$BV$9 -> 75 | CD21: =BY21 -> 0 | CE21: =CD21 -> 0
A22: =IFERROR(__xludf.DUMMYFUNCTION("""COMPUTED_VALUE"""),"https://drive.google.com/open?id=1R0wA1QXQbAwYILUJUKO7z4Ci3IcHThXO&authuser=jay.agg%40gmail.com&usp=drive_fs") -> https://drive.google.com/open?id=1R0wA1QXQbAwYILUJUKO7z4Ci3IcHThXO&authuser=jay.agg%40gmail.com&usp=drive_fs | B22: =IFERROR(__xludf.DUMMYFUNCTION("""COMPUTED_VALUE"""),"Food") -> Food | C22: =IFERROR(__xludf.DUMMYFUNCTION("""COMPUTED_VALUE"""),"Dry Fruit") -> Dry Fruit | D22: =IFERROR(__xludf.DUMMYFUNCTION("""COMPUTED_VALUE"""),"100gram 4*1.5*5 inch LB") -> 100gram 4*1.5*5 inch LB | E22: =IFERROR(__xludf.DUMMYFUNCTION("""COMPUTED_VALUE"""),4) -> 4 | F22: =IFERROR(__xludf.DUMMYFUNCTION("""COMPUTED_VALUE"""),1926) -> 1926 | G22: =IFERROR(__xludf.DUMMYFUNCTION("""COMPUTED_VALUE"""),15) -> 15 | H22: =IFERROR(__xludf.DUMMYFUNCTION("""COMPUTED_VALUE"""),25) -> 25 | I22: =IFERROR(__xludf.DUMMYFUNCTION("""COMPUTED_VALUE"""),100) -> 100 | L22: =IFERROR(__xludf.DUMMYFUNCTION("""COMPUTED_VALUE"""),1) -> 1 | M22: =IFERROR(__xludf.DUMMYFUNCTION("""COMPUTED_VALUE"""),0.16) -> 0.16 | N22: =IFERROR(__xludf.DUMMYFUNCTION("""COMPUTED_VALUE"""),1) -> 1 | P22: =IFERROR(__xludf.DUMMYFUNCTION("""COMPUTED_VALUE"""),"Offset") -> Offset | Q22: =IFERROR(__xludf.DUMMYFUNCTION("""COMPUTED_VALUE"""),"Packaging") -> Packaging | BC22: =IFERROR(__xludf.DUMMYFUNCTION("""COMPUTED_VALUE"""),"Packaging") -> Packaging | BD22: =IFERROR(__xludf.DUMMYFUNCTION("""COMPUTED_VALUE"""),"Corrugation") -> Corrugation | BS22: Maplitho | BT22: Normal | BU22: 65 GSM | BV22: =#REF! -> #REF! | CD22: =BY22 -> 0 | CE22: =CD22 -> 0
A23: =IFERROR(__xludf.DUMMYFUNCTION("""COMPUTED_VALUE"""),"https://drive.google.com/open?id=1R61V6cd_s3Pq01sfSW5K3t7WSGP_L0As&authuser=jay.agg%40gmail.com&usp=drive_fs") -> https://drive.google.com/open?id=1R61V6cd_s3Pq01sfSW5K3t7WSGP_L0As&authuser=jay.agg%40gmail.com&usp=drive_fs | B23: =IFERROR(__xludf.DUMMYFUNCTION("""COMPUTED_VALUE"""),"Food") -> Food | C23: =IFERROR(__xludf.DUMMYFUNCTION("""COMPUTED_VALUE"""),"Dry Fruit") -> Dry Fruit | D23: =IFERROR(__xludf.DUMMYFUNCTION("""COMPUTED_VALUE"""),"200gram 4.5*1.5*7 inch LB") -> 200gram 4.5*1.5*7 inch LB | E23: =IFERROR(__xludf.DUMMYFUNCTION("""COMPUTED_VALUE"""),4) -> 4 | F23: =IFERROR(__xludf.DUMMYFUNCTION("""COMPUTED_VALUE"""),1926) -> 1926 | G23: =IFERROR(__xludf.DUMMYFUNCTION("""COMPUTED_VALUE"""),19) -> 19 | H23: =IFERROR(__xludf.DUMMYFUNCTION("""COMPUTED_VALUE"""),26) -> 26 | I23: =IFERROR(__xludf.DUMMYFUNCTION("""COMPUTED_VALUE"""),100) -> 100 | L23: =IFERROR(__xludf.DUMMYFUNCTION("""COMPUTED_VALUE"""),1) -> 1 | M23: =IFERROR(__xludf.DUMMYFUNCTION("""COMPUTED_VALUE"""),0.16) -> 0.16 | N23: =IFERROR(__xludf.DUMMYFUNCTION("""COMPUTED_VALUE"""),1) -> 1 | P23: =IFERROR(__xludf.DUMMYFUNCTION("""COMPUTED_VALUE"""),"Offset") -> Offset | Q23: =IFERROR(__xludf.DUMMYFUNCTION("""COMPUTED_VALUE"""),"Packaging") -> Packaging | BC23: =IFERROR(__xludf.DUMMYFUNCTION("""COMPUTED_VALUE"""),"Packaging") -> Packaging | BD23: =IFERROR(__xludf.DUMMYFUNCTION("""COMPUTED_VALUE"""),"Cosmetic") -> Cosmetic | BS23: Maplitho | BT23: Custom | BU23: 80 GSM | BV23: =Quotation!$C$21 -> 0 | CD23: =BY23 -> 0 | CE23: =CD23 -> 0
A24: =IFERROR(__xludf.DUMMYFUNCTION("""COMPUTED_VALUE"""),"https://drive.google.com/open?id=1R69JTM091j0R6Hbk7JlIcmy1o0TJXQlC&authuser=jay.agg%40gmail.com&usp=drive_fs") -> https://drive.google.com/open?id=1R69JTM091j0R6Hbk7JlIcmy1o0TJXQlC&authuser=jay.agg%40gmail.com&usp=drive_fs | B24: =IFERROR(__xludf.DUMMYFUNCTION("""COMPUTED_VALUE"""),"Food") -> Food | C24: =IFERROR(__xludf.DUMMYFUNCTION("""COMPUTED_VALUE"""),"Dry Fruit") -> Dry Fruit | D24: =IFERROR(__xludf.DUMMYFUNCTION("""COMPUTED_VALUE"""),"250gram 5*1.5*7 inch LB") -> 250gram 5*1.5*7 inch LB | E24: =IFERROR(__xludf.DUMMYFUNCTION("""COMPUTED_VALUE"""),2) -> 2 | F24: =IFERROR(__xludf.DUMMYFUNCTION("""COMPUTED_VALUE"""),1926) -> 1926 | G24: =IFERROR(__xludf.DUMMYFUNCTION("""COMPUTED_VALUE"""),14) -> 14 | H24: =IFERROR(__xludf.DUMMYFUNCTION("""COMPUTED_VALUE"""),19) -> 19 | I24: =IFERROR(__xludf.DUMMYFUNCTION("""COMPUTED_VALUE"""),100) -> 100 | L24: =IFERROR(__xludf.DUMMYFUNCTION("""COMPUTED_VALUE"""),1) -> 1 | M24: =IFERROR(__xludf.DUMMYFUNCTION("""COMPUTED_VALUE"""),0.16) -> 0.16 | N24: =IFERROR(__xludf.DUMMYFUNCTION("""COMPUTED_VALUE"""),1) -> 1 | P24: =IFERROR(__xludf.DUMMYFUNCTION("""COMPUTED_VALUE"""),"Offset") -> Offset | Q24: =IFERROR(__xludf.DUMMYFUNCTION("""COMPUTED_VALUE"""),"Packaging") -> Packaging | BC24: =IFERROR(__xludf.DUMMYFUNCTION("""COMPUTED_VALUE"""),"Packaging") -> Packaging | BD24: =IFERROR(__xludf.DUMMYFUNCTION("""COMPUTED_VALUE"""),"Cup") -> Cup | BS24: Maplitho | BT24: Normal | BU24: 90 GSM | BV24: =$BV$22 -> #REF! | CD24: =BY24 -> 0 | CE24: =CD24 -> 0
A25: =IFERROR(__xludf.DUMMYFUNCTION("""COMPUTED_VALUE"""),"https://drive.google.com/open?id=1QTWTuFZk9eNr_4lY0kX3TKgeYtsriRPs&authuser=jay.agg%40gmail.com&usp=drive_fs") -> https://drive.google.com/open?id=1QTWTuFZk9eNr_4lY0kX3TKgeYtsriRPs&authuser=jay.agg%40gmail.com&usp=drive_fs | B25: =IFERROR(__xludf.DUMMYFUNCTION("""COMPUTED_VALUE"""),"Food") -> Food | C25: =IFERROR(__xludf.DUMMYFUNCTION("""COMPUTED_VALUE"""),"Fast Food") -> Fast Food | D25: =IFERROR(__xludf.DUMMYFUNCTION("""COMPUTED_VALUE"""),"8*7*2 inch") -> 8*7*2 inch | E25: =IFERROR(__xludf.DUMMYFUNCTION("""COMPUTED_VALUE"""),1) -> 1 | F25: =IFERROR(__xludf.DUMMYFUNCTION("""COMPUTED_VALUE"""),1926) -> 1926 | G25: =IFERROR(__xludf.DUMMYFUNCTION("""COMPUTED_VALUE"""),18) -> 18 | H25: =IFERROR(__xludf.DUMMYFUNCTION("""COMPUTED_VALUE"""),19) -> 19 | I25: =IFERROR(__xludf.DUMMYFUNCTION("""COMPUTED_VALUE"""),100) -> 100 | N25: =IFERROR(__xludf.DUMMYFUNCTION("""COMPUTED_VALUE"""),1) -> 1 | P25: =IFERROR(__xludf.DUMMYFUNCTION("""COMPUTED_VALUE"""),"Offset") -> Offset | Q25: =IFERROR(__xludf.DUMMYFUNCTION("""COMPUTED_VALUE"""),"Packaging") -> Packaging | BC25: =IFERROR(__xludf.DUMMYFUNCTION("""COMPUTED_VALUE"""),"Packaging") -> Packaging | BD25: =IFERROR(__xludf.DUMMYFUNCTION("""COMPUTED_VALUE"""),"Daily Essential") -> Daily Essential | BS25: Maplitho | BT25: Normal | BU25: 100 GSM | BV25: =$BV$22 -> #REF! | CD25: =BY25 -> 0 | CE25: =CD25 -> 0
A26: =IFERROR(__xludf.DUMMYFUNCTION("""COMPUTED_VALUE"""),"https://drive.google.com/open?id=1QhZ36zVV0AY4GNL7jcG9woN0_jfH4vH2&authuser=jay.agg%40gmail.com&usp=drive_fs") -> https://drive.google.com/open?id=1QhZ36zVV0AY4GNL7jcG9woN0_jfH4vH2&authuser=jay.agg%40gmail.com&usp=drive_fs | B26: =IFERROR(__xludf.DUMMYFUNCTION("""COMPUTED_VALUE"""),"Food") -> Food | C26: =IFERROR(__xludf.DUMMYFUNCTION("""COMPUTED_VALUE"""),"Fast Food") -> Fast Food | D26: =IFERROR(__xludf.DUMMYFUNCTION("""COMPUTED_VALUE"""),"5*5*4.5 inch") -> 5*5*4.5 inch | E26: =IFERROR(__xludf.DUMMYFUNCTION("""COMPUTED_VALUE"""),2) -> 2 | F26: =IFERROR(__xludf.DUMMYFUNCTION("""COMPUTED_VALUE"""),1926) -> 1926 | G26: =IFERROR(__xludf.DUMMYFUNCTION("""COMPUTED_VALUE"""),19.5) -> 19.5 | H26: =IFERROR(__xludf.DUMMYFUNCTION("""COMPUTED_VALUE"""),23) -> 23 | I26: =IFERROR(__xludf.DUMMYFUNCTION("""COMPUTED_VALUE"""),100) -> 100 | N26: =IFERROR(__xludf.DUMMYFUNCTION("""COMPUTED_VALUE"""),1) -> 1 | P26: =IFERROR(__xludf.DUMMYFUNCTION("""COMPUTED_VALUE"""),"Offset") -> Offset | Q26: =IFERROR(__xludf.DUMMYFUNCTION("""COMPUTED_VALUE"""),"Packaging") -> Packaging | BC26: =IFERROR(__xludf.DUMMYFUNCTION("""COMPUTED_VALUE"""),"Packaging") -> Packaging | BD26: =IFERROR(__xludf.DUMMYFUNCTION("""COMPUTED_VALUE"""),"Dhoop") -> Dhoop | BS26: Maplitho | BT26: Normal | BU26: 110 GSM | BV26: =$BV$22 -> #REF! | CD26: =BY26 -> 0 | CE26: =CD26 -> 0
A27: =IFERROR(__xludf.DUMMYFUNCTION("""COMPUTED_VALUE"""),"https://drive.google.com/open?id=1Qhw5hCt6AslPxvpSURfZvOXwooNNK0lB&authuser=jay.agg%40gmail.com&usp=drive_fs") -> https://drive.google.com/open?id=1Qhw5hCt6AslPxvpSURfZvOXwooNNK0lB&authuser=jay.agg%40gmail.com&usp=drive_fs | B27: =IFERROR(__xludf.DUMMYFUNCTION("""COMPUTED_VALUE"""),"Food") -> Food | C27: =IFERROR(__xludf.DUMMYFUNCTION("""COMPUTED_VALUE"""),"Fast Food") -> Fast Food | D27: =IFERROR(__xludf.DUMMYFUNCTION("""COMPUTED_VALUE"""),"100*150*45 mm") -> 100*150*45 mm | E27: =IFERROR(__xludf.DUMMYFUNCTION("""COMPUTED_VALUE"""),2) -> 2 | F27: =IFERROR(__xludf.DUMMYFUNCTION("""COMPUTED_VALUE"""),1926) -> 1926 | G27: =IFERROR(__xludf.DUMMYFUNCTION("""COMPUTED_VALUE"""),15) -> 15 | H27: =IFERROR(__xludf.DUMMYFUNCTION("""COMPUTED_VALUE"""),20) -> 20 | I27: =IFERROR(__xludf.DUMMYFUNCTION("""COMPUTED_VALUE"""),100) -> 100 | N27: =IFERROR(__xludf.DUMMYFUNCTION("""COMPUTED_VALUE"""),1) -> 1 | P27: =IFERROR(__xludf.DUMMYFUNCTION("""COMPUTED_VALUE"""),"Offset") -> Offset | Q27: =IFERROR(__xludf.DUMMYFUNCTION("""COMPUTED_VALUE"""),"Packaging") -> Packaging | BC27: =IFERROR(__xludf.DUMMYFUNCTION("""COMPUTED_VALUE"""),"Packaging") -> Packaging | BD27: =IFERROR(__xludf.DUMMYFUNCTION("""COMPUTED_VALUE"""),"Dude Love") -> Dude Love | BS27: Maplitho | BT27: Normal | BU27: 130 GSM | BV27: =$BV$22 -> #REF! | CD27: =BY27 -> 0 | CE27: =CD27 -> 0
A28: =IFERROR(__xludf.DUMMYFUNCTION("""COMPUTED_VALUE"""),"https://drive.google.com/open?id=1QUlYw3yWCJ5eG6Uy83i49XImWyIv8ly_&authuser=jay.agg%40gmail.com&usp=drive_fs") -> https://drive.google.com/open?id=1QUlYw3yWCJ5eG6Uy83i49XImWyIv8ly_&authuser=jay.agg%40gmail.com&usp=drive_fs | B28: =IFERROR(__xludf.DUMMYFUNCTION("""COMPUTED_VALUE"""),"Food") -> Food | C28: =IFERROR(__xludf.DUMMYFUNCTION("""COMPUTED_VALUE"""),"Khakra") -> Khakra | D28: =IFERROR(__xludf.DUMMYFUNCTION("""COMPUTED_VALUE"""),"220*220*30 mm") -> 220*220*30 mm | E28: =IFERROR(__xludf.DUMMYFUNCTION("""COMPUTED_VALUE"""),1) -> 1 | F28: =IFERROR(__xludf.DUMMYFUNCTION("""COMPUTED_VALUE"""),1926) -> 1926 | G28: =IFERROR(__xludf.DUMMYFUNCTION("""COMPUTED_VALUE"""),13) -> 13 | H28: =IFERROR(__xludf.DUMMYFUNCTION("""COMPUTED_VALUE"""),21) -> 21 | I28: =IFERROR(__xludf.DUMMYFUNCTION("""COMPUTED_VALUE"""),100) -> 100 | M28: =IFERROR(__xludf.DUMMYFUNCTION("""COMPUTED_VALUE"""),0.1) -> 0.1 | N28: =IFERROR(__xludf.DUMMYFUNCTION("""COMPUTED_VALUE"""),1) -> 1 | P28: =IFERROR(__xludf.DUMMYFUNCTION("""COMPUTED_VALUE"""),"Offset") -> Offset | Q28: =IFERROR(__xludf.DUMMYFUNCTION("""COMPUTED_VALUE"""),"Packaging") -> Packaging | BC28: =IFERROR(__xludf.DUMMYFUNCTION("""COMPUTED_VALUE"""),"Packaging") -> Packaging | BD28: =IFERROR(__xludf.DUMMYFUNCTION("""COMPUTED_VALUE"""),"Electricity") -> Electricity | BS28: Maplitho | BT28: Normal | BU28: 150 GSM | BV28: =$BV$22 -> #REF! | CD28: =BY28 -> 0 | CE28: =CD28 -> 0
A29: =IFERROR(__xludf.DUMMYFUNCTION("""COMPUTED_VALUE"""),"https://drive.google.com/open?id=1QRiCFXEjTTmENEZKNbx8VjC2NioVX2p8&authuser=jay.agg%40gmail.com&usp=drive_fs") -> https://drive.google.com/open?id=1QRiCFXEjTTmENEZKNbx8VjC2NioVX2p8&authuser=jay.agg%40gmail.com&usp=drive_fs | B29: =IFERROR(__xludf.DUMMYFUNCTION("""COMPUTED_VALUE"""),"Food") -> Food | C29: =IFERROR(__xludf.DUMMYFUNCTION("""COMPUTED_VALUE"""),"Walnut") -> Walnut | D29: =IFERROR(__xludf.DUMMYFUNCTION("""COMPUTED_VALUE"""),"24*46*161 mm") -> 24*46*161 mm | E29: =IFERROR(__xludf.DUMMYFUNCTION("""COMPUTED_VALUE"""),9) -> 9 | F29: =IFERROR(__xludf.DUMMYFUNCTION("""COMPUTED_VALUE"""),1926) -> 1926 | G29: =IFERROR(__xludf.DUMMYFUNCTION("""COMPUTED_VALUE"""),19) -> 19 | H29: =IFERROR(__xludf.DUMMYFUNCTION("""COMPUTED_VALUE"""),26) -> 26 | I29: =IFERROR(__xludf.DUMMYFUNCTION("""COMPUTED_VALUE"""),100) -> 100 | M29: =IFERROR(__xludf.DUMMYFUNCTION("""COMPUTED_VALUE"""),0.1) -> 0.1 | N29: =IFERROR(__xludf.DUMMYFUNCTION("""COMPUTED_VALUE"""),1) -> 1 | P29: =IFERROR(__xludf.DUMMYFUNCTION("""COMPUTED_VALUE"""),"Offset") -> Offset | Q29: =IFERROR(__xludf.DUMMYFUNCTION("""COMPUTED_VALUE"""),"Packaging") -> Packaging | BC29: =IFERROR(__xludf.DUMMYFUNCTION("""COMPUTED_VALUE"""),"Packaging") -> Packaging | BD29: =IFERROR(__xludf.DUMMYFUNCTION("""COMPUTED_VALUE"""),"Everstylish") -> Everstylish | CD29: =BY29 -> 0 | CE29: =CD29 -> 0
A30: =IFERROR(__xludf.DUMMYFUNCTION("""COMPUTED_VALUE"""),"https://drive.google.com/open?id=1QQdUxmlDOPkf9Hsc7uKFwvH0Xou6f57E&authuser=jay.agg%40gmail.com&usp=drive_fs") -> https://drive.google.com/open?id=1QQdUxmlDOPkf9Hsc7uKFwvH0Xou6f57E&authuser=jay.agg%40gmail.com&usp=drive_fs | B30: =IFERROR(__xludf.DUMMYFUNCTION("""COMPUTED_VALUE"""),"Food") -> Food | C30: =IFERROR(__xludf.DUMMYFUNCTION("""COMPUTED_VALUE"""),"Chocolate") -> Chocolate | D30: =IFERROR(__xludf.DUMMYFUNCTION("""COMPUTED_VALUE"""),"50*50*100 mm") -> 50*50*100 mm | E30: =IFERROR(__xludf.DUMMYFUNCTION("""COMPUTED_VALUE"""),6) -> 6 | F30: =IFERROR(__xludf.DUMMYFUNCTION("""COMPUTED_VALUE"""),1926) -> 1926 | G30: =IFERROR(__xludf.DUMMYFUNCTION("""COMPUTED_VALUE"""),18) -> 18 | H30: =IFERROR(__xludf.DUMMYFUNCTION("""COMPUTED_VALUE"""),25) -> 25 | I30: =IFERROR(__xludf.DUMMYFUNCTION("""COMPUTED_VALUE"""),100) -> 100 | M30: =IFERROR(__xludf.DUMMYFUNCTION("""COMPUTED_VALUE"""),0.1) -> 0.1 | N30: =IFERROR(__xludf.DUMMYFUNCTION("""COMPUTED_VALUE"""),1) -> 1 | P30: =IFERROR(__xludf.DUMMYFUNCTION("""COMPUTED_VALUE"""),"Offset") -> Offset | Q30: =IFERROR(__xludf.DUMMYFUNCTION("""COMPUTED_VALUE"""),"Packaging") -> Packaging | BC30: =IFERROR(__xludf.DUMMYFUNCTION("""COMPUTED_VALUE"""),"Packaging") -> Packaging | BD30: =IFERROR(__xludf.DUMMYFUNCTION("""COMPUTED_VALUE"""),"FMCG") -> FMCG | CD30: =BY30 -> 0 | CE30: =CD30 -> 0
A31: =IFERROR(__xludf.DUMMYFUNCTION("""COMPUTED_VALUE"""),"https://drive.google.com/open?id=1QtXn0evE-9VW4-ZQJmVDufU_5NTVKUY6&authuser=jay.agg%40gmail.com&usp=drive_fs") -> https://drive.google.com/open?id=1QtXn0evE-9VW4-ZQJmVDufU_5NTVKUY6&authuser=jay.agg%40gmail.com&usp=drive_fs | B31: =IFERROR(__xludf.DUMMYFUNCTION("""COMPUTED_VALUE"""),"Food") -> Food | C31: =IFERROR(__xludf.DUMMYFUNCTION("""COMPUTED_VALUE"""),"Butter") -> Butter | D31: =IFERROR(__xludf.DUMMYFUNCTION("""COMPUTED_VALUE"""),"70*63*130 mm") -> 70*63*130 mm | E31: =IFERROR(__xludf.DUMMYFUNCTION("""COMPUTED_VALUE"""),2) -> 2 | F31: =IFERROR(__xludf.DUMMYFUNCTION("""COMPUTED_VALUE"""),1926) -> 1926 | G31: =IFERROR(__xludf.DUMMYFUNCTION("""COMPUTED_VALUE"""),12) -> 12 | H31: =IFERROR(__xludf.DUMMYFUNCTION("""COMPUTED_VALUE"""),21) -> 21 | I31: =IFERROR(__xludf.DUMMYFUNCTION("""COMPUTED_VALUE"""),100) -> 100 | M31: =IFERROR(__xludf.DUMMYFUNCTION("""COMPUTED_VALUE"""),0.1) -> 0.1 | N31: =IFERROR(__xludf.DUMMYFUNCTION("""COMPUTED_VALUE"""),1) -> 1 | P31: =IFERROR(__xludf.DUMMYFUNCTION("""COMPUTED_VALUE"""),"Offset") -> Offset | Q31: =IFERROR(__xludf.DUMMYFUNCTION("""COMPUTED_VALUE"""),"Packaging") -> Packaging | BC31: =IFERROR(__xludf.DUMMYFUNCTION("""COMPUTED_VALUE"""),"Packaging") -> Packaging | BD31: =IFERROR(__xludf.DUMMYFUNCTION("""COMPUTED_VALUE"""),"Food") -> Food | BS31: Art Card | BT31: Normal | BU31: 90 GSM | BV31: =#REF! -> #REF! | CD31: =BY31 -> 0 | CE31: =CD31 -> 0
A32: =IFERROR(__xludf.DUMMYFUNCTION("""COMPUTED_VALUE"""),"https://drive.google.com/open?id=1j2Ak7n2uIi0WIIJrDAWZ9xkRCHIeqUHe&authuser=jay.agg%40gmail.com&usp=drive_fs") -> https://drive.google.com/open?id=1j2Ak7n2uIi0WIIJrDAWZ9xkRCHIeqUHe&authuser=jay.agg%40gmail.com&usp=drive_fs | B32: =IFERROR(__xludf.DUMMYFUNCTION("""COMPUTED_VALUE"""),"Food") -> Food | C32: =IFERROR(__xludf.DUMMYFUNCTION("""COMPUTED_VALUE"""),"Fast Food") -> Fast Food | D32: =IFERROR(__xludf.DUMMYFUNCTION("""COMPUTED_VALUE"""),"Sleeve 5.25*3.25*2.25 inch") -> Sleeve 5.25*3.25*2.25 inch | E32: =IFERROR(__xludf.DUMMYFUNCTION("""COMPUTED_VALUE"""),6) -> 6 | F32: =IFERROR(__xludf.DUMMYFUNCTION("""COMPUTED_VALUE"""),1926) -> 1926 | G32: =IFERROR(__xludf.DUMMYFUNCTION("""COMPUTED_VALUE"""),18) -> 18 | H32: =IFERROR(__xludf.DUMMYFUNCTION("""COMPUTED_VALUE"""),23) -> 23 | I32: =IFERROR(__xludf.DUMMYFUNCTION("""COMPUTED_VALUE"""),100) -> 100 | M32: =IFERROR(__xludf.DUMMYFUNCTION("""COMPUTED_VALUE"""),0.1) -> 0.1 | N32: =IFERROR(__xludf.DUMMYFUNCTION("""COMPUTED_VALUE"""),1) -> 1 | P32: =IFERROR(__xludf.DUMMYFUNCTION("""COMPUTED_VALUE"""),"Offset") -> Offset | Q32: =IFERROR(__xludf.DUMMYFUNCTION("""COMPUTED_VALUE"""),"Packaging") -> Packaging | BC32: =IFERROR(__xludf.DUMMYFUNCTION("""COMPUTED_VALUE"""),"Packaging") -> Packaging | BD32: =IFERROR(__xludf.DUMMYFUNCTION("""COMPUTED_VALUE"""),"Fratelli") -> Fratelli | BS32: Art Card | BT32: Normal | BU32: 100 GSM | BV32: =#REF! -> #REF! | CD32: =BY32 -> 0 | CE32: =CD32 -> 0
A33: =IFERROR(__xludf.DUMMYFUNCTION("""COMPUTED_VALUE"""),"https://drive.google.com/open?id=1jIKxVpMBt0sYXYuHJ9pjoEVFnOlIpxpb&authuser=jay.agg%40gmail.com&usp=drive_fs") -> https://drive.google.com/open?id=1jIKxVpMBt0sYXYuHJ9pjoEVFnOlIpxpb&authuser=jay.agg%40gmail.com&usp=drive_fs | B33: =IFERROR(__xludf.DUMMYFUNCTION("""COMPUTED_VALUE"""),"Food") -> Food | C33: =IFERROR(__xludf.DUMMYFUNCTION("""COMPUTED_VALUE"""),"Fast Food") -> Fast Food | D33: =IFERROR(__xludf.DUMMYFUNCTION("""COMPUTED_VALUE"""),"9.375*3.75*2 inch") -> 9.375*3.75*2 inch | E33: =IFERROR(__xludf.DUMMYFUNCTION("""COMPUTED_VALUE"""),2) -> 2 | F33: =IFERROR(__xludf.DUMMYFUNCTION("""COMPUTED_VALUE"""),1926) -> 1926 | G33: =IFERROR(__xludf.DUMMYFUNCTION("""COMPUTED_VALUE"""),18) -> 18 | H33: =IFERROR(__xludf.DUMMYFUNCTION("""COMPUTED_VALUE"""),25) -> 25 | I33: =IFERROR(__xludf.DUMMYFUNCTION("""COMPUTED_VALUE"""),100) -> 100 | N33: =IFERROR(__xludf.DUMMYFUNCTION("""COMPUTED_VALUE"""),1) -> 1 | P33: =IFERROR(__xludf.DUMMYFUNCTION("""COMPUTED_VALUE"""),"Offset") -> Offset | Q33: =IFERROR(__xludf.DUMMYFUNCTION("""COMPUTED_VALUE"""),"Packaging") -> Packaging | BC33: =IFERROR(__xludf.DUMMYFUNCTION("""COMPUTED_VALUE"""),"Packaging") -> Packaging | BD33: =IFERROR(__xludf.DUMMYFUNCTION("""COMPUTED_VALUE"""),"Games") -> Games | BS33: Art Card | BT33: Normal | BU33: 110 GSM | BV33: =#REF! -> #REF! | CD33: =BY33 -> 0 | CE33: =CD33 -> 0
A34: =IFERROR(__xludf.DUMMYFUNCTION("""COMPUTED_VALUE"""),"https://drive.google.com/open?id=1jPGlPvth33ow0BsuXPn_9Fd0aGa4tOR5&authuser=jay.agg%40gmail.com&usp=drive_fs") -> https://drive.google.com/open?id=1jPGlPvth33ow0BsuXPn_9Fd0aGa4tOR5&authuser=jay.agg%40gmail.com&usp=drive_fs | B34: =IFERROR(__xludf.DUMMYFUNCTION("""COMPUTED_VALUE"""),"Food") -> Food | C34: =IFERROR(__xludf.DUMMYFUNCTION("""COMPUTED_VALUE"""),"Fast Food") -> Fast Food | D34: =IFERROR(__xludf.DUMMYFUNCTION("""COMPUTED_VALUE"""),"Momos 5.25*3.25*2.25 inch") -> Momos 5.25*3.25*2.25 inch | E34: =IFERROR(__xludf.DUMMYFUNCTION("""COMPUTED_VALUE"""),2) -> 2 | F34: =IFERROR(__xludf.DUMMYFUNCTION("""COMPUTED_VALUE"""),1926) -> 1926 | G34: =IFERROR(__xludf.DUMMYFUNCTION("""COMPUTED_VALUE"""),15) -> 15 | H34: =IFERROR(__xludf.DUMMYFUNCTION("""COMPUTED_VALUE"""),25) -> 25 | I34: =IFERROR(__xludf.DUMMYFUNCTION("""COMPUTED_VALUE"""),100) -> 100 | N34: =IFERROR(__xludf.DUMMYFUNCTION("""COMPUTED_VALUE"""),1) -> 1 | P34: =IFERROR(__xludf.DUMMYFUNCTION("""COMPUTED_VALUE"""),"Offset") -> Offset | Q34: =IFERROR(__xludf.DUMMYFUNCTION("""COMPUTED_VALUE"""),"Packaging") -> Packaging | BC34: =IFERROR(__xludf.DUMMYFUNCTION("""COMPUTED_VALUE"""),"Packaging") -> Packaging | BD34: =IFERROR(__xludf.DUMMYFUNCTION("""COMPUTED_VALUE"""),"Gugal Loban Cup") -> Gugal Loban Cup | BS34: Art Card | BT34: Normal | BU34: 130 GSM | BV34: =#REF! -> #REF! | CD34: =BY34 -> 0 | CE34: =CD34 -> 0
A35: =IFERROR(__xludf.DUMMYFUNCTION("""COMPUTED_VALUE"""),"https://drive.google.com/open?id=1jPSj61Xjqqhp0yAUgpJijU3oteatln8h&authuser=jay.agg%40gmail.com&usp=drive_fs") -> https://drive.google.com/open?id=1jPSj61Xjqqhp0yAUgpJijU3oteatln8h&authuser=jay.agg%40gmail.com&usp=drive_fs | B35: =IFERROR(__xludf.DUMMYFUNCTION("""COMPUTED_VALUE"""),"Food") -> Food | C35: =IFERROR(__xludf.DUMMYFUNCTION("""COMPUTED_VALUE"""),"Fast Food") -> Fast Food | D35: =IFERROR(__xludf.DUMMYFUNCTION("""COMPUTED_VALUE"""),"Kathi Roll 55*55*230 mm LB") -> Kathi Roll 55*55*230 mm LB | E35: =IFERROR(__xludf.DUMMYFUNCTION("""COMPUTED_VALUE"""),4) -> 4 | F35: =IFERROR(__xludf.DUMMYFUNCTION("""COMPUTED_VALUE"""),1926) -> 1926 | G35: =IFERROR(__xludf.DUMMYFUNCTION("""COMPUTED_VALUE"""),19) -> 19 | H35: =IFERROR(__xludf.DUMMYFUNCTION("""COMPUTED_VALUE"""),26) -> 26 | I35: =IFERROR(__xludf.DUMMYFUNCTION("""COMPUTED_VALUE"""),100) -> 100 | M35: =IFERROR(__xludf.DUMMYFUNCTION("""COMPUTED_VALUE"""),0.4) -> 0.4 | N35: =IFERROR(__xludf.DUMMYFUNCTION("""COMPUTED_VALUE"""),1) -> 1 | P35: =IFERROR(__xludf.DUMMYFUNCTION("""COMPUTED_VALUE"""),"Offset") -> Offset | Q35: =IFERROR(__xludf.DUMMYFUNCTION("""COMPUTED_VALUE"""),"Packaging") -> Packaging | BC35: =IFERROR(__xludf.DUMMYFUNCTION("""COMPUTED_VALUE"""),"Packaging") -> Packaging | BD35: =IFERROR(__xludf.DUMMYFUNCTION("""COMPUTED_VALUE"""),"Hard Bound") -> Hard Bound | BS35: Art Card | BT35: Normal | BU35: 150 GSM | BV35: =#REF! -> #REF! | CD35: =BY35 -> 0 | CE35: =CD35 -> 0
A36: =IFERROR(__xludf.DUMMYFUNCTION("""COMPUTED_VALUE"""),"https://drive.google.com/open?id=1n4sM_hMizxMor4aS4-NffW1QEWkmmRaC&authuser=jay.agg%40gmail.com&usp=drive_fs") -> https://drive.google.com/open?id=1n4sM_hMizxMor4aS4-NffW1QEWkmmRaC&authuser=jay.agg%40gmail.com&usp=drive_fs | B36: =IFERROR(__xludf.DUMMYFUNCTION("""COMPUTED_VALUE"""),"Food") -> Food | C36: =IFERROR(__xludf.DUMMYFUNCTION("""COMPUTED_VALUE"""),"Dry Fruit") -> Dry Fruit | D36: =IFERROR(__xludf.DUMMYFUNCTION("""COMPUTED_VALUE"""),"110*40*160 mm LB") -> 110*40*160 mm LB | E36: =IFERROR(__xludf.DUMMYFUNCTION("""COMPUTED_VALUE"""),4) -> 4 | F36: =IFERROR(__xludf.DUMMYFUNCTION("""COMPUTED_VALUE"""),1926) -> 1926 | G36: =IFERROR(__xludf.DUMMYFUNCTION("""COMPUTED_VALUE"""),18) -> 18 | H36: =IFERROR(__xludf.DUMMYFUNCTION("""COMPUTED_VALUE"""),25) -> 25 | I36: =IFERROR(__xludf.DUMMYFUNCTION("""COMPUTED_VALUE"""),100) -> 100 | M36: =IFERROR(__xludf.DUMMYFUNCTION("""COMPUTED_VALUE"""),0.16) -> 0.16 | N36: =IFERROR(__xludf.DUMMYFUNCTION("""COMPUTED_VALUE"""),1) -> 1 | P36: =IFERROR(__xludf.DUMMYFUNCTION("""COMPUTED_VALUE"""),"Offset") -> Offset | Q36: =IFERROR(__xludf.DUMMYFUNCTION("""COMPUTED_VALUE"""),"Packaging") -> Packaging | BC36: =IFERROR(__xludf.DUMMYFUNCTION("""COMPUTED_VALUE"""),"Packaging") -> Packaging | BD36: =IFERROR(__xludf.DUMMYFUNCTION("""COMPUTED_VALUE"""),"Hardware") -> Hardware | BS36: Art Card | BT36: Normal | BU36: 170 GSM | BV36: =#REF! -> #REF! | CD36: =BY36 -> 0 | CE36: =CD36 -> 0
A37: =IFERROR(__xludf.DUMMYFUNCTION("""COMPUTED_VALUE"""),"https://drive.google.com/open?id=1pIykPqoOxble5EREsGAMRPdA1QccQ1AJ&authuser=jay.agg%40gmail.com&usp=drive_fs") -> https://drive.google.com/open?id=1pIykPqoOxble5EREsGAMRPdA1QccQ1AJ&authuser=jay.agg%40gmail.com&usp=drive_fs | B37: =IFERROR(__xludf.DUMMYFUNCTION("""COMPUTED_VALUE"""),"Food") -> Food | C37: =IFERROR(__xludf.DUMMYFUNCTION("""COMPUTED_VALUE"""),"Cake Mix 500g") -> Cake Mix 500g | D37: =IFERROR(__xludf.DUMMYFUNCTION("""COMPUTED_VALUE"""),"140*45*180 mm") -> 140*45*180 mm | E37: =IFERROR(__xludf.DUMMYFUNCTION("""COMPUTED_VALUE"""),2) -> 2 | F37: =IFERROR(__xludf.DUMMYFUNCTION("""COMPUTED_VALUE"""),1926) -> 1926 | G37: =IFERROR(__xludf.DUMMYFUNCTION("""COMPUTED_VALUE"""),15.75) -> 15.75 | H37: =IFERROR(__xludf.DUMMYFUNCTION("""COMPUTED_VALUE"""),20.75) -> 20.75 | I37: =IFERROR(__xludf.DUMMYFUNCTION("""COMPUTED_VALUE"""),100) -> 100 | M37: =IFERROR(__xludf.DUMMYFUNCTION("""COMPUTED_VALUE"""),0.1) -> 0.1 | N37: =IFERROR(__xludf.DUMMYFUNCTION("""COMPUTED_VALUE"""),1) -> 1 | P37: =IFERROR(__xludf.DUMMYFUNCTION("""COMPUTED_VALUE"""),"Offset") -> Offset | Q37: =IFERROR(__xludf.DUMMYFUNCTION("""COMPUTED_VALUE"""),"Packaging") -> Packaging | BC37: =IFERROR(__xludf.DUMMYFUNCTION("""COMPUTED_VALUE"""),"Packaging") -> Packaging | BD37: =IFERROR(__xludf.DUMMYFUNCTION("""COMPUTED_VALUE"""),"Hawa Dhoop") -> Hawa Dhoop | BS37: Art Card | BT37: Normal | BU37: 220 GSM | BV37: =#REF! -> #REF! | CD37: =BY37 -> 0 | CE37: =CD37 -> 0
A38: =IFERROR(__xludf.DUMMYFUNCTION("""COMPUTED_VALUE"""),"https://drive.google.com/open?id=1pOGW1xVCuMnUABRqNq-5cbJ_ByoO8G5w&authuser=jay.agg%40gmail.com&usp=drive_fs") -> https://drive.google.com/open?id=1pOGW1xVCuMnUABRqNq-5cbJ_ByoO8G5w&authuser=jay.agg%40gmail.com&usp=drive_fs | B38: =IFERROR(__xludf.DUMMYFUNCTION("""COMPUTED_VALUE"""),"Food") -> Food | C38: =IFERROR(__xludf.DUMMYFUNCTION("""COMPUTED_VALUE"""),"Cake Mix 1kg") -> Cake Mix 1kg | D38: =IFERROR(__xludf.DUMMYFUNCTION("""COMPUTED_VALUE"""),"165*52*235 mm") -> 165*52*235 mm | E38: =IFERROR(__xludf.DUMMYFUNCTION("""COMPUTED_VALUE"""),2) -> 2 | F38: =IFERROR(__xludf.DUMMYFUNCTION("""COMPUTED_VALUE"""),1926) -> 1926 | G38: =IFERROR(__xludf.DUMMYFUNCTION("""COMPUTED_VALUE"""),19) -> 19 | H38: =IFERROR(__xludf.DUMMYFUNCTION("""COMPUTED_VALUE"""),26) -> 26 | I38: =IFERROR(__xludf.DUMMYFUNCTION("""COMPUTED_VALUE"""),100) -> 100 | M38: =IFERROR(__xludf.DUMMYFUNCTION("""COMPUTED_VALUE"""),0.1) -> 0.1 | N38: =IFERROR(__xludf.DUMMYFUNCTION("""COMPUTED_VALUE"""),1) -> 1 | P38: =IFERROR(__xludf.DUMMYFUNCTION("""COMPUTED_VALUE"""),"Offset") -> Offset | Q38: =IFERROR(__xludf.DUMMYFUNCTION("""COMPUTED_VALUE"""),"Packaging") -> Packaging | BC38: =IFERROR(__xludf.DUMMYFUNCTION("""COMPUTED_VALUE"""),"Packaging") -> Packaging | BD38: =IFERROR(__xludf.DUMMYFUNCTION("""COMPUTED_VALUE"""),"Hawan Box") -> Hawan Box | BS38: Art Card | BT38: Normal | BU38: 250 GSM | BV38: =#REF! -> #REF! | CD38: =BY38 -> 0 | CE38: =CD38 -> 0
A39: =IFERROR(__xludf.DUMMYFUNCTION("""COMPUTED_VALUE"""),"https://drive.google.com/open?id=1w7snRg3lAxc0KM66W8RpVqDwD0jEOGQk&authuser=jay.agg%40gmail.com&usp=drive_fs") -> https://drive.google.com/open?id=1w7snRg3lAxc0KM66W8RpVqDwD0jEOGQk&authuser=jay.agg%40gmail.com&usp=drive_fs | B39: =IFERROR(__xludf.DUMMYFUNCTION("""COMPUTED_VALUE"""),"Food") -> Food | C39: =IFERROR(__xludf.DUMMYFUNCTION("""COMPUTED_VALUE"""),"Dog Food") -> Dog Food | D39: =IFERROR(__xludf.DUMMYFUNCTION("""COMPUTED_VALUE"""),"180*75*240 mm") -> 180*75*240 mm | E39: =IFERROR(__xludf.DUMMYFUNCTION("""COMPUTED_VALUE"""),1) -> 1 | F39: =IFERROR(__xludf.DUMMYFUNCTION("""COMPUTED_VALUE"""),1926) -> 1926 | G39: =IFERROR(__xludf.DUMMYFUNCTION("""COMPUTED_VALUE"""),15.75) -> 15.75 | H39: =IFERROR(__xludf.DUMMYFUNCTION("""COMPUTED_VALUE"""),20.75) -> 20.75 | I39: =IFERROR(__xludf.DUMMYFUNCTION("""COMPUTED_VALUE"""),100) -> 100 | M39: =IFERROR(__xludf.DUMMYFUNCTION("""COMPUTED_VALUE"""),0.1) -> 0.1 | N39: =IFERROR(__xludf.DUMMYFUNCTION("""COMPUTED_VALUE"""),1) -> 1 | P39: =IFERROR(__xludf.DUMMYFUNCTION("""COMPUTED_VALUE"""),"Offset") -> Offset | Q39: =IFERROR(__xludf.DUMMYFUNCTION("""COMPUTED_VALUE"""),"Packaging") -> Packaging | BC39: =IFERROR(__xludf.DUMMYFUNCTION("""COMPUTED_VALUE"""),"Packaging") -> Packaging | BD39: =IFERROR(__xludf.DUMMYFUNCTION("""COMPUTED_VALUE"""),"Henna Raj") -> Henna Raj | BS39: Art Card | BT39: Normal | BU39: 300 GSM | BV39: =#REF! -> #REF! | CD39: =BY39 -> 0 | CE39: =CD39 -> 0
A40: =IFERROR(__xludf.DUMMYFUNCTION("""COMPUTED_VALUE"""),"https://drive.google.com/open?id=1sp_9QJ74BN0EliJ8M8A64Pg3lvPXme-q&authuser=jay.agg%40gmail.com&usp=drive_fs") -> https://drive.google.com/open?id=1sp_9QJ74BN0EliJ8M8A64Pg3lvPXme-q&authuser=jay.agg%40gmail.com&usp=drive_fs | B40: =IFERROR(__xludf.DUMMYFUNCTION("""COMPUTED_VALUE"""),"Food") -> Food | C40: =IFERROR(__xludf.DUMMYFUNCTION("""COMPUTED_VALUE"""),"Gol Gappe") -> Gol Gappe | D40: =IFERROR(__xludf.DUMMYFUNCTION("""COMPUTED_VALUE"""),"178*127*52 mm | 7*5*2 inch") -> 178*127*52 mm | 7*5*2 inch | E40: =IFERROR(__xludf.DUMMYFUNCTION("""COMPUTED_VALUE"""),2) -> 2 | F40: =IFERROR(__xludf.DUMMYFUNCTION("""COMPUTED_VALUE"""),1926) -> 1926 | G40: =IFERROR(__xludf.DUMMYFUNCTION("""COMPUTED_VALUE"""),15) -> 15 | H40: =IFERROR(__xludf.DUMMYFUNCTION("""COMPUTED_VALUE"""),25) -> 25 | I40: =IFERROR(__xludf.DUMMYFUNCTION("""COMPUTED_VALUE"""),100) -> 100 | N40: =IFERROR(__xludf.DUMMYFUNCTION("""COMPUTED_VALUE"""),1) -> 1 | P40: =IFERROR(__xludf.DUMMYFUNCTION("""COMPUTED_VALUE"""),"Offset") -> Offset | Q40: =IFERROR(__xludf.DUMMYFUNCTION("""COMPUTED_VALUE"""),"Packaging") -> Packaging | BC40: =IFERROR(__xludf.DUMMYFUNCTION("""COMPUTED_VALUE"""),"Packaging") -> Packaging | BD40: =IFERROR(__xludf.DUMMYFUNCTION("""COMPUTED_VALUE"""),"HIT Chowk") -> HIT Chowk | BS40: Art Card | BT40: Normal | BU40: 350 GSM | BV40: =#REF! -> #REF! | CD40: =BY40 -> 0 | CE40: =CD40 -> 0
A41: =IFERROR(__xludf.DUMMYFUNCTION("""COMPUTED_VALUE"""),"https://drive.google.com/open?id=1wtvYpY8aQ2dYsGMZNWZHepkN93W2bRIs&authuser=jay.agg%40gmail.com&usp=drive_fs") -> https://drive.google.com/open?id=1wtvYpY8aQ2dYsGMZNWZHepkN93W2bRIs&authuser=jay.agg%40gmail.com&usp=drive_fs | B41: =IFERROR(__xludf.DUMMYFUNCTION("""COMPUTED_VALUE"""),"Food") -> Food | C41: =IFERROR(__xludf.DUMMYFUNCTION("""COMPUTED_VALUE"""),"Egg Box") -> Egg Box | D41: =IFERROR(__xludf.DUMMYFUNCTION("""COMPUTED_VALUE"""),"178*81*81 mm | 7*3.2*3.2 inch") -> 178*81*81 mm | 7*3.2*3.2 inch | E41: =IFERROR(__xludf.DUMMYFUNCTION("""COMPUTED_VALUE"""),3) -> 3 | F41: =IFERROR(__xludf.DUMMYFUNCTION("""COMPUTED_VALUE"""),1926) -> 1926 | G41: =IFERROR(__xludf.DUMMYFUNCTION("""COMPUTED_VALUE"""),14) -> 14 | H41: =IFERROR(__xludf.DUMMYFUNCTION("""COMPUTED_VALUE"""),22) -> 22 | I41: =IFERROR(__xludf.DUMMYFUNCTION("""COMPUTED_VALUE"""),100) -> 100 | M41: =IFERROR(__xludf.DUMMYFUNCTION("""COMPUTED_VALUE"""),0.1) -> 0.1 | N41: =IFERROR(__xludf.DUMMYFUNCTION("""COMPUTED_VALUE"""),1) -> 1 | P41: =IFERROR(__xludf.DUMMYFUNCTION("""COMPUTED_VALUE"""),"Offset") -> Offset | Q41: =IFERROR(__xludf.DUMMYFUNCTION("""COMPUTED_VALUE"""),"Packaging") -> Packaging | BC41: =IFERROR(__xludf.DUMMYFUNCTION("""COMPUTED_VALUE"""),"Packaging") -> Packaging | BD41: =IFERROR(__xludf.DUMMYFUNCTION("""COMPUTED_VALUE"""),"HOB") -> HOB | BS41: Art Card | BT41: Normal | BU41: 80 GSM | BV41: =#REF! -> #REF! | CD41: =BY41 -> 0 | CE41: =Quotation!D24 -> 0
A42: =IFERROR(__xludf.DUMMYFUNCTION("""COMPUTED_VALUE"""),"https://drive.google.com/open?id=1yW-6rS7DrydjnRfme_YMtpVLN0LPOEG3&authuser=jay.agg%40gmail.com&usp=drive_fs") -> https://drive.google.com/open?id=1yW-6rS7DrydjnRfme_YMtpVLN0LPOEG3&authuser=jay.agg%40gmail.com&usp=drive_fs | B42: =IFERROR(__xludf.DUMMYFUNCTION("""COMPUTED_VALUE"""),"Food") -> Food | C42: =IFERROR(__xludf.DUMMYFUNCTION("""COMPUTED_VALUE"""),"Chicken Envelop") -> Chicken Envelop | D42: =IFERROR(__xludf.DUMMYFUNCTION("""COMPUTED_VALUE"""),"165*240 mm | 6.5*9.5 inch W 4*6 inch") -> 165*240 mm | 6.5*9.5 inch W 4*6 inch | E42: =IFERROR(__xludf.DUMMYFUNCTION("""COMPUTED_VALUE"""),2) -> 2 | F42: =IFERROR(__xludf.DUMMYFUNCTION("""COMPUTED_VALUE"""),1926) -> 1926 | G42: =IFERROR(__xludf.DUMMYFUNCTION("""COMPUTED_VALUE"""),15) -> 15 | H42: =IFERROR(__xludf.DUMMYFUNCTION("""COMPUTED_VALUE"""),25) -> 25 | I42: =IFERROR(__xludf.DUMMYFUNCTION("""COMPUTED_VALUE"""),100) -> 100 | L42: =IFERROR(__xludf.DUMMYFUNCTION("""COMPUTED_VALUE"""),2) -> 2 | M42: =IFERROR(__xludf.DUMMYFUNCTION("""COMPUTED_VALUE"""),0.2) -> 0.2 | N42: =IFERROR(__xludf.DUMMYFUNCTION("""COMPUTED_VALUE"""),1) -> 1 | P42: =IFERROR(__xludf.DUMMYFUNCTION("""COMPUTED_VALUE"""),"Offset") -> Offset | Q42: =IFERROR(__xludf.DUMMYFUNCTION("""COMPUTED_VALUE"""),"Packaging") -> Packaging | BC42: =IFERROR(__xludf.DUMMYFUNCTION("""COMPUTED_VALUE"""),"Packaging") -> Packaging | BD42: =IFERROR(__xludf.DUMMYFUNCTION("""COMPUTED_VALUE"""),"Hosiery") -> Hosiery | BS42: Other Type | BT42: Normal | BV42: =#REF! -> #REF! | CD42: =BY42 -> 0 | CE42: =CD42 -> 0
A43: =IFERROR(__xludf.DUMMYFUNCTION("""COMPUTED_VALUE"""),"https://drive.google.com/open?id=16rGecGFRPqzZiav5oiujTYJBYkBawRPk&authuser=jay.agg%40gmail.com&usp=drive_fs") -> https://drive.google.com/open?id=16rGecGFRPqzZiav5oiujTYJBYkBawRPk&authuser=jay.agg%40gmail.com&usp=drive_fs | B43: =IFERROR(__xludf.DUMMYFUNCTION("""COMPUTED_VALUE"""),"Food") -> Food | C43: =IFERROR(__xludf.DUMMYFUNCTION("""COMPUTED_VALUE"""),"South Indian") -> South Indian | D43: =IFERROR(__xludf.DUMMYFUNCTION("""COMPUTED_VALUE"""),"Dosa 406*152*51 mm | 16*6*2 inch") -> Dosa 406*152*51 mm | 16*6*2 inch | E43: =IFERROR(__xludf.DUMMYFUNCTION("""COMPUTED_VALUE"""),1) -> 1 | F43: =IFERROR(__xludf.DUMMYFUNCTION("""COMPUTED_VALUE"""),1926) -> 1926 | G43: =IFERROR(__xludf.DUMMYFUNCTION("""COMPUTED_VALUE"""),18) -> 18 | H43: =IFERROR(__xludf.DUMMYFUNCTION("""COMPUTED_VALUE"""),21) -> 21 | I43: =IFERROR(__xludf.DUMMYFUNCTION("""COMPUTED_VALUE"""),100) -> 100 | N43: =IFERROR(__xludf.DUMMYFUNCTION("""COMPUTED_VALUE"""),1) -> 1 | P43: =IFERROR(__xludf.DUMMYFUNCTION("""COMPUTED_VALUE"""),"Offset") -> Offset | Q43: =IFERROR(__xludf.DUMMYFUNCTION("""COMPUTED_VALUE"""),"Packaging") -> Packaging | BC43: =IFERROR(__xludf.DUMMYFUNCTION("""COMPUTED_VALUE"""),"Packaging") -> Packaging | BD43: =IFERROR(__xludf.DUMMYFUNCTION("""COMPUTED_VALUE"""),"Jwellery") -> Jwellery | BS43: Other Type | BT43: Custom | BV43: =$BV$9 -> 75
A44: =IFERROR(__xludf.DUMMYFUNCTION("""COMPUTED_VALUE"""),"https://drive.google.com/open?id=1LnxmtJvvSGJY7VkJq3aAu_pl1Ts7X2OV&authuser=jay.agg%40gmail.com&usp=drive_fs") -> https://drive.google.com/open?id=1LnxmtJvvSGJY7VkJq3aAu_pl1Ts7X2OV&authuser=jay.agg%40gmail.com&usp=drive_fs | B44: =IFERROR(__xludf.DUMMYFUNCTION("""COMPUTED_VALUE"""),"Food") -> Food | C44: =IFERROR(__xludf.DUMMYFUNCTION("""COMPUTED_VALUE"""),"Flakes") -> Flakes | D44: =IFERROR(__xludf.DUMMYFUNCTION("""COMPUTED_VALUE"""),"140*38*190 mm | 5.5*1.5*7.5 inch") -> 140*38*190 mm | 5.5*1.5*7.5 inch | E44: =IFERROR(__xludf.DUMMYFUNCTION("""COMPUTED_VALUE"""),2) -> 2 | F44: =IFERROR(__xludf.DUMMYFUNCTION("""COMPUTED_VALUE"""),1926) -> 1926 | G44: =IFERROR(__xludf.DUMMYFUNCTION("""COMPUTED_VALUE"""),15.75) -> 15.75 | H44: =IFERROR(__xludf.DUMMYFUNCTION("""COMPUTED_VALUE"""),20.75) -> 20.75 | I44: =IFERROR(__xludf.DUMMYFUNCTION("""COMPUTED_VALUE"""),100) -> 100 | M44: =IFERROR(__xludf.DUMMYFUNCTION("""COMPUTED_VALUE"""),0.1) -> 0.1 | N44: =IFERROR(__xludf.DUMMYFUNCTION("""COMPUTED_VALUE"""),1) -> 1 | P44: =IFERROR(__xludf.DUMMYFUNCTION("""COMPUTED_VALUE"""),"Offset") -> Offset | Q44: =IFERROR(__xludf.DUMMYFUNCTION("""COMPUTED_VALUE"""),"Packaging") -> Packaging | BC44: =IFERROR(__xludf.DUMMYFUNCTION("""COMPUTED_VALUE"""),"Packaging") -> Packaging | BD44: =IFERROR(__xludf.DUMMYFUNCTION("""COMPUTED_VALUE"""),"Led") -> Led | BS44: Custom Paper | BT44: Custom | BV44: =$BV$9 -> 75 | BY44: GSM
A45: =IFERROR(__xludf.DUMMYFUNCTION("""COMPUTED_VALUE"""),"https://drive.google.com/open?id=1MM1rWUjsBimB1oEX-BTeoKxBdLPyBOd8&authuser=jay.agg%40gmail.com&usp=drive_fs") -> https://drive.google.com/open?id=1MM1rWUjsBimB1oEX-BTeoKxBdLPyBOd8&authuser=jay.agg%40gmail.com&usp=drive_fs | B45: =IFERROR(__xludf.DUMMYFUNCTION("""COMPUTED_VALUE"""),"Food") -> Food | C45: =IFERROR(__xludf.DUMMYFUNCTION("""COMPUTED_VALUE"""),"Gulab Jamun") -> Gulab Jamun | D45: =IFERROR(__xludf.DUMMYFUNCTION("""COMPUTED_VALUE"""),"146*40*190 mm | 5.7*1.5*7.5 inch") -> 146*40*190 mm | 5.7*1.5*7.5 inch | E45: =IFERROR(__xludf.DUMMYFUNCTION("""COMPUTED_VALUE"""),2) -> 2 | F45: =IFERROR(__xludf.DUMMYFUNCTION("""COMPUTED_VALUE"""),1926) -> 1926 | G45: =IFERROR(__xludf.DUMMYFUNCTION("""COMPUTED_VALUE"""),15.75) -> 15.75 | H45: =IFERROR(__xludf.DUMMYFUNCTION("""COMPUTED_VALUE"""),20.75) -> 20.75 | I45: =IFERROR(__xludf.DUMMYFUNCTION("""COMPUTED_VALUE"""),100) -> 100 | M45: =IFERROR(__xludf.DUMMYFUNCTION("""COMPUTED_VALUE"""),0.1) -> 0.1 | N45: =IFERROR(__xludf.DUMMYFUNCTION("""COMPUTED_VALUE"""),1) -> 1 | P45: =IFERROR(__xludf.DUMMYFUNCTION("""COMPUTED_VALUE"""),"Offset") -> Offset | Q45: =IFERROR(__xludf.DUMMYFUNCTION("""COMPUTED_VALUE"""),"Packaging") -> Packaging | BC45: =IFERROR(__xludf.DUMMYFUNCTION("""COMPUTED_VALUE"""),"Packaging") -> Packaging | BD45: =IFERROR(__xludf.DUMMYFUNCTION("""COMPUTED_VALUE"""),"Lifespan") -> Lifespan | BF45: Digital | BG45: 1001 | BH45: =IFERROR(__xludf.DUMMYFUNCTION("QUERY(BF45:BG51,BH4)"),"Packaging") -> Packaging | BI45: =IFERROR(__xludf.DUMMYFUNCTION("""COMPUTED_VALUE"""),1926) -> 1926 | BJ45: =IFERROR(__xludf.DUMMYFUNCTION("QUERY(Price!AY2:AZ50,BI4)"),"#N/A") -> #N/A | BL45: =IFERROR(__xludf.DUMMYFUNCTION("QUERY(Price!BC2:BD8,BJ4)"),"#N/A") -> #N/A | BN45: =IFERROR(__xludf.DUMMYFUNCTION("QUERY(Price!AW2:AX50,BK4)"),"#N/A") -> #N/A | BP45: =IFERROR(__xludf.DUMMYFUNCTION("QUERY(Price!AU2:AV50,BL4)"),"Plain") -> Plain | BQ45: =IFERROR(__xludf.DUMMYFUNCTION("""COMPUTED_VALUE"""),0) -> 0 | BS45: Art Card | BT45: Custom | BV45: =$BV$9 -> 75
A46: =IFERROR(__xludf.DUMMYFUNCTION("""COMPUTED_VALUE"""),"https://drive.google.com/open?id=18WtWUp82-bxe5E36yJ652kShQ0NBVp9t&authuser=jay.agg%40gmail.com&usp=drive_fs") -> https://drive.google.com/open?id=18WtWUp82-bxe5E36yJ652kShQ0NBVp9t&authuser=jay.agg%40gmail.com&usp=drive_fs | B46: =IFERROR(__xludf.DUMMYFUNCTION("""COMPUTED_VALUE"""),"Food") -> Food | C46: =IFERROR(__xludf.DUMMYFUNCTION("""COMPUTED_VALUE"""),"Cookies") -> Cookies | D46: =IFERROR(__xludf.DUMMYFUNCTION("""COMPUTED_VALUE"""),"140*55*190 mm") -> 140*55*190 mm | E46: =IFERROR(__xludf.DUMMYFUNCTION("""COMPUTED_VALUE"""),2) -> 2 | F46: =IFERROR(__xludf.DUMMYFUNCTION("""COMPUTED_VALUE"""),1926) -> 1926 | G46: =IFERROR(__xludf.DUMMYFUNCTION("""COMPUTED_VALUE"""),18) -> 18 | H46: =IFERROR(__xludf.DUMMYFUNCTION("""COMPUTED_VALUE"""),23) -> 23 | I46: =IFERROR(__xludf.DUMMYFUNCTION("""COMPUTED_VALUE"""),100) -> 100 | M46: =IFERROR(__xludf.DUMMYFUNCTION("""COMPUTED_VALUE"""),0.1) -> 0.1 | N46: =IFERROR(__xludf.DUMMYFUNCTION("""COMPUTED_VALUE"""),1) -> 1 | P46: =IFERROR(__xludf.DUMMYFUNCTION("""COMPUTED_VALUE"""),"Offset") -> Offset | Q46: =IFERROR(__xludf.DUMMYFUNCTION("""COMPUTED_VALUE"""),"Packaging") -> Packaging | BC46: =IFERROR(__xludf.DUMMYFUNCTION("""COMPUTED_VALUE"""),"Packaging") -> Packaging | BD46: =IFERROR(__xludf.DUMMYFUNCTION("""COMPUTED_VALUE"""),"Machine Parts") -> Machine Parts | BF46: Solvent | BG46: 1002
A47: =IFERROR(__xludf.DUMMYFUNCTION("""COMPUTED_VALUE"""),"https://drive.google.com/open?id=1sJOiUA7Cg8Dnqu2sHtqanOPoz9thjI2G&authuser=jay.agg%40gmail.com&usp=drive_fs") -> https://drive.google.com/open?id=1sJOiUA7Cg8Dnqu2sHtqanOPoz9thjI2G&authuser=jay.agg%40gmail.com&usp=drive_fs | B47: =IFERROR(__xludf.DUMMYFUNCTION("""COMPUTED_VALUE"""),"Food") -> Food | C47: =IFERROR(__xludf.DUMMYFUNCTION("""COMPUTED_VALUE"""),"Cookies") -> Cookies | D47: =IFERROR(__xludf.DUMMYFUNCTION("""COMPUTED_VALUE"""),"165*76*330 mm") -> 165*76*330 mm | E47: =IFERROR(__xludf.DUMMYFUNCTION("""COMPUTED_VALUE"""),1) -> 1 | F47: =IFERROR(__xludf.DUMMYFUNCTION("""COMPUTED_VALUE"""),1926) -> 1926 | G47: =IFERROR(__xludf.DUMMYFUNCTION("""COMPUTED_VALUE"""),19) -> 19 | H47: =IFERROR(__xludf.DUMMYFUNCTION("""COMPUTED_VALUE"""),20) -> 20 | I47: =IFERROR(__xludf.DUMMYFUNCTION("""COMPUTED_VALUE"""),100) -> 100 | M47: =IFERROR(__xludf.DUMMYFUNCTION("""COMPUTED_VALUE"""),0.1) -> 0.1 | N47: =IFERROR(__xludf.DUMMYFUNCTION("""COMPUTED_VALUE"""),1) -> 1 | P47: =IFERROR(__xludf.DUMMYFUNCTION("""COMPUTED_VALUE"""),"Offset") -> Offset | Q47: =IFERROR(__xludf.DUMMYFUNCTION("""COMPUTED_VALUE"""),"Packaging") -> Packaging | BC47: =IFERROR(__xludf.DUMMYFUNCTION("""COMPUTED_VALUE"""),"Packaging") -> Packaging | BD47: =IFERROR(__xludf.DUMMYFUNCTION("""COMPUTED_VALUE"""),"Masala") -> Masala | BF47: HP Latex | BG47: 1004
A48: =IFERROR(__xludf.DUMMYFUNCTION("""COMPUTED_VALUE"""),"https://drive.google.com/open?id=1Mk8KwkQiUvbHItBUpcNASorFhKK9mzY3&authuser=jay.agg%40gmail.com&usp=drive_fs") -> https://drive.google.com/open?id=1Mk8KwkQiUvbHItBUpcNASorFhKK9mzY3&authuser=jay.agg%40gmail.com&usp=drive_fs | B48: =IFERROR(__xludf.DUMMYFUNCTION("""COMPUTED_VALUE"""),"Food") -> Food | C48: =IFERROR(__xludf.DUMMYFUNCTION("""COMPUTED_VALUE"""),"Soyabean") -> Soyabean | D48: =IFERROR(__xludf.DUMMYFUNCTION("""COMPUTED_VALUE"""),"125*55*195 mm | 5*2.1*7.7 inch") -> 125*55*195 mm | 5*2.1*7.7 inch | E48: =IFERROR(__xludf.DUMMYFUNCTION("""COMPUTED_VALUE"""),2) -> 2 | F48: =IFERROR(__xludf.DUMMYFUNCTION("""COMPUTED_VALUE"""),1926) -> 1926 | G48: =IFERROR(__xludf.DUMMYFUNCTION("""COMPUTED_VALUE"""),15) -> 15 | H48: =IFERROR(__xludf.DUMMYFUNCTION("""COMPUTED_VALUE"""),25) -> 25 | I48: =IFERROR(__xludf.DUMMYFUNCTION("""COMPUTED_VALUE"""),100) -> 100 | M48: =IFERROR(__xludf.DUMMYFUNCTION("""COMPUTED_VALUE"""),0.1) -> 0.1 | N48: =IFERROR(__xludf.DUMMYFUNCTION("""COMPUTED_VALUE"""),1) -> 1 | P48: =IFERROR(__xludf.DUMMYFUNCTION("""COMPUTED_VALUE"""),"Offset") -> Offset | Q48: =IFERROR(__xludf.DUMMYFUNCTION("""COMPUTED_VALUE"""),"Packaging") -> Packaging | BC48: =IFERROR(__xludf.DUMMYFUNCTION("""COMPUTED_VALUE"""),"Packaging") -> Packaging | BD48: =IFERROR(__xludf.DUMMYFUNCTION("""COMPUTED_VALUE"""),"Maxobull") -> Maxobull | BF48: Eco Solvent | BG48: 1003
A49: =IFERROR(__xludf.DUMMYFUNCTION("""COMPUTED_VALUE"""),"https://drive.google.com/open?id=1NmrEWzL0jccCY3gRhr0OT_AIXLqaAYOX&authuser=jay.agg%40gmail.com&usp=drive_fs") -> https://drive.google.com/open?id=1NmrEWzL0jccCY3gRhr0OT_AIXLqaAYOX&authuser=jay.agg%40gmail.com&usp=drive_fs | B49: =IFERROR(__xludf.DUMMYFUNCTION("""COMPUTED_VALUE"""),"Food") -> Food | C49: =IFERROR(__xludf.DUMMYFUNCTION("""COMPUTED_VALUE"""),"Misc") -> Misc | D49: =IFERROR(__xludf.DUMMYFUNCTION("""COMPUTED_VALUE"""),"127*51*203 mm | 5*2*8 inch") -> 127*51*203 mm | 5*2*8 inch | E49: =IFERROR(__xludf.DUMMYFUNCTION("""COMPUTED_VALUE"""),2) -> 2 | F49: =IFERROR(__xludf.DUMMYFUNCTION("""COMPUTED_VALUE"""),1926) -> 1926 | G49: =IFERROR(__xludf.DUMMYFUNCTION("""COMPUTED_VALUE"""),15) -> 15 | H49: =IFERROR(__xludf.DUMMYFUNCTION("""COMPUTED_VALUE"""),25) -> 25 | I49: =IFERROR(__xludf.DUMMYFUNCTION("""COMPUTED_VALUE"""),100) -> 100 | M49: =IFERROR(__xludf.DUMMYFUNCTION("""COMPUTED_VALUE"""),0.1) -> 0.1 | N49: =IFERROR(__xludf.DUMMYFUNCTION("""COMPUTED_VALUE"""),1) -> 1 | P49: =IFERROR(__xludf.DUMMYFUNCTION("""COMPUTED_VALUE"""),"Offset") -> Offset | Q49: =IFERROR(__xludf.DUMMYFUNCTION("""COMPUTED_VALUE"""),"Packaging") -> Packaging | BC49: =IFERROR(__xludf.DUMMYFUNCTION("""COMPUTED_VALUE"""),"Packaging") -> Packaging | BD49: =IFERROR(__xludf.DUMMYFUNCTION("""COMPUTED_VALUE"""),"Medecine") -> Medecine | BF49: Commercial | BG49: 1926
A50: =IFERROR(__xludf.DUMMYFUNCTION("""COMPUTED_VALUE"""),"https://drive.google.com/open?id=1O3DBsUn3E9JvBhXZN8erEkDTKD49qVs-&authuser=jay.agg%40gmail.com&usp=drive_fs") -> https://drive.google.com/open?id=1O3DBsUn3E9JvBhXZN8erEkDTKD49qVs-&authuser=jay.agg%40gmail.com&usp=drive_fs | B50: =IFERROR(__xludf.DUMMYFUNCTION("""COMPUTED_VALUE"""),"Food") -> Food | C50: =IFERROR(__xludf.DUMMYFUNCTION("""COMPUTED_VALUE"""),"Cookies") -> Cookies | D50: =IFERROR(__xludf.DUMMYFUNCTION("""COMPUTED_VALUE"""),"60*60*150 mm | 2.3*2.3*5.9 inch") -> 60*60*150 mm | 2.3*2.3*5.9 inch | E50: =IFERROR(__xludf.DUMMYFUNCTION("""COMPUTED_VALUE"""),4) -> 4 | F50: =IFERROR(__xludf.DUMMYFUNCTION("""COMPUTED_VALUE"""),2029) -> 2029 | G50: =IFERROR(__xludf.DUMMYFUNCTION("""COMPUTED_VALUE"""),20) -> 20 | H50: =IFERROR(__xludf.DUMMYFUNCTION("""COMPUTED_VALUE"""),28) -> 28 | I50: =IFERROR(__xludf.DUMMYFUNCTION("""COMPUTED_VALUE"""),100) -> 100 | M50: =IFERROR(__xludf.DUMMYFUNCTION("""COMPUTED_VALUE"""),0.1) -> 0.1 | N50: =IFERROR(__xludf.DUMMYFUNCTION("""COMPUTED_VALUE"""),1) -> 1 | P50: =IFERROR(__xludf.DUMMYFUNCTION("""COMPUTED_VALUE"""),"Offset") -> Offset | Q50: =IFERROR(__xludf.DUMMYFUNCTION("""COMPUTED_VALUE"""),"Packaging") -> Packaging | BC50: =IFERROR(__xludf.DUMMYFUNCTION("""COMPUTED_VALUE"""),"Packaging") -> Packaging | BD50: =IFERROR(__xludf.DUMMYFUNCTION("""COMPUTED_VALUE"""),"Meethai & Cake") -> Meethai & Cake | BF50: Packaging | BG50: 1926
A51: =IFERROR(__xludf.DUMMYFUNCTION("""COMPUTED_VALUE"""),"https://drive.google.com/open?id=1OChsXdmJLOGgS9j_u_FIIbtfxgE_RFPu&authuser=jay.agg%40gmail.com&usp=drive_fs") -> https://drive.google.com/open?id=1OChsXdmJLOGgS9j_u_FIIbtfxgE_RFPu&authuser=jay.agg%40gmail.com&usp=drive_fs | B51: =IFERROR(__xludf.DUMMYFUNCTION("""COMPUTED_VALUE"""),"Food") -> Food | C51: =IFERROR(__xludf.DUMMYFUNCTION("""COMPUTED_VALUE"""),"Frozen") -> Frozen | D51: =IFERROR(__xludf.DUMMYFUNCTION("""COMPUTED_VALUE"""),"190*140*51 mm | 7.5*5.5*2 inch") -> 190*140*51 mm | 7.5*5.5*2 inch | E51: =IFERROR(__xludf.DUMMYFUNCTION("""COMPUTED_VALUE"""),3) -> 3 | F51: =IFERROR(__xludf.DUMMYFUNCTION("""COMPUTED_VALUE"""),1926) -> 1926 | G51: =IFERROR(__xludf.DUMMYFUNCTION("""COMPUTED_VALUE"""),18) -> 18 | H51: =IFERROR(__xludf.DUMMYFUNCTION("""COMPUTED_VALUE"""),23) -> 23 | I51: =IFERROR(__xludf.DUMMYFUNCTION("""COMPUTED_VALUE"""),100) -> 100 | M51: =IFERROR(__xludf.DUMMYFUNCTION("""COMPUTED_VALUE"""),0.1) -> 0.1 | N51: =IFERROR(__xludf.DUMMYFUNCTION("""COMPUTED_VALUE"""),1) -> 1 | P51: =IFERROR(__xludf.DUMMYFUNCTION("""COMPUTED_VALUE"""),"Offset") -> Offset | Q51: =IFERROR(__xludf.DUMMYFUNCTION("""COMPUTED_VALUE"""),"Packaging") -> Packaging | BC51: =IFERROR(__xludf.DUMMYFUNCTION("""COMPUTED_VALUE"""),"Packaging") -> Packaging | BD51: =IFERROR(__xludf.DUMMYFUNCTION("""COMPUTED_VALUE"""),"MFM") -> MFM | BF51: Hand Made | BG51: 1005
A52: =IFERROR(__xludf.DUMMYFUNCTION("""COMPUTED_VALUE"""),"https://drive.google.com/open?id=1Bnsb0frEED9Anr-37j2jzpXfxbfcoGZE&authuser=jay.agg%40gmail.com&usp=drive_fs") -> https://drive.google.com/open?id=1Bnsb0frEED9Anr-37j2jzpXfxbfcoGZE&authuser=jay.agg%40gmail.com&usp=drive_fs | B52: =IFERROR(__xludf.DUMMYFUNCTION("""COMPUTED_VALUE"""),"Food") -> Food | C52: =IFERROR(__xludf.DUMMYFUNCTION("""COMPUTED_VALUE"""),"Rusk") -> Rusk | D52: =IFERROR(__xludf.DUMMYFUNCTION("""COMPUTED_VALUE"""),"130*80*155 mm | 5*3*6 inch") -> 130*80*155 mm | 5*3*6 inch | E52: =IFERROR(__xludf.DUMMYFUNCTION("""COMPUTED_VALUE"""),2) -> 2 | F52: =IFERROR(__xludf.DUMMYFUNCTION("""COMPUTED_VALUE"""),1926) -> 1926 | G52: =IFERROR(__xludf.DUMMYFUNCTION("""COMPUTED_VALUE"""),18) -> 18 | H52: =IFERROR(__xludf.DUMMYFUNCTION("""COMPUTED_VALUE"""),25) -> 25 | I52: =IFERROR(__xludf.DUMMYFUNCTION("""COMPUTED_VALUE"""),100) -> 100 | M52: =IFERROR(__xludf.DUMMYFUNCTION("""COMPUTED_VALUE"""),0.1) -> 0.1 | N52: =IFERROR(__xludf.DUMMYFUNCTION("""COMPUTED_VALUE"""),1) -> 1 | P52: =IFERROR(__xludf.DUMMYFUNCTION("""COMPUTED_VALUE"""),"Offset") -> Offset | Q52: =IFERROR(__xludf.DUMMYFUNCTION("""COMPUTED_VALUE"""),"Packaging") -> Packaging | BC52: =IFERROR(__xludf.DUMMYFUNCTION("""COMPUTED_VALUE"""),"Packaging") -> Packaging | BD52: =IFERROR(__xludf.DUMMYFUNCTION("""COMPUTED_VALUE"""),"Misc") -> Misc
A53: =IFERROR(__xludf.DUMMYFUNCTION("""COMPUTED_VALUE"""),"https://drive.google.com/open?id=1Brn9QCMkUjdGOnRuWsTH_LaeUOxtQZ9b&authuser=jay.agg%40gmail.com&usp=drive_fs") -> https://drive.google.com/open?id=1Brn9QCMkUjdGOnRuWsTH_LaeUOxtQZ9b&authuser=jay.agg%40gmail.com&usp=drive_fs | B53: =IFERROR(__xludf.DUMMYFUNCTION("""COMPUTED_VALUE"""),"Food") -> Food | C53: =IFERROR(__xludf.DUMMYFUNCTION("""COMPUTED_VALUE"""),"Burger Box") -> Burger Box | D53: =IFERROR(__xludf.DUMMYFUNCTION("""COMPUTED_VALUE"""),"125*125*53 mm | 5*5*2 inch") -> 125*125*53 mm | 5*5*2 inch | E53: =IFERROR(__xludf.DUMMYFUNCTION("""COMPUTED_VALUE"""),3) -> 3 | F53: =IFERROR(__xludf.DUMMYFUNCTION("""COMPUTED_VALUE"""),2029) -> 2029 | G53: =IFERROR(__xludf.DUMMYFUNCTION("""COMPUTED_VALUE"""),20) -> 20 | H53: =IFERROR(__xludf.DUMMYFUNCTION("""COMPUTED_VALUE"""),28) -> 28 | I53: =IFERROR(__xludf.DUMMYFUNCTION("""COMPUTED_VALUE"""),100) -> 100 | M53: =IFERROR(__xludf.DUMMYFUNCTION("""COMPUTED_VALUE"""),1) -> 1 | N53: =IFERROR(__xludf.DUMMYFUNCTION("""COMPUTED_VALUE"""),1) -> 1 | P53: =IFERROR(__xludf.DUMMYFUNCTION("""COMPUTED_VALUE"""),"Offset") -> Offset | Q53: =IFERROR(__xludf.DUMMYFUNCTION("""COMPUTED_VALUE"""),"Packaging") -> Packaging | BC53: =IFERROR(__xludf.DUMMYFUNCTION("""COMPUTED_VALUE"""),"Packaging") -> Packaging | BD53: =IFERROR(__xludf.DUMMYFUNCTION("""COMPUTED_VALUE"""),"Mobile") -> Mobile
A54: =IFERROR(__xludf.DUMMYFUNCTION("""COMPUTED_VALUE"""),"https://drive.google.com/open?id=1OQZ-ePtmH2eRW6YsfL_Pau-Vk4pj3Ge2&authuser=jay.agg%40gmail.com&usp=drive_fs") -> https://drive.google.com/open?id=1OQZ-ePtmH2eRW6YsfL_Pau-Vk4pj3Ge2&authuser=jay.agg%40gmail.com&usp=drive_fs | B54: =IFERROR(__xludf.DUMMYFUNCTION("""COMPUTED_VALUE"""),"Food") -> Food | C54: =IFERROR(__xludf.DUMMYFUNCTION("""COMPUTED_VALUE"""),"Corn Flakes") -> Corn Flakes | D54: =IFERROR(__xludf.DUMMYFUNCTION("""COMPUTED_VALUE"""),"230*70*295 mm | 9*2.7*11.6 inch") -> 230*70*295 mm | 9*2.7*11.6 inch | E54: =IFERROR(__xludf.DUMMYFUNCTION("""COMPUTED_VALUE"""),1) -> 1 | F54: =IFERROR(__xludf.DUMMYFUNCTION("""COMPUTED_VALUE"""),1926) -> 1926 | G54: =IFERROR(__xludf.DUMMYFUNCTION("""COMPUTED_VALUE"""),18) -> 18 | H54: =IFERROR(__xludf.DUMMYFUNCTION("""COMPUTED_VALUE"""),25) -> 25 | I54: =IFERROR(__xludf.DUMMYFUNCTION("""COMPUTED_VALUE"""),100) -> 100 | M54: =IFERROR(__xludf.DUMMYFUNCTION("""COMPUTED_VALUE"""),0.1) -> 0.1 | N54: =IFERROR(__xludf.DUMMYFUNCTION("""COMPUTED_VALUE"""),1) -> 1 | P54: =IFERROR(__xludf.DUMMYFUNCTION("""COMPUTED_VALUE"""),"Offset") -> Offset | Q54: =IFERROR(__xludf.DUMMYFUNCTION("""COMPUTED_VALUE"""),"Packaging") -> Packaging | BC54: =IFERROR(__xludf.DUMMYFUNCTION("""COMPUTED_VALUE"""),"Packaging") -> Packaging | BD54: =IFERROR(__xludf.DUMMYFUNCTION("""COMPUTED_VALUE"""),"Mobile Accessories") -> Mobile Accessories
A55: =IFERROR(__xludf.DUMMYFUNCTION("""COMPUTED_VALUE"""),"https://drive.google.com/open?id=1O_3sh0g_XSvMgDCFr3QaNGWrPCMmR6No&authuser=jay.agg%40gmail.com&usp=drive_fs") -> https://drive.google.com/open?id=1O_3sh0g_XSvMgDCFr3QaNGWrPCMmR6No&authuser=jay.agg%40gmail.com&usp=drive_fs | B55: =IFERROR(__xludf.DUMMYFUNCTION("""COMPUTED_VALUE"""),"Food") -> Food | C55: =IFERROR(__xludf.DUMMYFUNCTION("""COMPUTED_VALUE"""),"Corn Flakes") -> Corn Flakes | D55: =IFERROR(__xludf.DUMMYFUNCTION("""COMPUTED_VALUE"""),"245*90*350 mm | 9.6*3.5*13.8 inch") -> 245*90*350 mm | 9.6*3.5*13.8 inch | E55: =IFERROR(__xludf.DUMMYFUNCTION("""COMPUTED_VALUE"""),1) -> 1 | F55: =IFERROR(__xludf.DUMMYFUNCTION("""COMPUTED_VALUE"""),2029) -> 2029 | G55: =IFERROR(__xludf.DUMMYFUNCTION("""COMPUTED_VALUE"""),20) -> 20 | H55: =IFERROR(__xludf.DUMMYFUNCTION("""COMPUTED_VALUE"""),28) -> 28 | I55: =IFERROR(__xludf.DUMMYFUNCTION("""COMPUTED_VALUE"""),100) -> 100 | M55: =IFERROR(__xludf.DUMMYFUNCTION("""COMPUTED_VALUE"""),0.1) -> 0.1 | N55: =IFERROR(__xludf.DUMMYFUNCTION("""COMPUTED_VALUE"""),1) -> 1 | P55: =IFERROR(__xludf.DUMMYFUNCTION("""COMPUTED_VALUE"""),"Offset") -> Offset | Q55: =IFERROR(__xludf.DUMMYFUNCTION("""COMPUTED_VALUE"""),"Packaging") -> Packaging | BC55: =IFERROR(__xludf.DUMMYFUNCTION("""COMPUTED_VALUE"""),"Packaging") -> Packaging | BD55: =IFERROR(__xludf.DUMMYFUNCTION("""COMPUTED_VALUE"""),"Nathabit") -> Nathabit
A56: =IFERROR(__xludf.DUMMYFUNCTION("""COMPUTED_VALUE"""),"https://drive.google.com/open?id=1OzRhqM1WSTTxUyiXmK-uo6qHSLFo1J6W&authuser=jay.agg%40gmail.com&usp=drive_fs") -> https://drive.google.com/open?id=1OzRhqM1WSTTxUyiXmK-uo6qHSLFo1J6W&authuser=jay.agg%40gmail.com&usp=drive_fs | B56: =IFERROR(__xludf.DUMMYFUNCTION("""COMPUTED_VALUE"""),"Food") -> Food | C56: =IFERROR(__xludf.DUMMYFUNCTION("""COMPUTED_VALUE"""),"Cookies") -> Cookies | D56: =IFERROR(__xludf.DUMMYFUNCTION("""COMPUTED_VALUE"""),"60*60*130 mm | 2.3*2.3*5.1 inch") -> 60*60*130 mm | 2.3*2.3*5.1 inch | E56: =IFERROR(__xludf.DUMMYFUNCTION("""COMPUTED_VALUE"""),6) -> 6 | F56: =IFERROR(__xludf.DUMMYFUNCTION("""COMPUTED_VALUE"""),2029) -> 2029 | G56: =IFERROR(__xludf.DUMMYFUNCTION("""COMPUTED_VALUE"""),20) -> 20 | H56: =IFERROR(__xludf.DUMMYFUNCTION("""COMPUTED_VALUE"""),28) -> 28 | I56: =IFERROR(__xludf.DUMMYFUNCTION("""COMPUTED_VALUE"""),100) -> 100 | M56: =IFERROR(__xludf.DUMMYFUNCTION("""COMPUTED_VALUE"""),0.1) -> 0.1 | N56: =IFERROR(__xludf.DUMMYFUNCTION("""COMPUTED_VALUE"""),1) -> 1 | P56: =IFERROR(__xludf.DUMMYFUNCTION("""COMPUTED_VALUE"""),"Offset") -> Offset | Q56: =IFERROR(__xludf.DUMMYFUNCTION("""COMPUTED_VALUE"""),"Packaging") -> Packaging | BC56: =IFERROR(__xludf.DUMMYFUNCTION("""COMPUTED_VALUE"""),"Packaging") -> Packaging | BD56: =IFERROR(__xludf.DUMMYFUNCTION("""COMPUTED_VALUE"""),"Pooja Kit") -> Pooja Kit
A57: =IFERROR(__xludf.DUMMYFUNCTION("""COMPUTED_VALUE"""),"https://drive.google.com/open?id=1Oo0o_Uf6_P3cO3tp05t4Mu8X7X5OlgLf&authuser=jay.agg%40gmail.com&usp=drive_fs") -> https://drive.google.com/open?id=1Oo0o_Uf6_P3cO3tp05t4Mu8X7X5OlgLf&authuser=jay.agg%40gmail.com&usp=drive_fs | B57: =IFERROR(__xludf.DUMMYFUNCTION("""COMPUTED_VALUE"""),"Food") -> Food | C57: =IFERROR(__xludf.DUMMYFUNCTION("""COMPUTED_VALUE"""),"Chocolate") -> Chocolate | D57: =IFERROR(__xludf.DUMMYFUNCTION("""COMPUTED_VALUE"""),"230*230*60 mm | 9*9*2.3 inch") -> 230*230*60 mm | 9*9*2.3 inch | E57: =IFERROR(__xludf.DUMMYFUNCTION("""COMPUTED_VALUE"""),1) -> 1 | F57: =IFERROR(__xludf.DUMMYFUNCTION("""COMPUTED_VALUE"""),1926) -> 1926 | G57: =IFERROR(__xludf.DUMMYFUNCTION("""COMPUTED_VALUE"""),15) -> 15 | H57: =IFERROR(__xludf.DUMMYFUNCTION("""COMPUTED_VALUE"""),25) -> 25 | I57: =IFERROR(__xludf.DUMMYFUNCTION("""COMPUTED_VALUE"""),100) -> 100 | M57: =IFERROR(__xludf.DUMMYFUNCTION("""COMPUTED_VALUE"""),0.12) -> 0.12 | N57: =IFERROR(__xludf.DUMMYFUNCTION("""COMPUTED_VALUE"""),1) -> 1 | P57: =IFERROR(__xludf.DUMMYFUNCTION("""COMPUTED_VALUE"""),"Offset") -> Offset | Q57: =IFERROR(__xludf.DUMMYFUNCTION("""COMPUTED_VALUE"""),"Packaging") -> Packaging | BC57: =IFERROR(__xludf.DUMMYFUNCTION("""COMPUTED_VALUE"""),"Packaging") -> Packaging | BD57: =IFERROR(__xludf.DUMMYFUNCTION("""COMPUTED_VALUE"""),"Power Plus") -> Power Plus
A58: =IFERROR(__xludf.DUMMYFUNCTION("""COMPUTED_VALUE"""),"https://drive.google.com/open?id=1PI4Qj-_AjnweI9SrJuQ8sE4p2KI5ldj8&authuser=jay.agg%40gmail.com&usp=drive_fs") -> https://drive.google.com/open?id=1PI4Qj-_AjnweI9SrJuQ8sE4p2KI5ldj8&authuser=jay.agg%40gmail.com&usp=drive_fs | B58: =IFERROR(__xludf.DUMMYFUNCTION("""COMPUTED_VALUE"""),"Food") -> Food | C58: =IFERROR(__xludf.DUMMYFUNCTION("""COMPUTED_VALUE"""),"Misc") -> Misc | D58: =IFERROR(__xludf.DUMMYFUNCTION("""COMPUTED_VALUE"""),"140*55*215 mm | 5.5*2.1*8.5 inch") -> 140*55*215 mm | 5.5*2.1*8.5 inch | E58: =IFERROR(__xludf.DUMMYFUNCTION("""COMPUTED_VALUE"""),2) -> 2 | F58: =IFERROR(__xludf.DUMMYFUNCTION("""COMPUTED_VALUE"""),1926) -> 1926 | G58: =IFERROR(__xludf.DUMMYFUNCTION("""COMPUTED_VALUE"""),18) -> 18 | H58: =IFERROR(__xludf.DUMMYFUNCTION("""COMPUTED_VALUE"""),23) -> 23 | I58: =IFERROR(__xludf.DUMMYFUNCTION("""COMPUTED_VALUE"""),100) -> 100 | M58: =IFERROR(__xludf.DUMMYFUNCTION("""COMPUTED_VALUE"""),0.1) -> 0.1 | N58: =IFERROR(__xludf.DUMMYFUNCTION("""COMPUTED_VALUE"""),1) -> 1 | P58: =IFERROR(__xludf.DUMMYFUNCTION("""COMPUTED_VALUE"""),"Offset") -> Offset | Q58: =IFERROR(__xludf.DUMMYFUNCTION("""COMPUTED_VALUE"""),"Packaging") -> Packaging | BC58: =IFERROR(__xludf.DUMMYFUNCTION("""COMPUTED_VALUE"""),"Packaging") -> Packaging | BD58: =IFERROR(__xludf.DUMMYFUNCTION("""COMPUTED_VALUE"""),"Purifier") -> Purifier | BH58: =IFERROR(__xludf.DUMMYFUNCTION("QUERY(Price!BA2:BB50,BN4)"),"#N/A") -> #N/A | BL58: =IFERROR(__xludf.DUMMYFUNCTION("QUERY(Price!BC2:BD15,BM4)"),"Plain") -> Plain | BM58: =IFERROR(__xludf.DUMMYFUNCTION("""COMPUTED_VALUE"""),0) -> 0 | BN58: =IFERROR(__xludf.DUMMYFUNCTION("QUERY(Price!AW2:AX50,BO4)"),"#N/A") -> #N/A
A59: =IFERROR(__xludf.DUMMYFUNCTION("""COMPUTED_VALUE"""),"https://drive.google.com/open?id=1PP_neZsWA5cyLtoIgy7kH8o3NIYpT0kG&authuser=jay.agg%40gmail.com&usp=drive_fs") -> https://drive.google.com/open?id=1PP_neZsWA5cyLtoIgy7kH8o3NIYpT0kG&authuser=jay.agg%40gmail.com&usp=drive_fs | B59: =IFERROR(__xludf.DUMMYFUNCTION("""COMPUTED_VALUE"""),"Food") -> Food | C59: =IFERROR(__xludf.DUMMYFUNCTION("""COMPUTED_VALUE"""),"Misc") -> Misc | D59: =IFERROR(__xludf.DUMMYFUNCTION("""COMPUTED_VALUE"""),"115*55*180 mm | 4.5*2.1*7 inch") -> 115*55*180 mm | 4.5*2.1*7 inch | E59: =IFERROR(__xludf.DUMMYFUNCTION("""COMPUTED_VALUE"""),2) -> 2 | F59: =IFERROR(__xludf.DUMMYFUNCTION("""COMPUTED_VALUE"""),1926) -> 1926 | G59: =IFERROR(__xludf.DUMMYFUNCTION("""COMPUTED_VALUE"""),14) -> 14 | H59: =IFERROR(__xludf.DUMMYFUNCTION("""COMPUTED_VALUE"""),22) -> 22 | I59: =IFERROR(__xludf.DUMMYFUNCTION("""COMPUTED_VALUE"""),100) -> 100 | M59: =IFERROR(__xludf.DUMMYFUNCTION("""COMPUTED_VALUE"""),0.1) -> 0.1 | N59: =IFERROR(__xludf.DUMMYFUNCTION("""COMPUTED_VALUE"""),1) -> 1 | P59: =IFERROR(__xludf.DUMMYFUNCTION("""COMPUTED_VALUE"""),"Offset") -> Offset | Q59: =IFERROR(__xludf.DUMMYFUNCTION("""COMPUTED_VALUE"""),"Packaging") -> Packaging | BC59: =IFERROR(__xludf.DUMMYFUNCTION("""COMPUTED_VALUE"""),"Packaging") -> Packaging | BD59: =IFERROR(__xludf.DUMMYFUNCTION("""COMPUTED_VALUE"""),"Readymer") -> Readymer | CD59: =#REF! -> #REF!
A60: =IFERROR(__xludf.DUMMYFUNCTION("""COMPUTED_VALUE"""),"https://drive.google.com/open?id=1SB1fkOosvR_f90I2hjw3Mt7nTCrWfKpN&authuser=jay.agg%40gmail.com&usp=drive_fs") -> https://drive.google.com/open?id=1SB1fkOosvR_f90I2hjw3Mt7nTCrWfKpN&authuser=jay.agg%40gmail.com&usp=drive_fs | B60: =IFERROR(__xludf.DUMMYFUNCTION("""COMPUTED_VALUE"""),"Food") -> Food | C60: =IFERROR(__xludf.DUMMYFUNCTION("""COMPUTED_VALUE"""),"Pizza") -> Pizza | D60: =IFERROR(__xludf.DUMMYFUNCTION("""COMPUTED_VALUE"""),"67*35*100 mm | 2.6*1.4*3.9 inch") -> 67*35*100 mm | 2.6*1.4*3.9 inch | E60: =IFERROR(__xludf.DUMMYFUNCTION("""COMPUTED_VALUE"""),8) -> 8 | F60: =IFERROR(__xludf.DUMMYFUNCTION("""COMPUTED_VALUE"""),2029) -> 2029 | G60: =IFERROR(__xludf.DUMMYFUNCTION("""COMPUTED_VALUE"""),19) -> 19 | H60: =IFERROR(__xludf.DUMMYFUNCTION("""COMPUTED_VALUE"""),26) -> 26 | I60: =IFERROR(__xludf.DUMMYFUNCTION("""COMPUTED_VALUE"""),100) -> 100 | M60: =IFERROR(__xludf.DUMMYFUNCTION("""COMPUTED_VALUE"""),0.1) -> 0.1 | N60: =IFERROR(__xludf.DUMMYFUNCTION("""COMPUTED_VALUE"""),1) -> 1 | P60: =IFERROR(__xludf.DUMMYFUNCTION("""COMPUTED_VALUE"""),"Offset") -> Offset | Q60: =IFERROR(__xludf.DUMMYFUNCTION("""COMPUTED_VALUE"""),"Packaging") -> Packaging | BC60: =IFERROR(__xludf.DUMMYFUNCTION("""COMPUTED_VALUE"""),"Packaging") -> Packaging | BD60: =IFERROR(__xludf.DUMMYFUNCTION("""COMPUTED_VALUE"""),"Safety Product") -> Safety Product | CC60: Offset | CD60: Met-Pet | CE60: 1926 | CF60: 2841 | CG60: 1 | CH60: 750
A61: =IFERROR(__xludf.DUMMYFUNCTION("""COMPUTED_VALUE"""),"https://drive.google.com/open?id=1TKLWete5--55wBRFs3xveb5fDxiB-I4-&authuser=jay.agg%40gmail.com&usp=drive_fs") -> https://drive.google.com/open?id=1TKLWete5--55wBRFs3xveb5fDxiB-I4-&authuser=jay.agg%40gmail.com&usp=drive_fs | B61: =IFERROR(__xludf.DUMMYFUNCTION("""COMPUTED_VALUE"""),"Food") -> Food | C61: =IFERROR(__xludf.DUMMYFUNCTION("""COMPUTED_VALUE"""),"Misc") -> Misc | D61: =IFERROR(__xludf.DUMMYFUNCTION("""COMPUTED_VALUE"""),"127*38*165 mm | 5*1.5*6.5 inch") -> 127*38*165 mm | 5*1.5*6.5 inch | E61: =IFERROR(__xludf.DUMMYFUNCTION("""COMPUTED_VALUE"""),2) -> 2 | F61: =IFERROR(__xludf.DUMMYFUNCTION("""COMPUTED_VALUE"""),1926) -> 1926 | G61: =IFERROR(__xludf.DUMMYFUNCTION("""COMPUTED_VALUE"""),14) -> 14 | H61: =IFERROR(__xludf.DUMMYFUNCTION("""COMPUTED_VALUE"""),19) -> 19 | I61: =IFERROR(__xludf.DUMMYFUNCTION("""COMPUTED_VALUE"""),100) -> 100 | M61: =IFERROR(__xludf.DUMMYFUNCTION("""COMPUTED_VALUE"""),0.1) -> 0.1 | N61: =IFERROR(__xludf.DUMMYFUNCTION("""COMPUTED_VALUE"""),1) -> 1 | P61: =IFERROR(__xludf.DUMMYFUNCTION("""COMPUTED_VALUE"""),"Offset") -> Offset | Q61: =IFERROR(__xludf.DUMMYFUNCTION("""COMPUTED_VALUE"""),"Packaging") -> Packaging | BC61: =IFERROR(__xludf.DUMMYFUNCTION("""COMPUTED_VALUE"""),"Packaging") -> Packaging | BD61: =IFERROR(__xludf.DUMMYFUNCTION("""COMPUTED_VALUE"""),"Sanitary") -> Sanitary | CC61: Offset | CD61: Met-Pet | CE61: 2029 | CF61: 2841 | CG61: 1 | CH61: 750
A62: =IFERROR(__xludf.DUMMYFUNCTION("""COMPUTED_VALUE"""),"https://drive.google.com/open?id=1TQZw00wR5JvWtj5NG5OjZK3sXFWuSHo8&authuser=jay.agg%40gmail.com&usp=drive_fs") -> https://drive.google.com/open?id=1TQZw00wR5JvWtj5NG5OjZK3sXFWuSHo8&authuser=jay.agg%40gmail.com&usp=drive_fs | B62: =IFERROR(__xludf.DUMMYFUNCTION("""COMPUTED_VALUE"""),"Food") -> Food | C62: =IFERROR(__xludf.DUMMYFUNCTION("""COMPUTED_VALUE"""),"Misc") -> Misc | D62: =IFERROR(__xludf.DUMMYFUNCTION("""COMPUTED_VALUE"""),"Food 90*38*140 mm | 3.5*1.5*5.5 inch") -> Food 90*38*140 mm | 3.5*1.5*5.5 inch | E62: =IFERROR(__xludf.DUMMYFUNCTION("""COMPUTED_VALUE"""),4) -> 4 | F62: =IFERROR(__xludf.DUMMYFUNCTION("""COMPUTED_VALUE"""),1926) -> 1926 | G62: =IFERROR(__xludf.DUMMYFUNCTION("""COMPUTED_VALUE"""),18) -> 18 | H62: =IFERROR(__xludf.DUMMYFUNCTION("""COMPUTED_VALUE"""),23) -> 23 | I62: =IFERROR(__xludf.DUMMYFUNCTION("""COMPUTED_VALUE"""),100) -> 100 | M62: =IFERROR(__xludf.DUMMYFUNCTION("""COMPUTED_VALUE"""),0.1) -> 0.1 | N62: =IFERROR(__xludf.DUMMYFUNCTION("""COMPUTED_VALUE"""),1) -> 1 | P62: =IFERROR(__xludf.DUMMYFUNCTION("""COMPUTED_VALUE"""),"Offset") -> Offset | Q62: =IFERROR(__xludf.DUMMYFUNCTION("""COMPUTED_VALUE"""),"Packaging") -> Packaging | BC62: =IFERROR(__xludf.DUMMYFUNCTION("""COMPUTED_VALUE"""),"Packaging") -> Packaging | BD62: =IFERROR(__xludf.DUMMYFUNCTION("""COMPUTED_VALUE"""),"Sanskriti") -> Sanskriti | BZ62: =IF(BZ64="","","and BZ = '"&BZ64&"'") -> and BZ = 'Printing' | CC62: Offset | CD62: Met-Pet | CE62: 2840 | CF62: 2841 | CG62: 1 | CH62: 750
A63: =IFERROR(__xludf.DUMMYFUNCTION("""COMPUTED_VALUE"""),"https://drive.google.com/open?id=1X5PjIAZXIE8xlRMRcdx9A7o928ykZfZe&authuser=jay.agg%40gmail.com&usp=drive_fs") -> https://drive.google.com/open?id=1X5PjIAZXIE8xlRMRcdx9A7o928ykZfZe&authuser=jay.agg%40gmail.com&usp=drive_fs | B63: =IFERROR(__xludf.DUMMYFUNCTION("""COMPUTED_VALUE"""),"Food") -> Food | C63: =IFERROR(__xludf.DUMMYFUNCTION("""COMPUTED_VALUE"""),"Dog Food") -> Dog Food | D63: =IFERROR(__xludf.DUMMYFUNCTION("""COMPUTED_VALUE"""),"178*76*254 mm | 7*3*10 inch") -> 178*76*254 mm | 7*3*10 inch | E63: =IFERROR(__xludf.DUMMYFUNCTION("""COMPUTED_VALUE"""),1) -> 1 | F63: =IFERROR(__xludf.DUMMYFUNCTION("""COMPUTED_VALUE"""),1926) -> 1926 | G63: =IFERROR(__xludf.DUMMYFUNCTION("""COMPUTED_VALUE"""),15.75) -> 15.75 | H63: =IFERROR(__xludf.DUMMYFUNCTION("""COMPUTED_VALUE"""),20.75) -> 20.75 | I63: =IFERROR(__xludf.DUMMYFUNCTION("""COMPUTED_VALUE"""),100) -> 100 | M63: =IFERROR(__xludf.DUMMYFUNCTION("""COMPUTED_VALUE"""),0.1) -> 0.1 | N63: =IFERROR(__xludf.DUMMYFUNCTION("""COMPUTED_VALUE"""),1) -> 1 | P63: =IFERROR(__xludf.DUMMYFUNCTION("""COMPUTED_VALUE"""),"Offset") -> Offset | Q63: =IFERROR(__xludf.DUMMYFUNCTION("""COMPUTED_VALUE"""),"Packaging") -> Packaging | BC63: =IFERROR(__xludf.DUMMYFUNCTION("""COMPUTED_VALUE"""),"Packaging") -> Packaging | BD63: =IFERROR(__xludf.DUMMYFUNCTION("""COMPUTED_VALUE"""),"Sathwa") -> Sathwa | BZ63: =CONCATENATE("select * where 1=1",BZ62) -> select * where 1=1and BZ = 'Printing' | CC63: Offset | CD63: Printing | CE63: 1926 | CF63: 1926 | CG63: 0 | CH63: =#REF! -> #REF!
A64: =IFERROR(__xludf.DUMMYFUNCTION("""COMPUTED_VALUE"""),"https://drive.google.com/open?id=1XRdxqvruzscLoyb9QY96v6kTiDz1KoV1&authuser=jay.agg%40gmail.com&usp=drive_fs") -> https://drive.google.com/open?id=1XRdxqvruzscLoyb9QY96v6kTiDz1KoV1&authuser=jay.agg%40gmail.com&usp=drive_fs | B64: =IFERROR(__xludf.DUMMYFUNCTION("""COMPUTED_VALUE"""),"Food") -> Food | C64: =IFERROR(__xludf.DUMMYFUNCTION("""COMPUTED_VALUE"""),"Dosa") -> Dosa | D64: =IFERROR(__xludf.DUMMYFUNCTION("""COMPUTED_VALUE"""),"Dosa 220*130*50 mm | 9*5.1*2 inch") -> Dosa 220*130*50 mm | 9*5.1*2 inch | E64: =IFERROR(__xludf.DUMMYFUNCTION("""COMPUTED_VALUE"""),1) -> 1 | F64: =IFERROR(__xludf.DUMMYFUNCTION("""COMPUTED_VALUE"""),1926) -> 1926 | G64: =IFERROR(__xludf.DUMMYFUNCTION("""COMPUTED_VALUE"""),13.7) -> 13.7 | H64: =IFERROR(__xludf.DUMMYFUNCTION("""COMPUTED_VALUE"""),15.75) -> 15.75 | I64: =IFERROR(__xludf.DUMMYFUNCTION("""COMPUTED_VALUE"""),100) -> 100 | M64: =IFERROR(__xludf.DUMMYFUNCTION("""COMPUTED_VALUE"""),0.1) -> 0.1 | N64: =IFERROR(__xludf.DUMMYFUNCTION("""COMPUTED_VALUE"""),1) -> 1 | P64: =IFERROR(__xludf.DUMMYFUNCTION("""COMPUTED_VALUE"""),"Offset") -> Offset | Q64: =IFERROR(__xludf.DUMMYFUNCTION("""COMPUTED_VALUE"""),"Packaging") -> Packaging | BC64: =IFERROR(__xludf.DUMMYFUNCTION("""COMPUTED_VALUE"""),"Packaging") -> Packaging | BD64: =IFERROR(__xludf.DUMMYFUNCTION("""COMPUTED_VALUE"""),"Shipper") -> Shipper | BY64: =Quotation!A29 -> Offset | BZ64: =Quotation!A33 -> Printing | CA64: =Quotation!F34 -> 2029 | CB64: =Quotation!A34 -> New Job | CC64: Offset | CD64: Printing | CE64: 2029 | CF64: 2029 | CG64: 0 | CH64: =#REF! -> #REF!
A65: =IFERROR(__xludf.DUMMYFUNCTION("""COMPUTED_VALUE"""),"https://drive.google.com/open?id=1_aW6Kpq_ImJfWMyFKdVseB6BTAdKY3Mg&authuser=jay.agg%40gmail.com&usp=drive_fs") -> https://drive.google.com/open?id=1_aW6Kpq_ImJfWMyFKdVseB6BTAdKY3Mg&authuser=jay.agg%40gmail.com&usp=drive_fs | B65: =IFERROR(__xludf.DUMMYFUNCTION("""COMPUTED_VALUE"""),"Food") -> Food | C65: =IFERROR(__xludf.DUMMYFUNCTION("""COMPUTED_VALUE"""),"Butter") -> Butter | D65: =IFERROR(__xludf.DUMMYFUNCTION("""COMPUTED_VALUE"""),"1kg 115*90*165 mm | 4.5*3.5*6.5 inch") -> 1kg 115*90*165 mm | 4.5*3.5*6.5 inch | E65: =IFERROR(__xludf.DUMMYFUNCTION("""COMPUTED_VALUE"""),2) -> 2 | F65: =IFERROR(__xludf.DUMMYFUNCTION("""COMPUTED_VALUE"""),1926) -> 1926 | G65: =IFERROR(__xludf.DUMMYFUNCTION("""COMPUTED_VALUE"""),19) -> 19 | H65: =IFERROR(__xludf.DUMMYFUNCTION("""COMPUTED_VALUE"""),26) -> 26 | I65: =IFERROR(__xludf.DUMMYFUNCTION("""COMPUTED_VALUE"""),100) -> 100 | M65: =IFERROR(__xludf.DUMMYFUNCTION("""COMPUTED_VALUE"""),0.1) -> 0.1 | N65: =IFERROR(__xludf.DUMMYFUNCTION("""COMPUTED_VALUE"""),1) -> 1 | P65: =IFERROR(__xludf.DUMMYFUNCTION("""COMPUTED_VALUE"""),"Offset") -> Offset | Q65: =IFERROR(__xludf.DUMMYFUNCTION("""COMPUTED_VALUE"""),"Packaging") -> Packaging | BC65: =IFERROR(__xludf.DUMMYFUNCTION("""COMPUTED_VALUE"""),"Packaging") -> Packaging | BD65: =IFERROR(__xludf.DUMMYFUNCTION("""COMPUTED_VALUE"""),"Shoe") -> Shoe | BY65: =IF(BY64="","","and CC = '"&BY64&"'") -> and CC = 'Offset' | BZ65: =IF(BZ64="","","and CD = '"&BZ64&"'") -> and CD = 'Printing' | CA65: =IF(CA64="","","and CA = "&CA64&"") -> and CA = 2029 | CB65: =IF(CB64="","","and CD = '"&CB64&"'") -> and CD = 'New Job' | CC65: Offset | CD65: Printing | CE65: 2840 | CF65: 2840 | CG65: 0 | CH65: =#REF! -> #REF!
A66: =IFERROR(__xludf.DUMMYFUNCTION("""COMPUTED_VALUE"""),"https://drive.google.com/open?id=12FIiLxoPpTrdQa5g9hjGPxPQQzXqY7NY&authuser=jay.agg%40gmail.com&usp=drive_fs") -> https://drive.google.com/open?id=12FIiLxoPpTrdQa5g9hjGPxPQQzXqY7NY&authuser=jay.agg%40gmail.com&usp=drive_fs | B66: =IFERROR(__xludf.DUMMYFUNCTION("""COMPUTED_VALUE"""),"Food") -> Food | C66: =IFERROR(__xludf.DUMMYFUNCTION("""COMPUTED_VALUE"""),"Fast Food") -> Fast Food | D66: =IFERROR(__xludf.DUMMYFUNCTION("""COMPUTED_VALUE"""),"Shawrama 115*115*420 mm | 4.5*4.5*16.5 inch") -> Shawrama 115*115*420 mm | 4.5*4.5*16.5 inch | E66: =IFERROR(__xludf.DUMMYFUNCTION("""COMPUTED_VALUE"""),1) -> 1 | F66: =IFERROR(__xludf.DUMMYFUNCTION("""COMPUTED_VALUE"""),2029) -> 2029 | G66: =IFERROR(__xludf.DUMMYFUNCTION("""COMPUTED_VALUE"""),19) -> 19 | H66: =IFERROR(__xludf.DUMMYFUNCTION("""COMPUTED_VALUE"""),28) -> 28 | I66: =IFERROR(__xludf.DUMMYFUNCTION("""COMPUTED_VALUE"""),100) -> 100 | M66: =IFERROR(__xludf.DUMMYFUNCTION("""COMPUTED_VALUE"""),0.1) -> 0.1 | N66: =IFERROR(__xludf.DUMMYFUNCTION("""COMPUTED_VALUE"""),1) -> 1 | P66: =IFERROR(__xludf.DUMMYFUNCTION("""COMPUTED_VALUE"""),"Offset") -> Offset | Q66: =IFERROR(__xludf.DUMMYFUNCTION("""COMPUTED_VALUE"""),"Packaging") -> Packaging | BC66: =IFERROR(__xludf.DUMMYFUNCTION("""COMPUTED_VALUE"""),"Packaging") -> Packaging | BD66: =IFERROR(__xludf.DUMMYFUNCTION("""COMPUTED_VALUE"""),"Stationery") -> Stationery | BY66: =CONCATENATE("select * where 1=1",BY65) -> select * where 1=1and CC = 'Offset' | BZ66: =CONCATENATE("select * where 1=1",BZ65) -> select * where 1=1and CD = 'Printing' | CA66: =CONCATENATE("select * where 1=1",CA65) -> select * where 1=1and CA = 2029 | CB66: =CONCATENATE("select * where 1=1",CB65) -> select * where 1=1and CD = 'New Job' | CC66: Flexible | CD66: Printing | CE66: 1001 | CF66: 1001 | CG66: 0
A67: =IFERROR(__xludf.DUMMYFUNCTION("""COMPUTED_VALUE"""),"https://drive.google.com/open?id=17Cs2gXrf0bk_owVb5U8fSdi86T1r_Le4&authuser=jay.agg%40gmail.com&usp=drive_fs") -> https://drive.google.com/open?id=17Cs2gXrf0bk_owVb5U8fSdi86T1r_Le4&authuser=jay.agg%40gmail.com&usp=drive_fs | B67: =IFERROR(__xludf.DUMMYFUNCTION("""COMPUTED_VALUE"""),"Food") -> Food | C67: =IFERROR(__xludf.DUMMYFUNCTION("""COMPUTED_VALUE"""),"Rusk") -> Rusk | D67: =IFERROR(__xludf.DUMMYFUNCTION("""COMPUTED_VALUE"""),"170*116*270 mm | 6.7*4.6*10.6 inch") -> 170*116*270 mm | 6.7*4.6*10.6 inch | E67: =IFERROR(__xludf.DUMMYFUNCTION("""COMPUTED_VALUE"""),1) -> 1 | F67: =IFERROR(__xludf.DUMMYFUNCTION("""COMPUTED_VALUE"""),2029) -> 2029 | G67: =IFERROR(__xludf.DUMMYFUNCTION("""COMPUTED_VALUE"""),19.5) -> 19.5 | H67: =IFERROR(__xludf.DUMMYFUNCTION("""COMPUTED_VALUE"""),23) -> 23 | I67: =IFERROR(__xludf.DUMMYFUNCTION("""COMPUTED_VALUE"""),100) -> 100 | M67: =IFERROR(__xludf.DUMMYFUNCTION("""COMPUTED_VALUE"""),0.1) -> 0.1 | N67: =IFERROR(__xludf.DUMMYFUNCTION("""COMPUTED_VALUE"""),1) -> 1 | P67: =IFERROR(__xludf.DUMMYFUNCTION("""COMPUTED_VALUE"""),"Offset") -> Offset | Q67: =IFERROR(__xludf.DUMMYFUNCTION("""COMPUTED_VALUE"""),"Packaging") -> Packaging | BC67: =IFERROR(__xludf.DUMMYFUNCTION("""COMPUTED_VALUE"""),"Packaging") -> Packaging | BD67: =IFERROR(__xludf.DUMMYFUNCTION("""COMPUTED_VALUE"""),"The Man Company") -> The Man Company | BY67: =IFERROR(__xludf.DUMMYFUNCTION("QUERY(CC60:CF71,BY66)"),"Offset") -> Offset | BZ67: =IFERROR(__xludf.DUMMYFUNCTION("""COMPUTED_VALUE"""),"Met-Pet") -> Met-Pet | CA67: =IFERROR(__xludf.DUMMYFUNCTION("""COMPUTED_VALUE"""),1926) -> 1926 | CB67: =IFERROR(__xludf.DUMMYFUNCTION("""COMPUTED_VALUE"""),2841) -> 2841 | CC67: Flexible | CD67: Printing | CE67: 1002 | CF67: 1002 | CG67: 0
A68: =IFERROR(__xludf.DUMMYFUNCTION("""COMPUTED_VALUE"""),"https://drive.google.com/open?id=1Crzlye474h-9wF00fQsxJwyCqlOGjSD8&authuser=jay.agg%40gmail.com&usp=drive_fs") -> https://drive.google.com/open?id=1Crzlye474h-9wF00fQsxJwyCqlOGjSD8&authuser=jay.agg%40gmail.com&usp=drive_fs | B68: =IFERROR(__xludf.DUMMYFUNCTION("""COMPUTED_VALUE"""),"Food") -> Food | C68: =IFERROR(__xludf.DUMMYFUNCTION("""COMPUTED_VALUE"""),"Misc") -> Misc | D68: =IFERROR(__xludf.DUMMYFUNCTION("""COMPUTED_VALUE"""),"127*25*203 mm | 5*1*8 inch") -> 127*25*203 mm | 5*1*8 inch | E68: =IFERROR(__xludf.DUMMYFUNCTION("""COMPUTED_VALUE"""),4) -> 4 | F68: =IFERROR(__xludf.DUMMYFUNCTION("""COMPUTED_VALUE"""),2029) -> 2029 | G68: =IFERROR(__xludf.DUMMYFUNCTION("""COMPUTED_VALUE"""),20) -> 20 | H68: =IFERROR(__xludf.DUMMYFUNCTION("""COMPUTED_VALUE"""),28) -> 28 | I68: =IFERROR(__xludf.DUMMYFUNCTION("""COMPUTED_VALUE"""),100) -> 100 | M68: =IFERROR(__xludf.DUMMYFUNCTION("""COMPUTED_VALUE"""),0.1) -> 0.1 | N68: =IFERROR(__xludf.DUMMYFUNCTION("""COMPUTED_VALUE"""),1) -> 1 | P68: =IFERROR(__xludf.DUMMYFUNCTION("""COMPUTED_VALUE"""),"Offset") -> Offset | Q68: =IFERROR(__xludf.DUMMYFUNCTION("""COMPUTED_VALUE"""),"Packaging") -> Packaging | BC68: =IFERROR(__xludf.DUMMYFUNCTION("""COMPUTED_VALUE"""),"Packaging") -> Packaging | BD68: =IFERROR(__xludf.DUMMYFUNCTION("""COMPUTED_VALUE"""),"Toy") -> Toy | BY68: =IFERROR(__xludf.DUMMYFUNCTION("""COMPUTED_VALUE"""),"Offset") -> Offset | BZ68: =IFERROR(__xludf.DUMMYFUNCTION("""COMPUTED_VALUE"""),"Met-Pet") -> Met-Pet | CA68: =IFERROR(__xludf.DUMMYFUNCTION("""COMPUTED_VALUE"""),2029) -> 2029 | CB68: =IFERROR(__xludf.DUMMYFUNCTION("""COMPUTED_VALUE"""),2841) -> 2841 | CC68: Flexible | CD68: Printing | CE68: 1003 | CF68: 1003 | CG68: 0
A69: =IFERROR(__xludf.DUMMYFUNCTION("""COMPUTED_VALUE"""),"https://drive.google.com/open?id=1DDicBlFYcVtWEZF0YUdJ8f7l9y1UIKJw&authuser=jay.agg%40gmail.com&usp=drive_fs") -> https://drive.google.com/open?id=1DDicBlFYcVtWEZF0YUdJ8f7l9y1UIKJw&authuser=jay.agg%40gmail.com&usp=drive_fs | B69: =IFERROR(__xludf.DUMMYFUNCTION("""COMPUTED_VALUE"""),"Food") -> Food | C69: =IFERROR(__xludf.DUMMYFUNCTION("""COMPUTED_VALUE"""),"Dosa") -> Dosa | D69: =IFERROR(__xludf.DUMMYFUNCTION("""COMPUTED_VALUE"""),"Dosa 305*76*38 mm | 12*3*1.5 inch") -> Dosa 305*76*38 mm | 12*3*1.5 inch | E69: =IFERROR(__xludf.DUMMYFUNCTION("""COMPUTED_VALUE"""),2) -> 2 | F69: =IFERROR(__xludf.DUMMYFUNCTION("""COMPUTED_VALUE"""),1926) -> 1926 | G69: =IFERROR(__xludf.DUMMYFUNCTION("""COMPUTED_VALUE"""),15.75) -> 15.75 | H69: =IFERROR(__xludf.DUMMYFUNCTION("""COMPUTED_VALUE"""),20.75) -> 20.75 | I69: =IFERROR(__xludf.DUMMYFUNCTION("""COMPUTED_VALUE"""),100) -> 100 | M69: =IFERROR(__xludf.DUMMYFUNCTION("""COMPUTED_VALUE"""),0.1) -> 0.1 | N69: =IFERROR(__xludf.DUMMYFUNCTION("""COMPUTED_VALUE"""),1) -> 1 | P69: =IFERROR(__xludf.DUMMYFUNCTION("""COMPUTED_VALUE"""),"Offset") -> Offset | Q69: =IFERROR(__xludf.DUMMYFUNCTION("""COMPUTED_VALUE"""),"Packaging") -> Packaging | BC69: =IFERROR(__xludf.DUMMYFUNCTION("""COMPUTED_VALUE"""),"Packaging") -> Packaging | BD69: =IFERROR(__xludf.DUMMYFUNCTION("""COMPUTED_VALUE"""),"Xpider") -> Xpider | BY69: =IFERROR(__xludf.DUMMYFUNCTION("""COMPUTED_VALUE"""),"Offset") -> Offset | BZ69: =IFERROR(__xludf.DUMMYFUNCTION("""COMPUTED_VALUE"""),"Met-Pet") -> Met-Pet | CA69: =IFERROR(__xludf.DUMMYFUNCTION("""COMPUTED_VALUE"""),2840) -> 2840 | CB69: =IFERROR(__xludf.DUMMYFUNCTION("""COMPUTED_VALUE"""),2841) -> 2841 | CC69: Flexible | CD69: Printing | CE69: 1004 | CF69: 1004 | CG69: 0
A70: =IFERROR(__xludf.DUMMYFUNCTION("""COMPUTED_VALUE"""),"https://drive.google.com/open?id=1S0JoeVa-x8xAselnMXu64Vmh1ngS_Cud&authuser=jay.agg%40gmail.com&usp=drive_fs") -> https://drive.google.com/open?id=1S0JoeVa-x8xAselnMXu64Vmh1ngS_Cud&authuser=jay.agg%40gmail.com&usp=drive_fs | B70: =IFERROR(__xludf.DUMMYFUNCTION("""COMPUTED_VALUE"""),"Food") -> Food | C70: =IFERROR(__xludf.DUMMYFUNCTION("""COMPUTED_VALUE"""),"Wrap") -> Wrap | D70: =IFERROR(__xludf.DUMMYFUNCTION("""COMPUTED_VALUE"""),"97*255 mm | 3.8*10 inch") -> 97*255 mm | 3.8*10 inch | E70: =IFERROR(__xludf.DUMMYFUNCTION("""COMPUTED_VALUE"""),4) -> 4 | F70: =IFERROR(__xludf.DUMMYFUNCTION("""COMPUTED_VALUE"""),2029) -> 2029 | G70: =IFERROR(__xludf.DUMMYFUNCTION("""COMPUTED_VALUE"""),18) -> 18 | H70: =IFERROR(__xludf.DUMMYFUNCTION("""COMPUTED_VALUE"""),25) -> 25 | I70: =IFERROR(__xludf.DUMMYFUNCTION("""COMPUTED_VALUE"""),100) -> 100 | M70: =IFERROR(__xludf.DUMMYFUNCTION("""COMPUTED_VALUE"""),0.12) -> 0.12 | N70: =IFERROR(__xludf.DUMMYFUNCTION("""COMPUTED_VALUE"""),1) -> 1 | P70: =IFERROR(__xludf.DUMMYFUNCTION("""COMPUTED_VALUE"""),"Offset") -> Offset | Q70: =IFERROR(__xludf.DUMMYFUNCTION("""COMPUTED_VALUE"""),"Packaging") -> Packaging | BY70: =IFERROR(__xludf.DUMMYFUNCTION("""COMPUTED_VALUE"""),"Offset") -> Offset | BZ70: =IFERROR(__xludf.DUMMYFUNCTION("""COMPUTED_VALUE"""),"Printing") -> Printing | CA70: =IFERROR(__xludf.DUMMYFUNCTION("""COMPUTED_VALUE"""),1926) -> 1926 | CB70: =IFERROR(__xludf.DUMMYFUNCTION("""COMPUTED_VALUE"""),1926) -> 1926 | CC70: Flexible | CD70: Printing | CE70: 1005 | CF70: 1005 | CG70: 0
A71: =IFERROR(__xludf.DUMMYFUNCTION("""COMPUTED_VALUE"""),"https://drive.google.com/open?id=1AUtF9453AsscwlYGhU2_slTjqLRIF5-J&authuser=jay.agg%40gmail.com&usp=drive_fs") -> https://drive.google.com/open?id=1AUtF9453AsscwlYGhU2_slTjqLRIF5-J&authuser=jay.agg%40gmail.com&usp=drive_fs | B71: =IFERROR(__xludf.DUMMYFUNCTION("""COMPUTED_VALUE"""),"Food") -> Food | C71: =IFERROR(__xludf.DUMMYFUNCTION("""COMPUTED_VALUE"""),"Chocolate") -> Chocolate | D71: =IFERROR(__xludf.DUMMYFUNCTION("""COMPUTED_VALUE"""),"200*100*40 mm | 7.8*3.9*1.6 inch W 2*3 inch") -> 200*100*40 mm | 7.8*3.9*1.6 inch W 2*3 inch | E71: =IFERROR(__xludf.DUMMYFUNCTION("""COMPUTED_VALUE"""),2) -> 2 | F71: =IFERROR(__xludf.DUMMYFUNCTION("""COMPUTED_VALUE"""),2029) -> 2029 | G71: =IFERROR(__xludf.DUMMYFUNCTION("""COMPUTED_VALUE"""),19) -> 19 | H71: =IFERROR(__xludf.DUMMYFUNCTION("""COMPUTED_VALUE"""),26) -> 26 | I71: =IFERROR(__xludf.DUMMYFUNCTION("""COMPUTED_VALUE"""),100) -> 100 | L71: =IFERROR(__xludf.DUMMYFUNCTION("""COMPUTED_VALUE"""),1.2) -> 1.2 | M71: =IFERROR(__xludf.DUMMYFUNCTION("""COMPUTED_VALUE"""),0.16) -> 0.16 | N71: =IFERROR(__xludf.DUMMYFUNCTION("""COMPUTED_VALUE"""),1) -> 1 | P71: =IFERROR(__xludf.DUMMYFUNCTION("""COMPUTED_VALUE"""),"Offset") -> Offset | Q71: =IFERROR(__xludf.DUMMYFUNCTION("""COMPUTED_VALUE"""),"Packaging") -> Packaging | BY71: =IFERROR(__xludf.DUMMYFUNCTION("""COMPUTED_VALUE"""),"Offset") -> Offset | BZ71: =IFERROR(__xludf.DUMMYFUNCTION("""COMPUTED_VALUE"""),"Printing") -> Printing | CA71: =IFERROR(__xludf.DUMMYFUNCTION("""COMPUTED_VALUE"""),2029) -> 2029 | CB71: =IFERROR(__xludf.DUMMYFUNCTION("""COMPUTED_VALUE"""),2029) -> 2029
A72: =IFERROR(__xludf.DUMMYFUNCTION("""COMPUTED_VALUE"""),"https://drive.google.com/open?id=1BAIIhR_t7CFMjNdm29pTFbTOYqLj8-1N&authuser=jay.agg%40gmail.com&usp=drive_fs") -> https://drive.google.com/open?id=1BAIIhR_t7CFMjNdm29pTFbTOYqLj8-1N&authuser=jay.agg%40gmail.com&usp=drive_fs | B72: =IFERROR(__xludf.DUMMYFUNCTION("""COMPUTED_VALUE"""),"Food") -> Food | C72: =IFERROR(__xludf.DUMMYFUNCTION("""COMPUTED_VALUE"""),"Misc") -> Misc | D72: =IFERROR(__xludf.DUMMYFUNCTION("""COMPUTED_VALUE"""),"90*90*90 mm | 3.5*3.5*3.5 inch") -> 90*90*90 mm | 3.5*3.5*3.5 inch | E72: =IFERROR(__xludf.DUMMYFUNCTION("""COMPUTED_VALUE"""),2) -> 2 | F72: =IFERROR(__xludf.DUMMYFUNCTION("""COMPUTED_VALUE"""),2029) -> 2029 | G72: =IFERROR(__xludf.DUMMYFUNCTION("""COMPUTED_VALUE"""),15.75) -> 15.75 | H72: =IFERROR(__xludf.DUMMYFUNCTION("""COMPUTED_VALUE"""),20.75) -> 20.75 | I72: =IFERROR(__xludf.DUMMYFUNCTION("""COMPUTED_VALUE"""),100) -> 100 | M72: =IFERROR(__xludf.DUMMYFUNCTION("""COMPUTED_VALUE"""),0.1) -> 0.1 | N72: =IFERROR(__xludf.DUMMYFUNCTION("""COMPUTED_VALUE"""),1) -> 1 | P72: =IFERROR(__xludf.DUMMYFUNCTION("""COMPUTED_VALUE"""),"Offset") -> Offset | Q72: =IFERROR(__xludf.DUMMYFUNCTION("""COMPUTED_VALUE"""),"Packaging") -> Packaging | BY72: =IFERROR(__xludf.DUMMYFUNCTION("""COMPUTED_VALUE"""),"Offset") -> Offset | BZ72: =IFERROR(__xludf.DUMMYFUNCTION("""COMPUTED_VALUE"""),"Printing") -> Printing | CA72: =IFERROR(__xludf.DUMMYFUNCTION("""COMPUTED_VALUE"""),2840) -> 2840 | CB72: =IFERROR(__xludf.DUMMYFUNCTION("""COMPUTED_VALUE"""),2840) -> 2840
A73: =IFERROR(__xludf.DUMMYFUNCTION("""COMPUTED_VALUE"""),"https://drive.google.com/open?id=1ByfbDMn70rz3SfUWd9dftPugVYPyZXSX&authuser=jay.agg%40gmail.com&usp=drive_fs") -> https://drive.google.com/open?id=1ByfbDMn70rz3SfUWd9dftPugVYPyZXSX&authuser=jay.agg%40gmail.com&usp=drive_fs | B73: =IFERROR(__xludf.DUMMYFUNCTION("""COMPUTED_VALUE"""),"Food") -> Food | C73: =IFERROR(__xludf.DUMMYFUNCTION("""COMPUTED_VALUE"""),"Misc") -> Misc | D73: =IFERROR(__xludf.DUMMYFUNCTION("""COMPUTED_VALUE"""),"73*30*70 mm | 2.8*1.2*2.75 inch") -> 73*30*70 mm | 2.8*1.2*2.75 inch | E73: =IFERROR(__xludf.DUMMYFUNCTION("""COMPUTED_VALUE"""),10) -> 10 | F73: =IFERROR(__xludf.DUMMYFUNCTION("""COMPUTED_VALUE"""),2029) -> 2029 | G73: =IFERROR(__xludf.DUMMYFUNCTION("""COMPUTED_VALUE"""),18) -> 18 | H73: =IFERROR(__xludf.DUMMYFUNCTION("""COMPUTED_VALUE"""),23) -> 23 | I73: =IFERROR(__xludf.DUMMYFUNCTION("""COMPUTED_VALUE"""),100) -> 100 | M73: =IFERROR(__xludf.DUMMYFUNCTION("""COMPUTED_VALUE"""),0.1) -> 0.1 | N73: =IFERROR(__xludf.DUMMYFUNCTION("""COMPUTED_VALUE"""),1) -> 1 | P73: =IFERROR(__xludf.DUMMYFUNCTION("""COMPUTED_VALUE"""),"Offset") -> Offset | Q73: =IFERROR(__xludf.DUMMYFUNCTION("""COMPUTED_VALUE"""),"Packaging") -> Packaging
A74: =IFERROR(__xludf.DUMMYFUNCTION("""COMPUTED_VALUE"""),"https://drive.google.com/open?id=1C22Fmp-iikp8lJHK8I3Zzh_qgIItIU1e&authuser=jay.agg%40gmail.com&usp=drive_fs") -> https://drive.google.com/open?id=1C22Fmp-iikp8lJHK8I3Zzh_qgIItIU1e&authuser=jay.agg%40gmail.com&usp=drive_fs | B74: =IFERROR(__xludf.DUMMYFUNCTION("""COMPUTED_VALUE"""),"Food") -> Food | C74: =IFERROR(__xludf.DUMMYFUNCTION("""COMPUTED_VALUE"""),"Misc") -> Misc | D74: =IFERROR(__xludf.DUMMYFUNCTION("""COMPUTED_VALUE"""),"168*84*220 mm | 6.6*3.3*8.6 inch") -> 168*84*220 mm | 6.6*3.3*8.6 inch | E74: =IFERROR(__xludf.DUMMYFUNCTION("""COMPUTED_VALUE"""),1) -> 1 | F74: =IFERROR(__xludf.DUMMYFUNCTION("""COMPUTED_VALUE"""),2029) -> 2029 | G74: =IFERROR(__xludf.DUMMYFUNCTION("""COMPUTED_VALUE"""),15.75) -> 15.75 | H74: =IFERROR(__xludf.DUMMYFUNCTION("""COMPUTED_VALUE"""),20.75) -> 20.75 | I74: =IFERROR(__xludf.DUMMYFUNCTION("""COMPUTED_VALUE"""),100) -> 100 | M74: =IFERROR(__xludf.DUMMYFUNCTION("""COMPUTED_VALUE"""),0.1) -> 0.1 | N74: =IFERROR(__xludf.DUMMYFUNCTION("""COMPUTED_VALUE"""),1) -> 1 | P74: =IFERROR(__xludf.DUMMYFUNCTION("""COMPUTED_VALUE"""),"Offset") -> Offset | Q74: =IFERROR(__xludf.DUMMYFUNCTION("""COMPUTED_VALUE"""),"Packaging") -> Packaging | BY74: =IFERROR(__xludf.DUMMYFUNCTION("QUERY(CD60:CH70,BZ66)"),"Printing") -> Printing | BZ74: =IFERROR(__xludf.DUMMYFUNCTION("""COMPUTED_VALUE"""),1926) -> 1926 | CA74: =IFERROR(__xludf.DUMMYFUNCTION("""COMPUTED_VALUE"""),1926) -> 1926 | CB74: =IFERROR(__xludf.DUMMYFUNCTION("""COMPUTED_VALUE"""),0) -> 0 | CC74: =IFERROR(__xludf.DUMMYFUNCTION("""COMPUTED_VALUE"""),250) -> 250 | CD74: =IFERROR(__xludf.DUMMYFUNCTION("QUERY(BZ74:CC80,CA66)"),2029) -> 2029 | CE74: =IFERROR(__xludf.DUMMYFUNCTION("""COMPUTED_VALUE"""),2029) -> 2029 | CF74: =IFERROR(__xludf.DUMMYFUNCTION("""COMPUTED_VALUE"""),0) -> 0 | CG74: =IFERROR(__xludf.DUMMYFUNCTION("""COMPUTED_VALUE"""),275) -> 275
A75: =IFERROR(__xludf.DUMMYFUNCTION("""COMPUTED_VALUE"""),"https://drive.google.com/open?id=1CKqQpvLGbMzH2O6QTTazvgUpvzQlllMB&authuser=jay.agg%40gmail.com&usp=drive_fs") -> https://drive.google.com/open?id=1CKqQpvLGbMzH2O6QTTazvgUpvzQlllMB&authuser=jay.agg%40gmail.com&usp=drive_fs | B75: =IFERROR(__xludf.DUMMYFUNCTION("""COMPUTED_VALUE"""),"Food") -> Food | C75: =IFERROR(__xludf.DUMMYFUNCTION("""COMPUTED_VALUE"""),"Millet") -> Millet | D75: =IFERROR(__xludf.DUMMYFUNCTION("""COMPUTED_VALUE"""),"1KG 165*65*210 mm | 6.5*2.6*8.3 inch") -> 1KG 165*65*210 mm | 6.5*2.6*8.3 inch | E75: =IFERROR(__xludf.DUMMYFUNCTION("""COMPUTED_VALUE"""),2) -> 2 | F75: =IFERROR(__xludf.DUMMYFUNCTION("""COMPUTED_VALUE"""),2029) -> 2029 | G75: =IFERROR(__xludf.DUMMYFUNCTION("""COMPUTED_VALUE"""),19) -> 19 | H75: =IFERROR(__xludf.DUMMYFUNCTION("""COMPUTED_VALUE"""),26) -> 26 | I75: =IFERROR(__xludf.DUMMYFUNCTION("""COMPUTED_VALUE"""),100) -> 100 | M75: =IFERROR(__xludf.DUMMYFUNCTION("""COMPUTED_VALUE"""),0.1) -> 0.1 | N75: =IFERROR(__xludf.DUMMYFUNCTION("""COMPUTED_VALUE"""),1) -> 1 | P75: =IFERROR(__xludf.DUMMYFUNCTION("""COMPUTED_VALUE"""),"Offset") -> Offset | Q75: =IFERROR(__xludf.DUMMYFUNCTION("""COMPUTED_VALUE"""),"Packaging") -> Packaging | BY75: =IFERROR(__xludf.DUMMYFUNCTION("""COMPUTED_VALUE"""),"Printing") -> Printing | BZ75: =IFERROR(__xludf.DUMMYFUNCTION("""COMPUTED_VALUE"""),2029) -> 2029 | CA75: =IFERROR(__xludf.DUMMYFUNCTION("""COMPUTED_VALUE"""),2029) -> 2029 | CB75: =IFERROR(__xludf.DUMMYFUNCTION("""COMPUTED_VALUE"""),0) -> 0 | CC75: =IFERROR(__xludf.DUMMYFUNCTION("""COMPUTED_VALUE"""),275) -> 275
A76: =IFERROR(__xludf.DUMMYFUNCTION("""COMPUTED_VALUE"""),"https://drive.google.com/open?id=1D5PrDkRh5NSfwGGrMo9-8-3--WX3L0Ft&authuser=jay.agg%40gmail.com&usp=drive_fs") -> https://drive.google.com/open?id=1D5PrDkRh5NSfwGGrMo9-8-3--WX3L0Ft&authuser=jay.agg%40gmail.com&usp=drive_fs | B76: =IFERROR(__xludf.DUMMYFUNCTION("""COMPUTED_VALUE"""),"Food") -> Food | C76: =IFERROR(__xludf.DUMMYFUNCTION("""COMPUTED_VALUE"""),"Millet") -> Millet | D76: =IFERROR(__xludf.DUMMYFUNCTION("""COMPUTED_VALUE"""),"500g145*64*160 mm | 5.7*2.5*6.3 inch") -> 500g145*64*160 mm | 5.7*2.5*6.3 inch | E76: =IFERROR(__xludf.DUMMYFUNCTION("""COMPUTED_VALUE"""),2) -> 2 | F76: =IFERROR(__xludf.DUMMYFUNCTION("""COMPUTED_VALUE"""),2029) -> 2029 | G76: =IFERROR(__xludf.DUMMYFUNCTION("""COMPUTED_VALUE"""),18) -> 18 | H76: =IFERROR(__xludf.DUMMYFUNCTION("""COMPUTED_VALUE"""),23) -> 23 | I76: =IFERROR(__xludf.DUMMYFUNCTION("""COMPUTED_VALUE"""),100) -> 100 | M76: =IFERROR(__xludf.DUMMYFUNCTION("""COMPUTED_VALUE"""),0.1) -> 0.1 | N76: =IFERROR(__xludf.DUMMYFUNCTION("""COMPUTED_VALUE"""),1) -> 1 | P76: =IFERROR(__xludf.DUMMYFUNCTION("""COMPUTED_VALUE"""),"Offset") -> Offset | Q76: =IFERROR(__xludf.DUMMYFUNCTION("""COMPUTED_VALUE"""),"Packaging") -> Packaging | BY76: =IFERROR(__xludf.DUMMYFUNCTION("""COMPUTED_VALUE"""),"Printing") -> Printing | BZ76: =IFERROR(__xludf.DUMMYFUNCTION("""COMPUTED_VALUE"""),2840) -> 2840 | CA76: =IFERROR(__xludf.DUMMYFUNCTION("""COMPUTED_VALUE"""),2840) -> 2840 | CB76: =IFERROR(__xludf.DUMMYFUNCTION("""COMPUTED_VALUE"""),0) -> 0 | CC76: =IFERROR(__xludf.DUMMYFUNCTION("""COMPUTED_VALUE"""),650) -> 650
A77: =IFERROR(__xludf.DUMMYFUNCTION("""COMPUTED_VALUE"""),"https://drive.google.com/open?id=1D6D48kO1Ul1ZLDDzrzde2t-VuNuOQ4v4&authuser=jay.agg%40gmail.com&usp=drive_fs") -> https://drive.google.com/open?id=1D6D48kO1Ul1ZLDDzrzde2t-VuNuOQ4v4&authuser=jay.agg%40gmail.com&usp=drive_fs | B77: =IFERROR(__xludf.DUMMYFUNCTION("""COMPUTED_VALUE"""),"Food") -> Food | C77: =IFERROR(__xludf.DUMMYFUNCTION("""COMPUTED_VALUE"""),"Peanut") -> Peanut | D77: =IFERROR(__xludf.DUMMYFUNCTION("""COMPUTED_VALUE"""),"120*120*160 mm | 4.7*4.7*6.3 inch") -> 120*120*160 mm | 4.7*4.7*6.3 inch | E77: =IFERROR(__xludf.DUMMYFUNCTION("""COMPUTED_VALUE"""),2) -> 2 | F77: =IFERROR(__xludf.DUMMYFUNCTION("""COMPUTED_VALUE"""),2029) -> 2029 | G77: =IFERROR(__xludf.DUMMYFUNCTION("""COMPUTED_VALUE"""),20) -> 20 | H77: =IFERROR(__xludf.DUMMYFUNCTION("""COMPUTED_VALUE"""),28) -> 28 | I77: =IFERROR(__xludf.DUMMYFUNCTION("""COMPUTED_VALUE"""),100) -> 100 | M77: =IFERROR(__xludf.DUMMYFUNCTION("""COMPUTED_VALUE"""),0.1) -> 0.1 | N77: =IFERROR(__xludf.DUMMYFUNCTION("""COMPUTED_VALUE"""),1) -> 1 | P77: =IFERROR(__xludf.DUMMYFUNCTION("""COMPUTED_VALUE"""),"Offset") -> Offset | Q77: =IFERROR(__xludf.DUMMYFUNCTION("""COMPUTED_VALUE"""),"Packaging") -> Packaging | BY77: =IFERROR(__xludf.DUMMYFUNCTION("""COMPUTED_VALUE"""),"Printing") -> Printing | BZ77: =IFERROR(__xludf.DUMMYFUNCTION("""COMPUTED_VALUE"""),1001) -> 1001 | CA77: =IFERROR(__xludf.DUMMYFUNCTION("""COMPUTED_VALUE"""),1001) -> 1001 | CB77: =IFERROR(__xludf.DUMMYFUNCTION("""COMPUTED_VALUE"""),0) -> 0
A78: =IFERROR(__xludf.DUMMYFUNCTION("""COMPUTED_VALUE"""),"https://drive.google.com/open?id=1DH_jtAZrmS4oA_LljmC6xnetppeIi0w7&authuser=jay.agg%40gmail.com&usp=drive_fs") -> https://drive.google.com/open?id=1DH_jtAZrmS4oA_LljmC6xnetppeIi0w7&authuser=jay.agg%40gmail.com&usp=drive_fs | B78: =IFERROR(__xludf.DUMMYFUNCTION("""COMPUTED_VALUE"""),"Food") -> Food | C78: =IFERROR(__xludf.DUMMYFUNCTION("""COMPUTED_VALUE"""),"Chocolate") -> Chocolate | D78: =IFERROR(__xludf.DUMMYFUNCTION("""COMPUTED_VALUE"""),"85*8.5*155 mm | 3.3*0.3*6.1 inch") -> 85*8.5*155 mm | 3.3*0.3*6.1 inch | E78: =IFERROR(__xludf.DUMMYFUNCTION("""COMPUTED_VALUE"""),6) -> 6 | F78: =IFERROR(__xludf.DUMMYFUNCTION("""COMPUTED_VALUE"""),2029) -> 2029 | G78: =IFERROR(__xludf.DUMMYFUNCTION("""COMPUTED_VALUE"""),18) -> 18 | H78: =IFERROR(__xludf.DUMMYFUNCTION("""COMPUTED_VALUE"""),23) -> 23 | I78: =IFERROR(__xludf.DUMMYFUNCTION("""COMPUTED_VALUE"""),100) -> 100 | M78: =IFERROR(__xludf.DUMMYFUNCTION("""COMPUTED_VALUE"""),0.12) -> 0.12 | N78: =IFERROR(__xludf.DUMMYFUNCTION("""COMPUTED_VALUE"""),1) -> 1 | P78: =IFERROR(__xludf.DUMMYFUNCTION("""COMPUTED_VALUE"""),"Offset") -> Offset | Q78: =IFERROR(__xludf.DUMMYFUNCTION("""COMPUTED_VALUE"""),"Packaging") -> Packaging | BY78: =IFERROR(__xludf.DUMMYFUNCTION("""COMPUTED_VALUE"""),"Printing") -> Printing | BZ78: =IFERROR(__xludf.DUMMYFUNCTION("""COMPUTED_VALUE"""),1002) -> 1002 | CA78: =IFERROR(__xludf.DUMMYFUNCTION("""COMPUTED_VALUE"""),1002) -> 1002 | CB78: =IFERROR(__xludf.DUMMYFUNCTION("""COMPUTED_VALUE"""),0) -> 0
A79: =IFERROR(__xludf.DUMMYFUNCTION("""COMPUTED_VALUE"""),"https://drive.google.com/open?id=1EDFHLal9OFKDcKtdrwzHrFcodX9TQmQF&authuser=jay.agg%40gmail.com&usp=drive_fs") -> https://drive.google.com/open?id=1EDFHLal9OFKDcKtdrwzHrFcodX9TQmQF&authuser=jay.agg%40gmail.com&usp=drive_fs | B79: =IFERROR(__xludf.DUMMYFUNCTION("""COMPUTED_VALUE"""),"Food") -> Food | C79: =IFERROR(__xludf.DUMMYFUNCTION("""COMPUTED_VALUE"""),"Sugar") -> Sugar | D79: =IFERROR(__xludf.DUMMYFUNCTION("""COMPUTED_VALUE"""),"65*30*80 mm | 2.5*1.2*3.1 inch") -> 65*30*80 mm | 2.5*1.2*3.1 inch | E79: =IFERROR(__xludf.DUMMYFUNCTION("""COMPUTED_VALUE"""),8) -> 8 | F79: =IFERROR(__xludf.DUMMYFUNCTION("""COMPUTED_VALUE"""),2029) -> 2029 | G79: =IFERROR(__xludf.DUMMYFUNCTION("""COMPUTED_VALUE"""),18) -> 18 | H79: =IFERROR(__xludf.DUMMYFUNCTION("""COMPUTED_VALUE"""),23) -> 23 | I79: =IFERROR(__xludf.DUMMYFUNCTION("""COMPUTED_VALUE"""),100) -> 100 | M79: =IFERROR(__xludf.DUMMYFUNCTION("""COMPUTED_VALUE"""),0.1) -> 0.1 | N79: =IFERROR(__xludf.DUMMYFUNCTION("""COMPUTED_VALUE"""),1) -> 1 | P79: =IFERROR(__xludf.DUMMYFUNCTION("""COMPUTED_VALUE"""),"Offset") -> Offset | Q79: =IFERROR(__xludf.DUMMYFUNCTION("""COMPUTED_VALUE"""),"Packaging") -> Packaging | BY79: =IFERROR(__xludf.DUMMYFUNCTION("""COMPUTED_VALUE"""),"Printing") -> Printing | BZ79: =IFERROR(__xludf.DUMMYFUNCTION("""COMPUTED_VALUE"""),1003) -> 1003 | CA79: =IFERROR(__xludf.DUMMYFUNCTION("""COMPUTED_VALUE"""),1003) -> 1003 | CB79: =IFERROR(__xludf.DUMMYFUNCTION("""COMPUTED_VALUE"""),0) -> 0
A80: =IFERROR(__xludf.DUMMYFUNCTION("""COMPUTED_VALUE"""),"https://drive.google.com/open?id=1ECt9F1f6-PNDi3P7M8-WDLzuWoONz4Pm&authuser=jay.agg%40gmail.com&usp=drive_fs") -> https://drive.google.com/open?id=1ECt9F1f6-PNDi3P7M8-WDLzuWoONz4Pm&authuser=jay.agg%40gmail.com&usp=drive_fs | B80: =IFERROR(__xludf.DUMMYFUNCTION("""COMPUTED_VALUE"""),"Food") -> Food | C80: =IFERROR(__xludf.DUMMYFUNCTION("""COMPUTED_VALUE"""),"Sugar") -> Sugar | D80: =IFERROR(__xludf.DUMMYFUNCTION("""COMPUTED_VALUE"""),"60*60*70 mm | 2.3*2.3*2.75 inch") -> 60*60*70 mm | 2.3*2.3*2.75 inch | E80: =IFERROR(__xludf.DUMMYFUNCTION("""COMPUTED_VALUE"""),8) -> 8 | F80: =IFERROR(__xludf.DUMMYFUNCTION("""COMPUTED_VALUE"""),2029) -> 2029 | G80: =IFERROR(__xludf.DUMMYFUNCTION("""COMPUTED_VALUE"""),20) -> 20 | H80: =IFERROR(__xludf.DUMMYFUNCTION("""COMPUTED_VALUE"""),28) -> 28 | I80: =IFERROR(__xludf.DUMMYFUNCTION("""COMPUTED_VALUE"""),100) -> 100 | M80: =IFERROR(__xludf.DUMMYFUNCTION("""COMPUTED_VALUE"""),0.1) -> 0.1 | N80: =IFERROR(__xludf.DUMMYFUNCTION("""COMPUTED_VALUE"""),1) -> 1 | P80: =IFERROR(__xludf.DUMMYFUNCTION("""COMPUTED_VALUE"""),"Offset") -> Offset | Q80: =IFERROR(__xludf.DUMMYFUNCTION("""COMPUTED_VALUE"""),"Packaging") -> Packaging | BY80: =IFERROR(__xludf.DUMMYFUNCTION("""COMPUTED_VALUE"""),"Printing") -> Printing | BZ80: =IFERROR(__xludf.DUMMYFUNCTION("""COMPUTED_VALUE"""),1004) -> 1004 | CA80: =IFERROR(__xludf.DUMMYFUNCTION("""COMPUTED_VALUE"""),1004) -> 1004 | CB80: =IFERROR(__xludf.DUMMYFUNCTION("""COMPUTED_VALUE"""),0) -> 0
A81: =IFERROR(__xludf.DUMMYFUNCTION("""COMPUTED_VALUE"""),"https://drive.google.com/open?id=1VnjDLGsZHYLMpIHTAPBXgjAaWeFFe8Co&authuser=jay.agg%40gmail.com&usp=drive_fs") -> https://drive.google.com/open?id=1VnjDLGsZHYLMpIHTAPBXgjAaWeFFe8Co&authuser=jay.agg%40gmail.com&usp=drive_fs | B81: =IFERROR(__xludf.DUMMYFUNCTION("""COMPUTED_VALUE"""),"Food") -> Food | C81: =IFERROR(__xludf.DUMMYFUNCTION("""COMPUTED_VALUE"""),"Misc") -> Misc | D81: =IFERROR(__xludf.DUMMYFUNCTION("""COMPUTED_VALUE"""),"267*267*20 mm | 10.5*10.5*0.75 inch W 7*7 inch") -> 267*267*20 mm | 10.5*10.5*0.75 inch W 7*7 inch | E81: =IFERROR(__xludf.DUMMYFUNCTION("""COMPUTED_VALUE"""),1) -> 1 | F81: =IFERROR(__xludf.DUMMYFUNCTION("""COMPUTED_VALUE"""),1926) -> 1926 | G81: =IFERROR(__xludf.DUMMYFUNCTION("""COMPUTED_VALUE"""),15) -> 15 | H81: =IFERROR(__xludf.DUMMYFUNCTION("""COMPUTED_VALUE"""),25) -> 25 | I81: =IFERROR(__xludf.DUMMYFUNCTION("""COMPUTED_VALUE"""),100) -> 100 | L81: =IFERROR(__xludf.DUMMYFUNCTION("""COMPUTED_VALUE"""),2) -> 2 | M81: =IFERROR(__xludf.DUMMYFUNCTION("""COMPUTED_VALUE"""),0.1) -> 0.1 | N81: =IFERROR(__xludf.DUMMYFUNCTION("""COMPUTED_VALUE"""),1) -> 1 | P81: =IFERROR(__xludf.DUMMYFUNCTION("""COMPUTED_VALUE"""),"Offset") -> Offset | Q81: =IFERROR(__xludf.DUMMYFUNCTION("""COMPUTED_VALUE"""),"Packaging") -> Packaging | BY81: =IFERROR(__xludf.DUMMYFUNCTION("""COMPUTED_VALUE"""),"Printing") -> Printing | BZ81: =IFERROR(__xludf.DUMMYFUNCTION("""COMPUTED_VALUE"""),1005) -> 1005 | CA81: =IFERROR(__xludf.DUMMYFUNCTION("""COMPUTED_VALUE"""),1005) -> 1005 | CB81: =IFERROR(__xludf.DUMMYFUNCTION("""COMPUTED_VALUE"""),0) -> 0
A82: =IFERROR(__xludf.DUMMYFUNCTION("""COMPUTED_VALUE"""),"https://drive.google.com/open?id=1W8K3LGsxJqHIDtIbqdtppHLaxRx4D66i&authuser=jay.agg%40gmail.com&usp=drive_fs") -> https://drive.google.com/open?id=1W8K3LGsxJqHIDtIbqdtppHLaxRx4D66i&authuser=jay.agg%40gmail.com&usp=drive_fs | B82: =IFERROR(__xludf.DUMMYFUNCTION("""COMPUTED_VALUE"""),"Food") -> Food | C82: =IFERROR(__xludf.DUMMYFUNCTION("""COMPUTED_VALUE"""),"Sugar Free") -> Sugar Free | D82: =IFERROR(__xludf.DUMMYFUNCTION("""COMPUTED_VALUE"""),"127*127*76 mm | 5*5*3 inch Flap") -> 127*127*76 mm | 5*5*3 inch Flap | E82: =IFERROR(__xludf.DUMMYFUNCTION("""COMPUTED_VALUE"""),2) -> 2 | F82: =IFERROR(__xludf.DUMMYFUNCTION("""COMPUTED_VALUE"""),2029) -> 2029 | G82: =IFERROR(__xludf.DUMMYFUNCTION("""COMPUTED_VALUE"""),18) -> 18 | H82: =IFERROR(__xludf.DUMMYFUNCTION("""COMPUTED_VALUE"""),23) -> 23 | I82: =IFERROR(__xludf.DUMMYFUNCTION("""COMPUTED_VALUE"""),100) -> 100 | M82: =IFERROR(__xludf.DUMMYFUNCTION("""COMPUTED_VALUE"""),0.1) -> 0.1 | N82: =IFERROR(__xludf.DUMMYFUNCTION("""COMPUTED_VALUE"""),1) -> 1 | P82: =IFERROR(__xludf.DUMMYFUNCTION("""COMPUTED_VALUE"""),"Offset") -> Offset | Q82: =IFERROR(__xludf.DUMMYFUNCTION("""COMPUTED_VALUE"""),"Packaging") -> Packaging
A83: =IFERROR(__xludf.DUMMYFUNCTION("""COMPUTED_VALUE"""),"https://drive.google.com/open?id=1MZcgRJR6eRn0bLxw4dJgnt1Z8c1PCcAl&authuser=jay.agg%40gmail.com&usp=drive_fs") -> https://drive.google.com/open?id=1MZcgRJR6eRn0bLxw4dJgnt1Z8c1PCcAl&authuser=jay.agg%40gmail.com&usp=drive_fs | B83: =IFERROR(__xludf.DUMMYFUNCTION("""COMPUTED_VALUE"""),"Food") -> Food | C83: =IFERROR(__xludf.DUMMYFUNCTION("""COMPUTED_VALUE"""),"Misc") -> Misc | D83: =IFERROR(__xludf.DUMMYFUNCTION("""COMPUTED_VALUE"""),"102*51*152 mm | 4*2*6 inch") -> 102*51*152 mm | 4*2*6 inch | E83: =IFERROR(__xludf.DUMMYFUNCTION("""COMPUTED_VALUE"""),4) -> 4 | F83: =IFERROR(__xludf.DUMMYFUNCTION("""COMPUTED_VALUE"""),2029) -> 2029 | G83: =IFERROR(__xludf.DUMMYFUNCTION("""COMPUTED_VALUE"""),19) -> 19 | H83: =IFERROR(__xludf.DUMMYFUNCTION("""COMPUTED_VALUE"""),26) -> 26 | I83: =IFERROR(__xludf.DUMMYFUNCTION("""COMPUTED_VALUE"""),100) -> 100 | M83: =IFERROR(__xludf.DUMMYFUNCTION("""COMPUTED_VALUE"""),0.1) -> 0.1 | N83: =IFERROR(__xludf.DUMMYFUNCTION("""COMPUTED_VALUE"""),1) -> 1 | P83: =IFERROR(__xludf.DUMMYFUNCTION("""COMPUTED_VALUE"""),"Offset") -> Offset | Q83: =IFERROR(__xludf.DUMMYFUNCTION("""COMPUTED_VALUE"""),"Packaging") -> Packaging | BT83: =F13 -> 0 | BW83: =IFERROR(__xludf.DUMMYFUNCTION("QUERY(BY67:CB72,BZ63)"),"Offset") -> Offset | BX83: =IFERROR(__xludf.DUMMYFUNCTION("""COMPUTED_VALUE"""),"Printing") -> Printing | BY83: =IFERROR(__xludf.DUMMYFUNCTION("""COMPUTED_VALUE"""),1926) -> 1926 | BZ83: =IFERROR(__xludf.DUMMYFUNCTION("""COMPUTED_VALUE"""),1926) -> 1926 | CA83: =BZ83*BY91 -> 1926 | CB83: =#REF! -> #REF! | CC83: =MAX(CA83,CB83) -> #REF!
A84: =IFERROR(__xludf.DUMMYFUNCTION("""COMPUTED_VALUE"""),"https://drive.google.com/open?id=1MfcBn_GQd5c1R_1f3A6p3lcJJN1Ro3F6&authuser=jay.agg%40gmail.com&usp=drive_fs") -> https://drive.google.com/open?id=1MfcBn_GQd5c1R_1f3A6p3lcJJN1Ro3F6&authuser=jay.agg%40gmail.com&usp=drive_fs | B84: =IFERROR(__xludf.DUMMYFUNCTION("""COMPUTED_VALUE"""),"Food") -> Food | C84: =IFERROR(__xludf.DUMMYFUNCTION("""COMPUTED_VALUE"""),"Misc") -> Misc | D84: =IFERROR(__xludf.DUMMYFUNCTION("""COMPUTED_VALUE"""),"140*35*195 mm | 5.5*1.4*7.6 inch LB") -> 140*35*195 mm | 5.5*1.4*7.6 inch LB | E84: =IFERROR(__xludf.DUMMYFUNCTION("""COMPUTED_VALUE"""),8) -> 8 | F84: =IFERROR(__xludf.DUMMYFUNCTION("""COMPUTED_VALUE"""),2840) -> 2840 | G84: =IFERROR(__xludf.DUMMYFUNCTION("""COMPUTED_VALUE"""),31.5) -> 31.5 | H84: =IFERROR(__xludf.DUMMYFUNCTION("""COMPUTED_VALUE"""),41.5) -> 41.5 | I84: =IFERROR(__xludf.DUMMYFUNCTION("""COMPUTED_VALUE"""),100) -> 100 | M84: =IFERROR(__xludf.DUMMYFUNCTION("""COMPUTED_VALUE"""),0.24) -> 0.24 | N84: =IFERROR(__xludf.DUMMYFUNCTION("""COMPUTED_VALUE"""),1) -> 1 | P84: =IFERROR(__xludf.DUMMYFUNCTION("""COMPUTED_VALUE"""),"Offset") -> Offset | Q84: =IFERROR(__xludf.DUMMYFUNCTION("""COMPUTED_VALUE"""),"Packaging") -> Packaging | BT84: =BT83 -> 0 | BW84: =IFERROR(__xludf.DUMMYFUNCTION("""COMPUTED_VALUE"""),"Offset") -> Offset | BX84: =IFERROR(__xludf.DUMMYFUNCTION("""COMPUTED_VALUE"""),"Printing") -> Printing | BY84: =IFERROR(__xludf.DUMMYFUNCTION("""COMPUTED_VALUE"""),2029) -> 2029 | BZ84: =IFERROR(__xludf.DUMMYFUNCTION("""COMPUTED_VALUE"""),2029) -> 2029 | CA84: =BZ84*BY91 -> 2029 | CB84: =#REF! -> #REF! | CC84: =MAX(CA84,CB84) -> #REF! | CD84: =Quotation!C35 -> Plain
A85: =IFERROR(__xludf.DUMMYFUNCTION("""COMPUTED_VALUE"""),"https://drive.google.com/open?id=1XbuBMiGIeJeLMlNdqinMKyIq2LAVN3Vo&authuser=jay.agg%40gmail.com&usp=drive_fs") -> https://drive.google.com/open?id=1XbuBMiGIeJeLMlNdqinMKyIq2LAVN3Vo&authuser=jay.agg%40gmail.com&usp=drive_fs | B85: =IFERROR(__xludf.DUMMYFUNCTION("""COMPUTED_VALUE"""),"Food") -> Food | C85: =IFERROR(__xludf.DUMMYFUNCTION("""COMPUTED_VALUE"""),"Cookies") -> Cookies | D85: =IFERROR(__xludf.DUMMYFUNCTION("""COMPUTED_VALUE"""),"160*50*85 mm | 6.3*2*3.3 inch") -> 160*50*85 mm | 6.3*2*3.3 inch | E85: =IFERROR(__xludf.DUMMYFUNCTION("""COMPUTED_VALUE"""),4) -> 4 | F85: =IFERROR(__xludf.DUMMYFUNCTION("""COMPUTED_VALUE"""),2029) -> 2029 | G85: =IFERROR(__xludf.DUMMYFUNCTION("""COMPUTED_VALUE"""),20) -> 20 | H85: =IFERROR(__xludf.DUMMYFUNCTION("""COMPUTED_VALUE"""),23) -> 23 | I85: =IFERROR(__xludf.DUMMYFUNCTION("""COMPUTED_VALUE"""),100) -> 100 | M85: =IFERROR(__xludf.DUMMYFUNCTION("""COMPUTED_VALUE"""),0.1) -> 0.1 | N85: =IFERROR(__xludf.DUMMYFUNCTION("""COMPUTED_VALUE"""),1) -> 1 | P85: =IFERROR(__xludf.DUMMYFUNCTION("""COMPUTED_VALUE"""),"Offset") -> Offset | Q85: =IFERROR(__xludf.DUMMYFUNCTION("""COMPUTED_VALUE"""),"Packaging") -> Packaging | BT85: =BT83 -> 0 | BW85: =IFERROR(__xludf.DUMMYFUNCTION("""COMPUTED_VALUE"""),"Offset") -> Offset | BX85: =IFERROR(__xludf.DUMMYFUNCTION("""COMPUTED_VALUE"""),"Printing") -> Printing | BY85: =IFERROR(__xludf.DUMMYFUNCTION("""COMPUTED_VALUE"""),2840) -> 2840 | BZ85: =IFERROR(__xludf.DUMMYFUNCTION("""COMPUTED_VALUE"""),2840) -> 2840 | CA85: =BZ85*BY91 -> 2840 | CB85: =#REF! -> #REF! | CC85: =MAX(CA85,CB85) -> #REF! | CD85: =IF(CD84="","","and CC = '"&CD84&"'") -> and CC = 'Plain'
A86: =IFERROR(__xludf.DUMMYFUNCTION("""COMPUTED_VALUE"""),"https://drive.google.com/open?id=1Zs1KOwwl0A7lPwcA-lFX7Uz5eZHgcnOh&authuser=jay.agg%40gmail.com&usp=drive_fs") -> https://drive.google.com/open?id=1Zs1KOwwl0A7lPwcA-lFX7Uz5eZHgcnOh&authuser=jay.agg%40gmail.com&usp=drive_fs | B86: =IFERROR(__xludf.DUMMYFUNCTION("""COMPUTED_VALUE"""),"Food") -> Food | C86: =IFERROR(__xludf.DUMMYFUNCTION("""COMPUTED_VALUE"""),"Chocolate") -> Chocolate | D86: =IFERROR(__xludf.DUMMYFUNCTION("""COMPUTED_VALUE"""),"75*15*150 mm | 2.9*0.6*5.9 inch") -> 75*15*150 mm | 2.9*0.6*5.9 inch | E86: =IFERROR(__xludf.DUMMYFUNCTION("""COMPUTED_VALUE"""),6) -> 6 | F86: =IFERROR(__xludf.DUMMYFUNCTION("""COMPUTED_VALUE"""),1926) -> 1926 | G86: =IFERROR(__xludf.DUMMYFUNCTION("""COMPUTED_VALUE"""),18) -> 18 | H86: =IFERROR(__xludf.DUMMYFUNCTION("""COMPUTED_VALUE"""),23) -> 23 | I86: =IFERROR(__xludf.DUMMYFUNCTION("""COMPUTED_VALUE"""),100) -> 100 | M86: =IFERROR(__xludf.DUMMYFUNCTION("""COMPUTED_VALUE"""),0.1) -> 0.1 | N86: =IFERROR(__xludf.DUMMYFUNCTION("""COMPUTED_VALUE"""),1) -> 1 | P86: =IFERROR(__xludf.DUMMYFUNCTION("""COMPUTED_VALUE"""),"Offset") -> Offset | Q86: =IFERROR(__xludf.DUMMYFUNCTION("""COMPUTED_VALUE"""),"Packaging") -> Packaging | BT86: =BT83 -> 0 | CD86: =CONCATENATE("select * where 1=1",CD85) -> select * where 1=1and CC = 'Plain'
A87: =IFERROR(__xludf.DUMMYFUNCTION("""COMPUTED_VALUE"""),"https://drive.google.com/open?id=1OUeI1hjrKsYImhu02Q5Rv64yicLMPFRa&authuser=jay.agg%40gmail.com&usp=drive_fs") -> https://drive.google.com/open?id=1OUeI1hjrKsYImhu02Q5Rv64yicLMPFRa&authuser=jay.agg%40gmail.com&usp=drive_fs | B87: =IFERROR(__xludf.DUMMYFUNCTION("""COMPUTED_VALUE"""),"Food") -> Food | C87: =IFERROR(__xludf.DUMMYFUNCTION("""COMPUTED_VALUE"""),"Chocolate") -> Chocolate | D87: =IFERROR(__xludf.DUMMYFUNCTION("""COMPUTED_VALUE"""),"75*15*150 mm | 2.9*0.6*5.9 inch Flat") -> 75*15*150 mm | 2.9*0.6*5.9 inch Flat | E87: =IFERROR(__xludf.DUMMYFUNCTION("""COMPUTED_VALUE"""),4) -> 4 | F87: =IFERROR(__xludf.DUMMYFUNCTION("""COMPUTED_VALUE"""),2029) -> 2029 | G87: =IFERROR(__xludf.DUMMYFUNCTION("""COMPUTED_VALUE"""),20) -> 20 | H87: =IFERROR(__xludf.DUMMYFUNCTION("""COMPUTED_VALUE"""),21) -> 21 | I87: =IFERROR(__xludf.DUMMYFUNCTION("""COMPUTED_VALUE"""),100) -> 100 | N87: =IFERROR(__xludf.DUMMYFUNCTION("""COMPUTED_VALUE"""),1) -> 1 | P87: =IFERROR(__xludf.DUMMYFUNCTION("""COMPUTED_VALUE"""),"Offset") -> Offset | Q87: =IFERROR(__xludf.DUMMYFUNCTION("""COMPUTED_VALUE"""),"Packaging") -> Packaging | BT87: =BT83 -> 0 | CC87: Plain | CD87: 0 | CE87: =IFERROR(__xludf.DUMMYFUNCTION("QUERY(CC87:CD88,CD86)"),"Plain") -> Plain | CF87: =IFERROR(__xludf.DUMMYFUNCTION("""COMPUTED_VALUE"""),0) -> 0
A88: =IFERROR(__xludf.DUMMYFUNCTION("""COMPUTED_VALUE"""),"https://drive.google.com/open?id=1RbVA9G0GfOooAXiRtSrF3W27xwr7sRW5&authuser=jay.agg%40gmail.com&usp=drive_fs") -> https://drive.google.com/open?id=1RbVA9G0GfOooAXiRtSrF3W27xwr7sRW5&authuser=jay.agg%40gmail.com&usp=drive_fs | B88: =IFERROR(__xludf.DUMMYFUNCTION("""COMPUTED_VALUE"""),"Food") -> Food | C88: =IFERROR(__xludf.DUMMYFUNCTION("""COMPUTED_VALUE"""),"Chocolate") -> Chocolate | D88: =IFERROR(__xludf.DUMMYFUNCTION("""COMPUTED_VALUE"""),"80*15*175 mm | 3.15*0.6*6.9 inch") -> 80*15*175 mm | 3.15*0.6*6.9 inch | E88: =IFERROR(__xludf.DUMMYFUNCTION("""COMPUTED_VALUE"""),6) -> 6 | F88: =IFERROR(__xludf.DUMMYFUNCTION("""COMPUTED_VALUE"""),1926) -> 1926 | G88: =IFERROR(__xludf.DUMMYFUNCTION("""COMPUTED_VALUE"""),18) -> 18 | H88: =IFERROR(__xludf.DUMMYFUNCTION("""COMPUTED_VALUE"""),25) -> 25 | I88: =IFERROR(__xludf.DUMMYFUNCTION("""COMPUTED_VALUE"""),100) -> 100 | M88: =IFERROR(__xludf.DUMMYFUNCTION("""COMPUTED_VALUE"""),0.1) -> 0.1 | N88: =IFERROR(__xludf.DUMMYFUNCTION("""COMPUTED_VALUE"""),1) -> 1 | P88: =IFERROR(__xludf.DUMMYFUNCTION("""COMPUTED_VALUE"""),"Offset") -> Offset | Q88: =IFERROR(__xludf.DUMMYFUNCTION("""COMPUTED_VALUE"""),"Packaging") -> Packaging | CC88: Leafing | CD88: 1
A89: =IFERROR(__xludf.DUMMYFUNCTION("""COMPUTED_VALUE"""),"https://drive.google.com/open?id=1SBLkVNmqnX4OYK4aJO7joLQzUcHSj3tX&authuser=jay.agg%40gmail.com&usp=drive_fs") -> https://drive.google.com/open?id=1SBLkVNmqnX4OYK4aJO7joLQzUcHSj3tX&authuser=jay.agg%40gmail.com&usp=drive_fs | B89: =IFERROR(__xludf.DUMMYFUNCTION("""COMPUTED_VALUE"""),"Food") -> Food | C89: =IFERROR(__xludf.DUMMYFUNCTION("""COMPUTED_VALUE"""),"Dog Food") -> Dog Food | D89: =IFERROR(__xludf.DUMMYFUNCTION("""COMPUTED_VALUE"""),"127*15*178 mm | 5*0.6*7 inch") -> 127*15*178 mm | 5*0.6*7 inch | E89: =IFERROR(__xludf.DUMMYFUNCTION("""COMPUTED_VALUE"""),4) -> 4 | F89: =IFERROR(__xludf.DUMMYFUNCTION("""COMPUTED_VALUE"""),1926) -> 1926 | G89: =IFERROR(__xludf.DUMMYFUNCTION("""COMPUTED_VALUE"""),18) -> 18 | H89: =IFERROR(__xludf.DUMMYFUNCTION("""COMPUTED_VALUE"""),25) -> 25 | I89: =IFERROR(__xludf.DUMMYFUNCTION("""COMPUTED_VALUE"""),100) -> 100 | M89: =IFERROR(__xludf.DUMMYFUNCTION("""COMPUTED_VALUE"""),0.1) -> 0.1 | N89: =IFERROR(__xludf.DUMMYFUNCTION("""COMPUTED_VALUE"""),1) -> 1 | P89: =IFERROR(__xludf.DUMMYFUNCTION("""COMPUTED_VALUE"""),"Offset") -> Offset | Q89: =IFERROR(__xludf.DUMMYFUNCTION("""COMPUTED_VALUE"""),"Packaging") -> Packaging
A90: =IFERROR(__xludf.DUMMYFUNCTION("""COMPUTED_VALUE"""),"https://drive.google.com/open?id=1bZ1xCuANVfYF3FIC18rTJsMQhSFLnJNm&authuser=jay.agg%40gmail.com&usp=drive_fs") -> https://drive.google.com/open?id=1bZ1xCuANVfYF3FIC18rTJsMQhSFLnJNm&authuser=jay.agg%40gmail.com&usp=drive_fs | B90: =IFERROR(__xludf.DUMMYFUNCTION("""COMPUTED_VALUE"""),"Food") -> Food | C90: =IFERROR(__xludf.DUMMYFUNCTION("""COMPUTED_VALUE"""),"Chocolate") -> Chocolate | D90: =IFERROR(__xludf.DUMMYFUNCTION("""COMPUTED_VALUE"""),"45*13*45 mm | 1.75*0.5*1.75 inch") -> 45*13*45 mm | 1.75*0.5*1.75 inch | E90: =IFERROR(__xludf.DUMMYFUNCTION("""COMPUTED_VALUE"""),20) -> 20 | F90: =IFERROR(__xludf.DUMMYFUNCTION("""COMPUTED_VALUE"""),1926) -> 1926 | G90: =IFERROR(__xludf.DUMMYFUNCTION("""COMPUTED_VALUE"""),15.75) -> 15.75 | H90: =IFERROR(__xludf.DUMMYFUNCTION("""COMPUTED_VALUE"""),20.75) -> 20.75 | I90: =IFERROR(__xludf.DUMMYFUNCTION("""COMPUTED_VALUE"""),100) -> 100 | M90: =IFERROR(__xludf.DUMMYFUNCTION("""COMPUTED_VALUE"""),0.1) -> 0.1 | N90: =IFERROR(__xludf.DUMMYFUNCTION("""COMPUTED_VALUE"""),1) -> 1 | P90: =IFERROR(__xludf.DUMMYFUNCTION("""COMPUTED_VALUE"""),"Offset") -> Offset | Q90: =IFERROR(__xludf.DUMMYFUNCTION("""COMPUTED_VALUE"""),"Packaging") -> Packaging | CD90: =Quotation!B31 -> Custom Paper
A91: =IFERROR(__xludf.DUMMYFUNCTION("""COMPUTED_VALUE"""),"https://drive.google.com/open?id=1bcZpGfPoMXDPTbSxzxMxjn7Rxt7adn7l&authuser=jay.agg%40gmail.com&usp=drive_fs") -> https://drive.google.com/open?id=1bcZpGfPoMXDPTbSxzxMxjn7Rxt7adn7l&authuser=jay.agg%40gmail.com&usp=drive_fs | B91: =IFERROR(__xludf.DUMMYFUNCTION("""COMPUTED_VALUE"""),"Food") -> Food | C91: =IFERROR(__xludf.DUMMYFUNCTION("""COMPUTED_VALUE"""),"Chocolate") -> Chocolate | D91: =IFERROR(__xludf.DUMMYFUNCTION("""COMPUTED_VALUE"""),"46*19*46 mm | 1.8*0.75*1.8 inch") -> 46*19*46 mm | 1.8*0.75*1.8 inch | E91: =IFERROR(__xludf.DUMMYFUNCTION("""COMPUTED_VALUE"""),20) -> 20 | F91: =IFERROR(__xludf.DUMMYFUNCTION("""COMPUTED_VALUE"""),1926) -> 1926 | G91: =IFERROR(__xludf.DUMMYFUNCTION("""COMPUTED_VALUE"""),18) -> 18 | H91: =IFERROR(__xludf.DUMMYFUNCTION("""COMPUTED_VALUE"""),23) -> 23 | I91: =IFERROR(__xludf.DUMMYFUNCTION("""COMPUTED_VALUE"""),100) -> 100 | M91: =IFERROR(__xludf.DUMMYFUNCTION("""COMPUTED_VALUE"""),0.1) -> 0.1 | N91: =IFERROR(__xludf.DUMMYFUNCTION("""COMPUTED_VALUE"""),1) -> 1 | P91: =IFERROR(__xludf.DUMMYFUNCTION("""COMPUTED_VALUE"""),"Offset") -> Offset | Q91: =IFERROR(__xludf.DUMMYFUNCTION("""COMPUTED_VALUE"""),"Packaging") -> Packaging | BW91: Custom Custom | BX91: 1 | BY91: =MAX(BX91,BX92) -> 1 | CD91: =IF(CD90="","","and CC = '"&CD90&"'") -> and CC = 'Custom Paper'
A92: =IFERROR(__xludf.DUMMYFUNCTION("""COMPUTED_VALUE"""),"https://drive.google.com/open?id=1TdHmVW8TpujDIJ9hmo96hi9fIYAhzrOL&authuser=jay.agg%40gmail.com&usp=drive_fs") -> https://drive.google.com/open?id=1TdHmVW8TpujDIJ9hmo96hi9fIYAhzrOL&authuser=jay.agg%40gmail.com&usp=drive_fs | B92: =IFERROR(__xludf.DUMMYFUNCTION("""COMPUTED_VALUE"""),"Food") -> Food | C92: =IFERROR(__xludf.DUMMYFUNCTION("""COMPUTED_VALUE"""),"Chocolate") -> Chocolate | D92: =IFERROR(__xludf.DUMMYFUNCTION("""COMPUTED_VALUE"""),"110*33*65 mm | 4.3*1.2*2.4 inch") -> 110*33*65 mm | 4.3*1.2*2.4 inch | E92: =IFERROR(__xludf.DUMMYFUNCTION("""COMPUTED_VALUE"""),6) -> 6 | F92: =IFERROR(__xludf.DUMMYFUNCTION("""COMPUTED_VALUE"""),2029) -> 2029 | G92: =IFERROR(__xludf.DUMMYFUNCTION("""COMPUTED_VALUE"""),20) -> 20 | H92: =IFERROR(__xludf.DUMMYFUNCTION("""COMPUTED_VALUE"""),28) -> 28 | I92: =IFERROR(__xludf.DUMMYFUNCTION("""COMPUTED_VALUE"""),100) -> 100 | M92: =IFERROR(__xludf.DUMMYFUNCTION("""COMPUTED_VALUE"""),0.16) -> 0.16 | N92: =IFERROR(__xludf.DUMMYFUNCTION("""COMPUTED_VALUE"""),1) -> 1 | P92: =IFERROR(__xludf.DUMMYFUNCTION("""COMPUTED_VALUE"""),"Offset") -> Offset | Q92: =IFERROR(__xludf.DUMMYFUNCTION("""COMPUTED_VALUE"""),"Packaging") -> Packaging | BW92: =Quotation!B30 -> 240*64*160 mm | 9.5*2.5*6.25 inch | BX92: 0 | CD92: =CONCATENATE("select * where 1=1",CD91) -> select * where 1=1and CC = 'Custom Paper'
A93: =IFERROR(__xludf.DUMMYFUNCTION("""COMPUTED_VALUE"""),"https://drive.google.com/open?id=1TeYHEy8TxqYIbPsxfxDa3-2Cc7CS_8AY&authuser=jay.agg%40gmail.com&usp=drive_fs") -> https://drive.google.com/open?id=1TeYHEy8TxqYIbPsxfxDa3-2Cc7CS_8AY&authuser=jay.agg%40gmail.com&usp=drive_fs | B93: =IFERROR(__xludf.DUMMYFUNCTION("""COMPUTED_VALUE"""),"Food") -> Food | C93: =IFERROR(__xludf.DUMMYFUNCTION("""COMPUTED_VALUE"""),"Chocolate") -> Chocolate | D93: =IFERROR(__xludf.DUMMYFUNCTION("""COMPUTED_VALUE"""),"230*90*42 mm | 9*3.5*1.6 inch") -> 230*90*42 mm | 9*3.5*1.6 inch | E93: =IFERROR(__xludf.DUMMYFUNCTION("""COMPUTED_VALUE"""),2) -> 2 | F93: =IFERROR(__xludf.DUMMYFUNCTION("""COMPUTED_VALUE"""),1926) -> 1926 | G93: =IFERROR(__xludf.DUMMYFUNCTION("""COMPUTED_VALUE"""),18) -> 18 | H93: =IFERROR(__xludf.DUMMYFUNCTION("""COMPUTED_VALUE"""),25) -> 25 | I93: =IFERROR(__xludf.DUMMYFUNCTION("""COMPUTED_VALUE"""),100) -> 100 | M93: =IFERROR(__xludf.DUMMYFUNCTION("""COMPUTED_VALUE"""),0.12) -> 0.12 | N93: =IFERROR(__xludf.DUMMYFUNCTION("""COMPUTED_VALUE"""),1) -> 1 | P93: =IFERROR(__xludf.DUMMYFUNCTION("""COMPUTED_VALUE"""),"Offset") -> Offset | Q93: =IFERROR(__xludf.DUMMYFUNCTION("""COMPUTED_VALUE"""),"Packaging") -> Packaging | CC93: Plain | CD93: 0 | CF93: =IFERROR(__xludf.DUMMYFUNCTION("QUERY(CC93:CE100,CD92)"),"Custom Paper") -> Custom Paper | CG93: =IFERROR(__xludf.DUMMYFUNCTION("""COMPUTED_VALUE"""),0) -> 0 | CH93: =IFERROR(__xludf.DUMMYFUNCTION("""COMPUTED_VALUE"""),1) -> 1
A94: =IFERROR(__xludf.DUMMYFUNCTION("""COMPUTED_VALUE"""),"https://drive.google.com/open?id=1br_Bmmo5BouaDD0ySdIBxeB0Zho9elM9&authuser=jay.agg%40gmail.com&usp=drive_fs") -> https://drive.google.com/open?id=1br_Bmmo5BouaDD0ySdIBxeB0Zho9elM9&authuser=jay.agg%40gmail.com&usp=drive_fs | B94: =IFERROR(__xludf.DUMMYFUNCTION("""COMPUTED_VALUE"""),"Food") -> Food | C94: =IFERROR(__xludf.DUMMYFUNCTION("""COMPUTED_VALUE"""),"Chocolate") -> Chocolate | D94: =IFERROR(__xludf.DUMMYFUNCTION("""COMPUTED_VALUE"""),"110*45*165 mm | 4.3*1.7*6.5 inch") -> 110*45*165 mm | 4.3*1.7*6.5 inch | E94: =IFERROR(__xludf.DUMMYFUNCTION("""COMPUTED_VALUE"""),4) -> 4 | F94: =IFERROR(__xludf.DUMMYFUNCTION("""COMPUTED_VALUE"""),2029) -> 2029 | G94: =IFERROR(__xludf.DUMMYFUNCTION("""COMPUTED_VALUE"""),20) -> 20 | H94: =IFERROR(__xludf.DUMMYFUNCTION("""COMPUTED_VALUE"""),28) -> 28 | I94: =IFERROR(__xludf.DUMMYFUNCTION("""COMPUTED_VALUE"""),100) -> 100 | M94: =IFERROR(__xludf.DUMMYFUNCTION("""COMPUTED_VALUE"""),0.1) -> 0.1 | N94: =IFERROR(__xludf.DUMMYFUNCTION("""COMPUTED_VALUE"""),1) -> 1 | P94: =IFERROR(__xludf.DUMMYFUNCTION("""COMPUTED_VALUE"""),"Offset") -> Offset | Q94: =IFERROR(__xludf.DUMMYFUNCTION("""COMPUTED_VALUE"""),"Packaging") -> Packaging | CC94: SBS | CD94: 1 | CE94: 0
A95: =IFERROR(__xludf.DUMMYFUNCTION("""COMPUTED_VALUE"""),"https://drive.google.com/open?id=1btVQf7Al07HEYIVxn9NCb5ooWJnS6fi0&authuser=jay.agg%40gmail.com&usp=drive_fs") -> https://drive.google.com/open?id=1btVQf7Al07HEYIVxn9NCb5ooWJnS6fi0&authuser=jay.agg%40gmail.com&usp=drive_fs | B95: =IFERROR(__xludf.DUMMYFUNCTION("""COMPUTED_VALUE"""),"Food") -> Food | C95: =IFERROR(__xludf.DUMMYFUNCTION("""COMPUTED_VALUE"""),"Chocolate") -> Chocolate | D95: =IFERROR(__xludf.DUMMYFUNCTION("""COMPUTED_VALUE"""),"67*53*190 mm | 2.6*2*7.5 inch") -> 67*53*190 mm | 2.6*2*7.5 inch | E95: =IFERROR(__xludf.DUMMYFUNCTION("""COMPUTED_VALUE"""),4) -> 4 | F95: =IFERROR(__xludf.DUMMYFUNCTION("""COMPUTED_VALUE"""),2029) -> 2029 | G95: =IFERROR(__xludf.DUMMYFUNCTION("""COMPUTED_VALUE"""),20) -> 20 | H95: =IFERROR(__xludf.DUMMYFUNCTION("""COMPUTED_VALUE"""),25) -> 25 | I95: =IFERROR(__xludf.DUMMYFUNCTION("""COMPUTED_VALUE"""),100) -> 100 | M95: =IFERROR(__xludf.DUMMYFUNCTION("""COMPUTED_VALUE"""),0.1) -> 0.1 | N95: =IFERROR(__xludf.DUMMYFUNCTION("""COMPUTED_VALUE"""),1) -> 1 | P95: =IFERROR(__xludf.DUMMYFUNCTION("""COMPUTED_VALUE"""),"Offset") -> Offset | Q95: =IFERROR(__xludf.DUMMYFUNCTION("""COMPUTED_VALUE"""),"Packaging") -> Packaging | CC95: WhiteBack | CD95: 1 | CE95: 0
A96: =IFERROR(__xludf.DUMMYFUNCTION("""COMPUTED_VALUE"""),"https://drive.google.com/open?id=1bu696xsT3kcj5Rq3y0z5VaE0FRBzU4hJ&authuser=jay.agg%40gmail.com&usp=drive_fs") -> https://drive.google.com/open?id=1bu696xsT3kcj5Rq3y0z5VaE0FRBzU4hJ&authuser=jay.agg%40gmail.com&usp=drive_fs | B96: =IFERROR(__xludf.DUMMYFUNCTION("""COMPUTED_VALUE"""),"Food") -> Food | C96: =IFERROR(__xludf.DUMMYFUNCTION("""COMPUTED_VALUE"""),"Chocolate") -> Chocolate | D96: =IFERROR(__xludf.DUMMYFUNCTION("""COMPUTED_VALUE"""),"100*60*198 mm | 3.9*2.4*7.8 inch") -> 100*60*198 mm | 3.9*2.4*7.8 inch | E96: =IFERROR(__xludf.DUMMYFUNCTION("""COMPUTED_VALUE"""),2) -> 2 | F96: =IFERROR(__xludf.DUMMYFUNCTION("""COMPUTED_VALUE"""),1926) -> 1926 | G96: =IFERROR(__xludf.DUMMYFUNCTION("""COMPUTED_VALUE"""),15) -> 15 | H96: =IFERROR(__xludf.DUMMYFUNCTION("""COMPUTED_VALUE"""),25) -> 25 | I96: =IFERROR(__xludf.DUMMYFUNCTION("""COMPUTED_VALUE"""),100) -> 100 | M96: =IFERROR(__xludf.DUMMYFUNCTION("""COMPUTED_VALUE"""),0.1) -> 0.1 | N96: =IFERROR(__xludf.DUMMYFUNCTION("""COMPUTED_VALUE"""),1) -> 1 | P96: =IFERROR(__xludf.DUMMYFUNCTION("""COMPUTED_VALUE"""),"Offset") -> Offset | Q96: =IFERROR(__xludf.DUMMYFUNCTION("""COMPUTED_VALUE"""),"Packaging") -> Packaging | CC96: GreyBack | CD96: 1 | CE96: 0
A97: =IFERROR(__xludf.DUMMYFUNCTION("""COMPUTED_VALUE"""),"https://drive.google.com/open?id=1cQZ1nLDZbcrBAbbuejJB5gYu4UDh2ip4&authuser=jay.agg%40gmail.com&usp=drive_fs") -> https://drive.google.com/open?id=1cQZ1nLDZbcrBAbbuejJB5gYu4UDh2ip4&authuser=jay.agg%40gmail.com&usp=drive_fs | B97: =IFERROR(__xludf.DUMMYFUNCTION("""COMPUTED_VALUE"""),"Food") -> Food | C97: =IFERROR(__xludf.DUMMYFUNCTION("""COMPUTED_VALUE"""),"Pop Corn") -> Pop Corn | D97: =IFERROR(__xludf.DUMMYFUNCTION("""COMPUTED_VALUE"""),"90*90*200 mm | 3.5*3.5*7.8 inch IL") -> 90*90*200 mm | 3.5*3.5*7.8 inch IL | E97: =IFERROR(__xludf.DUMMYFUNCTION("""COMPUTED_VALUE"""),2) -> 2 | F97: =IFERROR(__xludf.DUMMYFUNCTION("""COMPUTED_VALUE"""),1926) -> 1926 | G97: =IFERROR(__xludf.DUMMYFUNCTION("""COMPUTED_VALUE"""),18) -> 18 | H97: =IFERROR(__xludf.DUMMYFUNCTION("""COMPUTED_VALUE"""),23) -> 23 | I97: =IFERROR(__xludf.DUMMYFUNCTION("""COMPUTED_VALUE"""),100) -> 100 | M97: =IFERROR(__xludf.DUMMYFUNCTION("""COMPUTED_VALUE"""),0.23) -> 0.23 | N97: =IFERROR(__xludf.DUMMYFUNCTION("""COMPUTED_VALUE"""),1) -> 1 | P97: =IFERROR(__xludf.DUMMYFUNCTION("""COMPUTED_VALUE"""),"Offset") -> Offset | Q97: =IFERROR(__xludf.DUMMYFUNCTION("""COMPUTED_VALUE"""),"Packaging") -> Packaging | CC97: Custom Paper | CD97: 0 | CE97: 1
A98: =IFERROR(__xludf.DUMMYFUNCTION("""COMPUTED_VALUE"""),"https://drive.google.com/open?id=1cU17WcKhUy0IEwwgaJbbKg6a20l_eH8x&authuser=jay.agg%40gmail.com&usp=drive_fs") -> https://drive.google.com/open?id=1cU17WcKhUy0IEwwgaJbbKg6a20l_eH8x&authuser=jay.agg%40gmail.com&usp=drive_fs | B98: =IFERROR(__xludf.DUMMYFUNCTION("""COMPUTED_VALUE"""),"Food") -> Food | C98: =IFERROR(__xludf.DUMMYFUNCTION("""COMPUTED_VALUE"""),"Burger Box") -> Burger Box | D98: =IFERROR(__xludf.DUMMYFUNCTION("""COMPUTED_VALUE"""),"105*105*48 mm 4*4*2 inch") -> 105*105*48 mm 4*4*2 inch | E98: =IFERROR(__xludf.DUMMYFUNCTION("""COMPUTED_VALUE"""),3) -> 3 | F98: =IFERROR(__xludf.DUMMYFUNCTION("""COMPUTED_VALUE"""),1926) -> 1926 | G98: =IFERROR(__xludf.DUMMYFUNCTION("""COMPUTED_VALUE"""),19) -> 19 | H98: =IFERROR(__xludf.DUMMYFUNCTION("""COMPUTED_VALUE"""),26) -> 26 | I98: =IFERROR(__xludf.DUMMYFUNCTION("""COMPUTED_VALUE"""),100) -> 100 | M98: =IFERROR(__xludf.DUMMYFUNCTION("""COMPUTED_VALUE"""),1) -> 1 | N98: =IFERROR(__xludf.DUMMYFUNCTION("""COMPUTED_VALUE"""),1) -> 1 | P98: =IFERROR(__xludf.DUMMYFUNCTION("""COMPUTED_VALUE"""),"Offset") -> Offset | Q98: =IFERROR(__xludf.DUMMYFUNCTION("""COMPUTED_VALUE"""),"Packaging") -> Packaging | CC98: Other Type | CD98: 1 | CE98: 0
A99: =IFERROR(__xludf.DUMMYFUNCTION("""COMPUTED_VALUE"""),"https://drive.google.com/open?id=1cVGC95lD8FILuv7GIGTUPf3N-ZfRx8MG&authuser=jay.agg%40gmail.com&usp=drive_fs") -> https://drive.google.com/open?id=1cVGC95lD8FILuv7GIGTUPf3N-ZfRx8MG&authuser=jay.agg%40gmail.com&usp=drive_fs | B99: =IFERROR(__xludf.DUMMYFUNCTION("""COMPUTED_VALUE"""),"Food") -> Food | C99: =IFERROR(__xludf.DUMMYFUNCTION("""COMPUTED_VALUE"""),"Burger Box") -> Burger Box | D99: =IFERROR(__xludf.DUMMYFUNCTION("""COMPUTED_VALUE"""),"81*81*24 mm | 3.2*3.2*0.8 inch") -> 81*81*24 mm | 3.2*3.2*0.8 inch | E99: =IFERROR(__xludf.DUMMYFUNCTION("""COMPUTED_VALUE"""),6) -> 6 | F99: =IFERROR(__xludf.DUMMYFUNCTION("""COMPUTED_VALUE"""),1926) -> 1926 | G99: =IFERROR(__xludf.DUMMYFUNCTION("""COMPUTED_VALUE"""),18) -> 18 | H99: =IFERROR(__xludf.DUMMYFUNCTION("""COMPUTED_VALUE"""),21) -> 21 | I99: =IFERROR(__xludf.DUMMYFUNCTION("""COMPUTED_VALUE"""),100) -> 100 | M99: =IFERROR(__xludf.DUMMYFUNCTION("""COMPUTED_VALUE"""),1) -> 1 | N99: =IFERROR(__xludf.DUMMYFUNCTION("""COMPUTED_VALUE"""),1) -> 1 | P99: =IFERROR(__xludf.DUMMYFUNCTION("""COMPUTED_VALUE"""),"Offset") -> Offset | Q99: =IFERROR(__xludf.DUMMYFUNCTION("""COMPUTED_VALUE"""),"Packaging") -> Packaging | CC99: Maplitho | CD99: 1 | CE99: 0
A100: =IFERROR(__xludf.DUMMYFUNCTION("""COMPUTED_VALUE"""),"https://drive.google.com/open?id=1c_uTwy3Lwk3r1OGpaY2ETWXZ6pjESZx3&authuser=jay.agg%40gmail.com&usp=drive_fs") -> https://drive.google.com/open?id=1c_uTwy3Lwk3r1OGpaY2ETWXZ6pjESZx3&authuser=jay.agg%40gmail.com&usp=drive_fs | B100: =IFERROR(__xludf.DUMMYFUNCTION("""COMPUTED_VALUE"""),"Food") -> Food | C100: =IFERROR(__xludf.DUMMYFUNCTION("""COMPUTED_VALUE"""),"Momo Box") -> Momo Box | D100: =IFERROR(__xludf.DUMMYFUNCTION("""COMPUTED_VALUE"""),"150*90*35 mm | 5.9*3.5*1.4 inch") -> 150*90*35 mm | 5.9*3.5*1.4 inch | E100: =IFERROR(__xludf.DUMMYFUNCTION("""COMPUTED_VALUE"""),4) -> 4 | F100: =IFERROR(__xludf.DUMMYFUNCTION("""COMPUTED_VALUE"""),2029) -> 2029 | G100: =IFERROR(__xludf.DUMMYFUNCTION("""COMPUTED_VALUE"""),19.5) -> 19.5 | H100: =IFERROR(__xludf.DUMMYFUNCTION("""COMPUTED_VALUE"""),23) -> 23 | I100: =IFERROR(__xludf.DUMMYFUNCTION("""COMPUTED_VALUE"""),100) -> 100 | M100: =IFERROR(__xludf.DUMMYFUNCTION("""COMPUTED_VALUE"""),1) -> 1 | N100: =IFERROR(__xludf.DUMMYFUNCTION("""COMPUTED_VALUE"""),1) -> 1 | P100: =IFERROR(__xludf.DUMMYFUNCTION("""COMPUTED_VALUE"""),"Offset") -> Offset | Q100: =IFERROR(__xludf.DUMMYFUNCTION("""COMPUTED_VALUE"""),"Packaging") -> Packaging | CC100: Art Card | CD100: 1 | CE100: 0
...

Sheet Product6
B1: =#REF! -> #REF! | C1: =#REF! -> #REF! | D1: =#REF! -> #REF! | E1: =#REF! -> #REF! | F1: =#REF! -> #REF! | G1: =#REF! -> #REF! | H1: =#REF! -> #REF! | I1: =#REF! -> #REF! | ... U1: =#REF! -> #REF! | V1: Plain | AF1: Gumming Full | AG1: Gumming Top Bottom | AH1: Gumming 4 Sides | AI1: Dangler Making | AJ1: Dangler With Rivet | AK1: Dangler With Rivet and Elastic | AL1: Plain | AT1: Sheet Type | AU1: Sub Category
C2: =Quotation!A31 -> Wrap | D2: =Quotation!D30 -> 0 | E2: =AF16 -> 0 | F2: =V16 -> 0 | G2: ='[1]Custom Quote'!C28 -> #REF! | H2: ='[1]Custom Quote'!E27 -> #REF! | I2: =#REF! -> #REF! | J2: =#REF! -> #REF! | K2: =J2 -> #REF! | L2: =J2 -> #REF! | M2: =J2 -> #REF! | N2: =J2 -> #REF! | O2: =#REF! -> #REF! | P2: =#REF! -> #REF! | Q2: =#REF! -> #REF! | R2: =#REF! -> #REF! | S2: =#REF! -> #REF! | T2: =#REF! -> #REF! | U2: =#REF! -> #REF! | V2: 0 | AF2: =#REF! -> #REF! | AG2: =#REF! -> #REF! | AH2: =#REF! -> #REF! | AI2: =#REF! -> #REF! | AJ2: =#REF! -> #REF! | AK2: =#REF! -> #REF! | AL2: 0 | AT2: {=_xludf.UNIQUE(INDEX(#REF!,0))} -> #NAME? | AU2: {=_xludf.UNIQUE(INDEX(#REF!,0))} -> #NAME?
B3: =B1 -> #REF! | C3: =C1 -> #REF! | D3: =D1 -> #REF! | E3: =E1 -> #REF! | F3: =F1 -> #REF! | G3: =G1 -> #REF! | H3: =H1 -> #REF! | I3: =I1 -> #REF! | ... V3: =V1 -> Plain | AF3: Gumming Full | AG3: Gumming Top Bottom | AH3: Gumming 4 Sides | AI3: Dangler Making | AJ3: Dangler With Rivet | AK3: Dangler With Rivet and Elastic | AL3: Plain | AT3: #NAME? | AU3: #NAME?
B4: =B2 -> 0 | C4: =C2 -> Wrap | D4: =D2 -> 0 | E4: =E2 -> 0 | F4: =F2 -> 0 | G4: =G2 -> #REF! | H4: ='[1]Custom Quote'!E28 -> #REF! | I4: =#REF! -> #REF! | J4: =#REF! -> #REF! | K4: =J4 -> #REF! | L4: =J4 -> #REF! | M4: =J4 -> #REF! | N4: =J4 -> #REF! | O4: =#REF! -> #REF! | P4: =#REF! -> #REF! | Q4: =#REF! -> #REF! | R4: =#REF! -> #REF! | S4: =#REF! -> #REF! | T4: =#REF! -> #REF! | U4: =#REF! -> #REF! | V4: 0 | AF4: =#REF! -> #REF! | AG4: =#REF! -> #REF! | AH4: =#REF! -> #REF! | AI4: =#REF! -> #REF! | AJ4: =#REF! -> #REF! | AK4: =#REF! -> #REF! | AL4: 0 | AT4: #NAME? | AU4: #NAME?
B5: =B3 -> #REF! | C5: =C3 -> #REF! | D5: =D3 -> #REF! | E5: =E3 -> #REF! | F5: =F3 -> #REF! | G5: =G3 -> #REF! | H5: =H3 -> #REF! | I5: =I3 -> #REF! | J5: =J3 -> #REF! | K5: =K1 -> #REF! | L5: =L1 -> #REF! | M5: =M1 -> #REF! | N5: =N1 -> #REF! | O5: =O3 -> #REF! | P5: =P3 -> #REF! | Q5: =Q3 -> #REF! | R5: =R3 -> #REF! | S5: =S3 -> #REF! | T5: =T3 -> #REF! | U5: =U3 -> #REF! | V5: =V3 -> Plain | AF5: Gumming Full | AG5: Gumming Top Bottom | AH5: Gumming 4 Sides | AI5: Dangler Making | AJ5: Dangler With Rivet | AK5: Dangler With Rivet and Elastic | AL5: Plain | AT5: #NAME? | AU5: #NAME?
B6: =B4 -> 0 | C6: =C4 -> Wrap | D6: =D4 -> 0 | E6: =E4 -> 0 | F6: =F4 -> 0 | G6: =G4 -> #REF! | H6: ='[1]Custom Quote'!E29 -> #REF! | I6: =#REF! -> #REF! | J6: =#REF! -> #REF! | K6: =J6 -> #REF! | L6: =J6 -> #REF! | M6: =J6 -> #REF! | N6: =J6 -> #REF! | O6: =#REF! -> #REF! | P6: #REF! | Q6: #REF! | R6: #REF! | S6: #REF! | T6: =#REF! -> #REF! | U6: =#REF! -> #REF! | V6: 0 | AF6: =#REF! -> #REF! | AG6: =#REF! -> #REF! | AH6: =#REF! -> #REF! | AI6: =#REF! -> #REF! | AJ6: =#REF! -> #REF! | AK6: =#REF! -> #REF! | AL6: 0 | AT6: #NAME? | AU6: #NAME?
W7: =Product2!BI45 -> 1926 | X7: =IF(W7="","","and AM = "&W7&"") -> and AM = 1926 | AT7: #NAME? | AU7: #NAME?
X8: =CONCATENATE("select * where 1=1",X7) -> select * where 1=1and AM = 1926 | AT8: #NAME? | AU8: Acrylic Imported 4mm
A9: Machine Type | B9: Product Length Main | C9: Product Width Main | D9: Sheet Size | E9: Machine | F9: Sheet Length | G9: Sheet Width | H9: Sheet Value | I9: F1 | J9: F2 | K9: F3 | L9: F4 | M9: F5 | N9: F6 | O9: Products Per Sheet | P9: Per Product Cost | R9: Sheets Required | U9: =IF(T12="All","","and U = "&T12&"") -> and U = 0 | X9: =IF(B2="","","and F = '"&B2&"'") | Z9: =IF(C2="","","and A = '"&C2&"'") -> and A = 'Wrap' | AU9: Acrylic Imported 5mm
B10: =IFERROR(__xludf.DUMMYFUNCTION("SPLIT(Quotation!D30,""*"")"),"#VALUE!") -> #VALUE! | D10: =IFERROR(__xludf.DUMMYFUNCTION("QUERY(AL16:AP629,X8)"),"#N/A") -> #N/A | I10: =ROUNDDOWN(F10/$B$10,0) -> #VALUE! | J10: =ROUNDDOWN(G10/$C$10,0) -> #DIV/0! | K10: =ROUNDDOWN(G10/$B$10,0) -> #VALUE! | L10: =ROUNDDOWN(F10/$C$10,0) -> #DIV/0! | M10: =(I10*J10)+(MAX((ROUNDDOWN((F10-(I10*$B$10))/$B$10,0)),(ROUNDDOWN((G10-(J10*$C$10))/$B$10,0)))*L10) -> #VALUE! | N10: =(K10*L10)+((MAX((ROUNDDOWN((G10-(K10*$B$10))/$B$10,0)),(ROUNDDOWN((F10-(L10*$C$10))/$B$10,0)))*J10)) -> #VALUE! | O10: #VALUE! | P10: =H10/O10 -> #VALUE! | R10: =ROUNDUP(Q10/O10,0) -> #VALUE! | S10: =((F10+0.5)*G10)/O10 -> #VALUE! | T10: =MIN(S10:S13) -> #VALUE! | U10: =IF(T10="All","","and O = "&T10&"") -> #VALUE! | X10: =IF(A10="","","and A = '"&A10&"'") | AG10: =IF(J10="","","and A = '"&J10&"'") -> #DIV/0!
I11: =ROUNDDOWN(F11/$B$10,0) -> #VALUE! | J11: =ROUNDDOWN(G11/$C$10,0) -> #DIV/0! | K11: =ROUNDDOWN(G11/$B$10,0) -> #VALUE! | L11: =ROUNDDOWN(F11/$C$10,0) -> #DIV/0! | M11: =(I11*J11)+(MAX((ROUNDDOWN((F11-(I11*$B$10))/$B$10,0)),(ROUNDDOWN((G11-(J11*$C$10))/$B$10,0)))*L11) -> #VALUE! | N11: =(K11*L11)+((MAX((ROUNDDOWN((G11-(K11*$B$10))/$B$10,0)),(ROUNDDOWN((F11-(L11*$C$10))/$B$10,0)))*J11)) -> #VALUE! | O11: #VALUE! | P11: =H11/O11 -> #VALUE! | R11: =ROUNDUP(Q11/O11,0) -> #VALUE! | S11: =((F11+0.5)*G11)/O11 -> #VALUE! | T11: =MAX(O10:O13) -> 0 | U11: =IF(T11="All","","and O = "&T11&"") -> and O = 0 | X11: =CONCATENATE("select * where 1=1",X9,Z9) -> select * where 1=1and A = 'Wrap'
I12: =ROUNDDOWN(F12/$B$10,0) -> #VALUE! | J12: =ROUNDDOWN(G12/$C$10,0) -> #DIV/0! | K12: =ROUNDDOWN(G12/$B$10,0) -> #VALUE! | L12: =ROUNDDOWN(F12/$C$10,0) -> #DIV/0! | M12: =(I12*J12)+(MAX((ROUNDDOWN((F12-(I12*$B$10))/$B$10,0)),(ROUNDDOWN((G12-(J12*$C$10))/$B$10,0)))*L12) -> #VALUE! | N12: =(K12*L12)+((MAX((ROUNDDOWN((G12-(K12*$B$10))/$B$10,0)),(ROUNDDOWN((F12-(L12*$C$10))/$B$10,0)))*J12)) -> #VALUE! | O12: #VALUE! | P12: =H11/O12 -> #VALUE! | R12: =ROUNDUP(Q12/O12,0) -> #VALUE! | S12: =((F12+0.5)*G12)/O12 -> #VALUE! | T12: =MIN(U29:U629) -> 0 | U12: =CONCATENATE("select * where 1=1",U11) -> select * where 1=1and O = 0
I13: =ROUNDDOWN(F13/$B$10,0) -> #VALUE! | J13: =ROUNDDOWN(G13/$C$10,0) -> #DIV/0! | K13: =ROUNDDOWN(G13/$B$10,0) -> #VALUE! | L13: =ROUNDDOWN(F13/$C$10,0) -> #DIV/0! | M13: =(I13*J13)+(MAX((ROUNDDOWN((F13-(I13*$B$10))/$B$10,0)),(ROUNDDOWN((G13-(J13*$C$10))/$B$10,0)))*L13) -> #VALUE! | N13: =(K13*L13)+((MAX((ROUNDDOWN((G13-(K13*$B$10))/$B$10,0)),(ROUNDDOWN((F13-(L13*$C$10))/$B$10,0)))*J13)) -> #VALUE! | O13: #VALUE! | P13: =H13/O13 -> #VALUE! | R13: =ROUNDUP(Q13/O13,0) -> #VALUE! | S13: =((F13+0.5)*G13)/O13 -> #VALUE! | U13: =CONCATENATE("select * where 1=1",U9) -> select * where 1=1and U = 0
I14: =ROUNDDOWN(F14/$B$10,0) -> #VALUE! | J14: =ROUNDDOWN(G14/$C$10,0) -> #DIV/0! | K14: =ROUNDDOWN(G14/$B$10,0) -> #VALUE! | L14: =ROUNDDOWN(F14/$C$10,0) -> #DIV/0! | M14: =(I14*J14)+(MAX((ROUNDDOWN((F14-(I14*$B$10))/$B$10,0)),(ROUNDDOWN((G14-(J14*$C$10))/$B$10,0)))*L14) -> #VALUE! | N14: =(K14*L14)+((MAX((ROUNDDOWN((G14-(K14*$B$10))/$B$10,0)),(ROUNDDOWN((F14-(L14*$C$10))/$B$10,0)))*J14)) -> #VALUE! | O14: #VALUE! | P14: =H14/O14 -> #VALUE! | R14: =ROUNDUP(Q14/O14,0) -> #VALUE! | S14: =((F14+0.5)*G14)/O14 -> #VALUE!
I15: =ROUNDDOWN(F15/$B$10,0) -> #VALUE! | J15: =ROUNDDOWN(G15/$C$10,0) -> #DIV/0! | K15: =ROUNDDOWN(G15/$B$10,0) -> #VALUE! | L15: =ROUNDDOWN(F15/$C$10,0) -> #DIV/0! | M15: =(I15*J15)+(MAX((ROUNDDOWN((F15-(I15*$B$10))/$B$10,0)),(ROUNDDOWN((G15-(J15*$C$10))/$B$10,0)))*L15) -> #VALUE! | N15: =(K15*L15)+((MAX((ROUNDDOWN((G15-(K15*$B$10))/$B$10,0)),(ROUNDDOWN((F15-(L15*$C$10))/$B$10,0)))*J15)) -> #VALUE! | O15: #VALUE! | P15: =H15/O15 -> #VALUE! | R15: =ROUNDUP(Q15/O15,0) -> #VALUE! | S15: =((F15+0.5)*G15)/O15 -> #VALUE! | U15: Sheet Size | V15: Machine | W15: Sheet Length | X15: Sheet Width | Y15: Sheet Value | Z15: F1 | AA15: F2 | AB15: F3 | AC15: F4 | AD15: F5 | AE15: F6 | AF15: Products Per Sheet | AG15: Per Product Cost | AI15: Sheets Required | AL15: Sheet Size | AM15: Machine | AN15: Sheet Length | AO15: Sheet Width | AP15: Sheet Value | AU15: Sheet Type | AV15: Sheet Size | AW15: Size | AX15: Sheet Price | AY15: Machine | AZ15: Sheet Type | BA15: Split A | BB15: Split B | BD15: Sheet Type | BE15: Sheet Size | BF15: Size | BG15: Sheet Price | BH15: Machine | BI15: Sheet Type | BJ15: Split A | BK15: Split B
I16: =ROUNDDOWN(F16/$B$10,0) -> #VALUE! | J16: =ROUNDDOWN(G16/$C$10,0) -> #DIV/0! | K16: =ROUNDDOWN(G16/$B$10,0) -> #VALUE! | L16: =ROUNDDOWN(F16/$C$10,0) -> #DIV/0! | M16: =(I16*J16)+(MAX((ROUNDDOWN((F16-(I16*$B$10))/$B$10,0)),(ROUNDDOWN((G16-(J16*$C$10))/$B$10,0)))*L16) -> #VALUE! | N16: =(K16*L16)+((MAX((ROUNDDOWN((G16-(K16*$B$10))/$B$10,0)),(ROUNDDOWN((F16-(L16*$C$10))/$B$10,0)))*J16)) -> #VALUE! | O16: =MAX(M16:N16) -> #VALUE! | P16: =H16/O16 -> #VALUE! | R16: =ROUNDUP(Q16/O16,0) -> #VALUE! | S16: =((F16+0.5)*G16)/O16 -> #VALUE! | U16: =IFERROR(__xludf.DUMMYFUNCTION("QUERY($U$29:$AI$99,U$13)"),"#VALUE!") -> #VALUE! | AL16: {=INDEX(BE16:BE629,0)} -> 0 | AM16: {=INDEX(BH16:BH629,0)} -> 0 | AN16: =INDEX((BJ16:BJ629)-0.5,0) -> #VALUE! | AO16: =INDEX((BK16:BK629)-0.5,0) -> -0.5 | AP16: {=INDEX(BG16:BG629,0)} -> 0 | AU16: =IFERROR(__xludf.DUMMYFUNCTION("QUERY(Price!$A$2:$F629,$X$11)"),"#N/A") -> #N/A | BA16: =IFERROR(__xludf.DUMMYFUNCTION("SPLIT(AW16,""*"")"),"#VALUE!") -> #VALUE! | BD16: =IFERROR(__xludf.DUMMYFUNCTION("QUERY(AU16:BB629,""Select * where AU is not null"",0)"),"#N/A") -> #N/A | BJ16: =IFERROR(__xludf.DUMMYFUNCTION("""COMPUTED_VALUE"""),"#VALUE!") -> #VALUE!
I17: =ROUNDDOWN(F17/$B$10,0) -> #VALUE! | J17: =ROUNDDOWN(G17/$C$10,0) -> #DIV/0! | K17: =ROUNDDOWN(G17/$B$10,0) -> #VALUE! | L17: =ROUNDDOWN(F17/$C$10,0) -> #DIV/0! | M17: =(I17*J17)+(MAX((ROUNDDOWN((F17-(I17*$B$10))/$B$10,0)),(ROUNDDOWN((G17-(J17*$C$10))/$B$10,0)))*L17) -> #VALUE! | N17: =(K17*L17)+((MAX((ROUNDDOWN((G17-(K17*$B$10))/$B$10,0)),(ROUNDDOWN((F17-(L17*$C$10))/$B$10,0)))*J17)) -> #VALUE! | O17: =MAX(M17:N17) -> #VALUE! | P17: =H17/O17 -> #VALUE! | R17: =ROUNDUP(Q17/O17,0) -> #VALUE! | S17: =((F17+0.5)*G17)/O17 -> #VALUE! | AL17: 0 | AM17: 0 | AN17: -0.5 | AO17: -0.5 | AP17: 0 | BA17: =IFERROR(__xludf.DUMMYFUNCTION("SPLIT(AW17,""*"")"),"#VALUE!") -> #VALUE!
I18: =ROUNDDOWN(F18/$B$10,0) -> #VALUE! | J18: =ROUNDDOWN(G18/$C$10,0) -> #DIV/0! | K18: =ROUNDDOWN(G18/$B$10,0) -> #VALUE! | L18: =ROUNDDOWN(F18/$C$10,0) -> #DIV/0! | M18: =(I18*J18)+(MAX((ROUNDDOWN((F18-(I18*$B$10))/$B$10,0)),(ROUNDDOWN((G18-(J18*$C$10))/$B$10,0)))*L18) -> #VALUE! | N18: =(K18*L18)+((MAX((ROUNDDOWN((G18-(K18*$B$10))/$B$10,0)),(ROUNDDOWN((F18-(L18*$C$10))/$B$10,0)))*J18)) -> #VALUE! | O18: =MAX(M18:N18) -> #VALUE! | P18: =H18/O18 -> #VALUE! | R18: =ROUNDUP(Q18/O18,0) -> #VALUE! | S18: =((F18+0.5)*G18)/O18 -> #VALUE! | AL18: 0 | AM18: 0 | AN18: -0.5 | AO18: -0.5 | AP18: 0 | BA18: =IFERROR(__xludf.DUMMYFUNCTION("SPLIT(AW18,""*"")"),"#VALUE!") -> #VALUE!
I19: =ROUNDDOWN(F19/$B$10,0) -> #VALUE! | J19: =ROUNDDOWN(G19/$C$10,0) -> #DIV/0! | K19: =ROUNDDOWN(G19/$B$10,0) -> #VALUE! | L19: =ROUNDDOWN(F19/$C$10,0) -> #DIV/0! | M19: =(I19*J19)+(MAX((ROUNDDOWN((F19-(I19*$B$10))/$B$10,0)),(ROUNDDOWN((G19-(J19*$C$10))/$B$10,0)))*L19) -> #VALUE! | N19: =(K19*L19)+((MAX((ROUNDDOWN((G19-(K19*$B$10))/$B$10,0)),(ROUNDDOWN((F19-(L19*$C$10))/$B$10,0)))*J19)) -> #VALUE! | O19: =MAX(M19:N19) -> #VALUE! | P19: =H19/O19 -> #VALUE! | R19: =ROUNDUP(Q19/O19,0) -> #VALUE! | S19: =((F19+0.5)*G19)/O19 -> #VALUE! | AL19: 0 | AM19: 0 | AN19: -0.5 | AO19: -0.5 | AP19: 0 | BA19: =IFERROR(__xludf.DUMMYFUNCTION("SPLIT(AW19,""*"")"),"#VALUE!") -> #VALUE!
I20: =ROUNDDOWN(F20/$B$10,0) -> #VALUE! | J20: =ROUNDDOWN(G20/$C$10,0) -> #DIV/0! | K20: =ROUNDDOWN(G20/$B$10,0) -> #VALUE! | L20: =ROUNDDOWN(F20/$C$10,0) -> #DIV/0! | M20: =(I20*J20)+(MAX((ROUNDDOWN((F20-(I20*$B$10))/$B$10,0)),(ROUNDDOWN((G20-(J20*$C$10))/$B$10,0)))*L20) -> #VALUE! | N20: =(K20*L20)+((MAX((ROUNDDOWN((G20-(K20*$B$10))/$B$10,0)),(ROUNDDOWN((F20-(L20*$C$10))/$B$10,0)))*J20)) -> #VALUE! | O20: =MAX(M20:N20) -> #VALUE! | P20: =H20/O20 -> #VALUE! | R20: =ROUNDUP(Q20/O20,0) -> #VALUE! | S20: =((F20+0.5)*G20)/O20 -> #VALUE! | AL20: 0 | AM20: 0 | AN20: -0.5 | AO20: -0.5 | AP20: 0 | BA20: =IFERROR(__xludf.DUMMYFUNCTION("SPLIT(AW20,""*"")"),"#VALUE!") -> #VALUE!
I21: =ROUNDDOWN(F21/$B$10,0) -> #VALUE! | J21: =ROUNDDOWN(G21/$C$10,0) -> #DIV/0! | K21: =ROUNDDOWN(G21/$B$10,0) -> #VALUE! | L21: =ROUNDDOWN(F21/$C$10,0) -> #DIV/0! | M21: =(I21*J21)+(MAX((ROUNDDOWN((F21-(I21*$B$10))/$B$10,0)),(ROUNDDOWN((G21-(J21*$C$10))/$B$10,0)))*L21) -> #VALUE! | N21: =(K21*L21)+((MAX((ROUNDDOWN((G21-(K21*$B$10))/$B$10,0)),(ROUNDDOWN((F21-(L21*$C$10))/$B$10,0)))*J21)) -> #VALUE! | O21: =MAX(M21:N21) -> #VALUE! | P21: =H21/O21 -> #VALUE! | R21: =ROUNDUP(Q21/O21,0) -> #VALUE! | S21: =((F21+0.5)*G21)/O21 -> #VALUE! | AL21: 0 | AM21: 0 | AN21: -0.5 | AO21: -0.5 | AP21: 0 | BA21: =IFERROR(__xludf.DUMMYFUNCTION("SPLIT(AW21,""*"")"),"#VALUE!") -> #VALUE!
I22: =ROUNDDOWN(F22/$B$10,0) -> #VALUE! | J22: =ROUNDDOWN(G22/$C$10,0) -> #DIV/0! | K22: =ROUNDDOWN(G22/$B$10,0) -> #VALUE! | L22: =ROUNDDOWN(F22/$C$10,0) -> #DIV/0! | M22: =(I22*J22)+(MAX((ROUNDDOWN((F22-(I22*$B$10))/$B$10,0)),(ROUNDDOWN((G22-(J22*$C$10))/$B$10,0)))*L22) -> #VALUE! | N22: =(K22*L22)+((MAX((ROUNDDOWN((G22-(K22*$B$10))/$B$10,0)),(ROUNDDOWN((F22-(L22*$C$10))/$B$10,0)))*J22)) -> #VALUE! | O22: =MAX(M22:N22) -> #VALUE! | P22: =H22/O22 -> #VALUE! | R22: =ROUNDUP(Q22/O22,0) -> #VALUE! | AL22: 0 | AM22: 0 | AN22: -0.5 | AO22: -0.5 | AP22: 0 | BA22: =IFERROR(__xludf.DUMMYFUNCTION("SPLIT(AW22,""*"")"),"#VALUE!") -> #VALUE!
I23: =ROUNDDOWN(F23/$B$10,0) -> #VALUE! | J23: =ROUNDDOWN(G23/$C$10,0) -> #DIV/0! | K23: =ROUNDDOWN(G23/$B$10,0) -> #VALUE! | L23: =ROUNDDOWN(F23/$C$10,0) -> #DIV/0! | M23: =(I23*J23)+(MAX((ROUNDDOWN((F23-(I23*$B$10))/$B$10,0)),(ROUNDDOWN((G23-(J23*$C$10))/$B$10,0)))*L23) -> #VALUE! | N23: =(K23*L23)+((MAX((ROUNDDOWN((G23-(K23*$B$10))/$B$10,0)),(ROUNDDOWN((F23-(L23*$C$10))/$B$10,0)))*J23)) -> #VALUE! | O23: =MAX(M23:N23) -> #VALUE! | P23: =H23/O23 -> #VALUE! | R23: =ROUNDUP(Q23/O23,0) -> #VALUE! | AL23: 0 | AM23: 0 | AN23: -0.5 | AO23: -0.5 | AP23: 0 | BA23: =IFERROR(__xludf.DUMMYFUNCTION("SPLIT(AW23,""*"")"),"#VALUE!") -> #VALUE!
I24: =ROUNDDOWN(F24/$B$10,0) -> #VALUE! | J24: =ROUNDDOWN(G24/$C$10,0) -> #DIV/0! | K24: =ROUNDDOWN(G24/$B$10,0) -> #VALUE! | L24: =ROUNDDOWN(F24/$C$10,0) -> #DIV/0! | M24: =(I24*J24)+(MAX((ROUNDDOWN((F24-(I24*$B$10))/$B$10,0)),(ROUNDDOWN((G24-(J24*$C$10))/$B$10,0)))*L24) -> #VALUE! | N24: =(K24*L24)+((MAX((ROUNDDOWN((G24-(K24*$B$10))/$B$10,0)),(ROUNDDOWN((F24-(L24*$C$10))/$B$10,0)))*J24)) -> #VALUE! | O24: =MAX(M24:N24) -> #VALUE! | P24: =H24/O24 -> #VALUE! | R24: =ROUNDUP(Q24/O24,0) -> #VALUE! | AL24: 0 | AM24: 0 | AN24: -0.5 | AO24: -0.5 | AP24: 0 | BA24: =IFERROR(__xludf.DUMMYFUNCTION("SPLIT(AW24,""*"")"),"#VALUE!") -> #VALUE!
I25: =ROUNDDOWN(F25/$B$10,0) -> #VALUE! | J25: =ROUNDDOWN(G25/$C$10,0) -> #DIV/0! | K25: =ROUNDDOWN(G25/$B$10,0) -> #VALUE! | L25: =ROUNDDOWN(F25/$C$10,0) -> #DIV/0! | M25: =(I25*J25)+(MAX((ROUNDDOWN((F25-(I25*$B$10))/$B$10,0)),(ROUNDDOWN((G25-(J25*$C$10))/$B$10,0)))*L25) -> #VALUE! | N25: =(K25*L25)+((MAX((ROUNDDOWN((G25-(K25*$B$10))/$B$10,0)),(ROUNDDOWN((F25-(L25*$C$10))/$B$10,0)))*J25)) -> #VALUE! | O25: =MAX(M25:N25) -> #VALUE! | P25: =H25/O25 -> #VALUE! | R25: =ROUNDUP(Q25/O25,0) -> #VALUE! | AL25: 0 | AM25: 0 | AN25: -0.5 | AO25: -0.5 | AP25: 0 | BA25: =IFERROR(__xludf.DUMMYFUNCTION("SPLIT(AW25,""*"")"),"#VALUE!") -> #VALUE!
I26: =ROUNDDOWN(F26/$B$10,0) -> #VALUE! | J26: =ROUNDDOWN(G26/$C$10,0) -> #DIV/0! | K26: =ROUNDDOWN(G26/$B$10,0) -> #VALUE! | L26: =ROUNDDOWN(F26/$C$10,0) -> #DIV/0! | M26: =(I26*J26)+(MAX((ROUNDDOWN((F26-(I26*$B$10))/$B$10,0)),(ROUNDDOWN((G26-(J26*$C$10))/$B$10,0)))*L26) -> #VALUE! | N26: =(K26*L26)+((MAX((ROUNDDOWN((G26-(K26*$B$10))/$B$10,0)),(ROUNDDOWN((F26-(L26*$C$10))/$B$10,0)))*J26)) -> #VALUE! | O26: =MAX(M26:N26) -> #VALUE! | P26: =H26/O26 -> #VALUE! | R26: =ROUNDUP(Q26/O26,0) -> #VALUE! | AL26: 0 | AM26: 0 | AN26: -0.5 | AO26: -0.5 | AP26: 0 | BA26: =IFERROR(__xludf.DUMMYFUNCTION("SPLIT(AW26,""*"")"),"#VALUE!") -> #VALUE!
I27: =ROUNDDOWN(F27/$B$10,0) -> #VALUE! | J27: =ROUNDDOWN(G27/$C$10,0) -> #DIV/0! | K27: =ROUNDDOWN(G27/$B$10,0) -> #VALUE! | L27: =ROUNDDOWN(F27/$C$10,0) -> #DIV/0! | M27: =(I27*J27)+(MAX((ROUNDDOWN((F27-(I27*$B$10))/$B$10,0)),(ROUNDDOWN((G27-(J27*$C$10))/$B$10,0)))*L27) -> #VALUE! | N27: =(K27*L27)+((MAX((ROUNDDOWN((G27-(K27*$B$10))/$B$10,0)),(ROUNDDOWN((F27-(L27*$C$10))/$B$10,0)))*J27)) -> #VALUE! | O27: =MAX(M27:N27) -> #VALUE! | P27: =H27/O27 -> #VALUE! | R27: =ROUNDUP(Q27/O27,0) -> #VALUE! | AL27: 0 | AM27: 0 | AN27: -0.5 | AO27: -0.5 | AP27: 0 | BA27: =IFERROR(__xludf.DUMMYFUNCTION("SPLIT(AW27,""*"")"),"#VALUE!") -> #VALUE!
I28: =ROUNDDOWN(F28/$B$10,0) -> #VALUE! | J28: =ROUNDDOWN(G28/$C$10,0) -> #DIV/0! | K28: =ROUNDDOWN(G28/$B$10,0) -> #VALUE! | L28: =ROUNDDOWN(F28/$C$10,0) -> #DIV/0! | M28: =(I28*J28)+(MAX((ROUNDDOWN((F28-(I28*$B$10))/$B$10,0)),(ROUNDDOWN((G28-(J28*$C$10))/$B$10,0)))*L28) -> #VALUE! | N28: =(K28*L28)+((MAX((ROUNDDOWN((G28-(K28*$B$10))/$B$10,0)),(ROUNDDOWN((F28-(L28*$C$10))/$B$10,0)))*J28)) -> #VALUE! | O28: =MAX(M28:N28) -> #VALUE! | P28: =H28/O28 -> #VALUE! | R28: =ROUNDUP(Q28/O28,0) -> #VALUE! | U28: Sheet Size | V28: Machine | W28: Sheet Length | X28: Sheet Width | Y28: Sheet Value | Z28: F1 | AA28: F2 | AB28: F3 | AC28: F4 | AD28: F5 | AE28: F6 | AF28: Products Per Sheet | AG28: Per Product Cost | AI28: Sheets Required | AL28: 0 | AM28: 0 | AN28: -0.5 | AO28: -0.5 | AP28: 0 | BA28: =IFERROR(__xludf.DUMMYFUNCTION("SPLIT(AW28,""*"")"),"#VALUE!") -> #VALUE!
I29: =ROUNDDOWN(F29/$B$10,0) -> #VALUE! | J29: =ROUNDDOWN(G29/$C$10,0) -> #DIV/0! | K29: =ROUNDDOWN(G29/$B$10,0) -> #VALUE! | L29: =ROUNDDOWN(F29/$C$10,0) -> #DIV/0! | M29: =(I29*J29)+(MAX((ROUNDDOWN((F29-(I29*$B$10))/$B$10,0)),(ROUNDDOWN((G29-(J29*$C$10))/$B$10,0)))*L29) -> #VALUE! | N29: =(K29*L29)+((MAX((ROUNDDOWN((G29-(K29*$B$10))/$B$10,0)),(ROUNDDOWN((F29-(L29*$C$10))/$B$10,0)))*J29)) -> #VALUE! | O29: =MAX(M29:N29) -> #VALUE! | P29: =H29/O29 -> #VALUE! | R29: =ROUNDUP(Q29/O29,0) -> #VALUE! | U29: =IFERROR(__xludf.DUMMYFUNCTION("QUERY($D$10:$S$20,U$12)"),"#VALUE!") -> #VALUE! | AL29: 0 | AM29: 0 | AN29: -0.5 | AO29: -0.5 | AP29: 0 | BA29: =IFERROR(__xludf.DUMMYFUNCTION("SPLIT(AW29,""*"")"),"#VALUE!") -> #VALUE!
I30: =ROUNDDOWN(F30/$B$10,0) -> #VALUE! | J30: =ROUNDDOWN(G30/$C$10,0) -> #DIV/0! | K30: =ROUNDDOWN(G30/$B$10,0) -> #VALUE! | L30: =ROUNDDOWN(F30/$C$10,0) -> #DIV/0! | M30: =(I30*J30)+(MAX((ROUNDDOWN((F30-(I30*$B$10))/$B$10,0)),(ROUNDDOWN((G30-(J30*$C$10))/$B$10,0)))*L30) -> #VALUE! | N30: =(K30*L30)+((MAX((ROUNDDOWN((G30-(K30*$B$10))/$B$10,0)),(ROUNDDOWN((F30-(L30*$C$10))/$B$10,0)))*J30)) -> #VALUE! | O30: =MAX(M30:N30) -> #VALUE! | P30: =H30/O30 -> #VALUE! | R30: =ROUNDUP(Q30/O30,0) -> #VALUE! | AL30: 0 | AM30: 0 | AN30: -0.5 | AO30: -0.5 | AP30: 0 | BA30: =IFERROR(__xludf.DUMMYFUNCTION("SPLIT(AW30,""*"")"),"#VALUE!") -> #VALUE!
I31: =ROUNDDOWN(F31/$B$10,0) -> #VALUE! | J31: =ROUNDDOWN(G31/$C$10,0) -> #DIV/0! | K31: =ROUNDDOWN(G31/$B$10,0) -> #VALUE! | L31: =ROUNDDOWN(F31/$C$10,0) -> #DIV/0! | M31: =(I31*J31)+(MAX((ROUNDDOWN((F31-(I31*$B$10))/$B$10,0)),(ROUNDDOWN((G31-(J31*$C$10))/$B$10,0)))*L31) -> #VALUE! | N31: =(K31*L31)+((MAX((ROUNDDOWN((G31-(K31*$B$10))/$B$10,0)),(ROUNDDOWN((F31-(L31*$C$10))/$B$10,0)))*J31)) -> #VALUE! | O31: =MAX(M31:N31) -> #VALUE! | P31: =H31/O31 -> #VALUE! | R31: =ROUNDUP(Q31/O31,0) -> #VALUE! | AL31: 0 | AM31: 0 | AN31: -0.5 | AO31: -0.5 | AP31: 0 | BA31: =IFERROR(__xludf.DUMMYFUNCTION("SPLIT(AW31,""*"")"),"#VALUE!") -> #VALUE!
I32: =ROUNDDOWN(F32/$B$10,0) -> #VALUE! | J32: =ROUNDDOWN(G32/$C$10,0) -> #DIV/0! | K32: =ROUNDDOWN(G32/$B$10,0) -> #VALUE! | L32: =ROUNDDOWN(F32/$C$10,0) -> #DIV/0! | M32: =(I32*J32)+(MAX((ROUNDDOWN((F32-(I32*$B$10))/$B$10,0)),(ROUNDDOWN((G32-(J32*$C$10))/$B$10,0)))*L32) -> #VALUE! | N32: =(K32*L32)+((MAX((ROUNDDOWN((G32-(K32*$B$10))/$B$10,0)),(ROUNDDOWN((F32-(L32*$C$10))/$B$10,0)))*J32)) -> #VALUE! | O32: =MAX(M32:N32) -> #VALUE! | P32: =H32/O32 -> #VALUE! | R32: =ROUNDUP(Q32/O32,0) -> #VALUE! | AL32: 0 | AM32: 0 | AN32: -0.5 | AO32: -0.5 | AP32: 0 | BA32: =IFERROR(__xludf.DUMMYFUNCTION("SPLIT(AW32,""*"")"),"#VALUE!") -> #VALUE!
I33: =ROUNDDOWN(F33/$B$10,0) -> #VALUE! | J33: =ROUNDDOWN(G33/$C$10,0) -> #DIV/0! | K33: =ROUNDDOWN(G33/$B$10,0) -> #VALUE! | L33: =ROUNDDOWN(F33/$C$10,0) -> #DIV/0! | M33: =(I33*J33)+(MAX((ROUNDDOWN((F33-(I33*$B$10))/$B$10,0)),(ROUNDDOWN((G33-(J33*$C$10))/$B$10,0)))*L33) -> #VALUE! | N33: =(K33*L33)+((MAX((ROUNDDOWN((G33-(K33*$B$10))/$B$10,0)),(ROUNDDOWN((F33-(L33*$C$10))/$B$10,0)))*J33)) -> #VALUE! | O33: =MAX(M33:N33) -> #VALUE! | P33: =H33/O33 -> #VALUE! | R33: =ROUNDUP(Q33/O33,0) -> #VALUE! | AL33: 0 | AM33: 0 | AN33: -0.5 | AO33: -0.5 | AP33: 0 | BA33: =IFERROR(__xludf.DUMMYFUNCTION("SPLIT(AW33,""*"")"),"#VALUE!") -> #VALUE!
I34: =ROUNDDOWN(F34/$B$10,0) -> #VALUE! | J34: =ROUNDDOWN(G34/$C$10,0) -> #DIV/0! | K34: =ROUNDDOWN(G34/$B$10,0) -> #VALUE! | L34: =ROUNDDOWN(F34/$C$10,0) -> #DIV/0! | M34: =(I34*J34)+(MAX((ROUNDDOWN((F34-(I34*$B$10))/$B$10,0)),(ROUNDDOWN((G34-(J34*$C$10))/$B$10,0)))*L34) -> #VALUE! | N34: =(K34*L34)+((MAX((ROUNDDOWN((G34-(K34*$B$10))/$B$10,0)),(ROUNDDOWN((F34-(L34*$C$10))/$B$10,0)))*J34)) -> #VALUE! | O34: =MAX(M34:N34) -> #VALUE! | P34: =H34/O34 -> #VALUE! | R34: =ROUNDUP(Q34/O34,0) -> #VALUE! | AL34: 0 | AM34: 0 | AN34: -0.5 | AO34: -0.5 | AP34: 0 | BA34: =IFERROR(__xludf.DUMMYFUNCTION("SPLIT(AW34,""*"")"),"#VALUE!") -> #VALUE!
I35: =ROUNDDOWN(F35/$B$10,0) -> #VALUE! | J35: =ROUNDDOWN(G35/$C$10,0) -> #DIV/0! | K35: =ROUNDDOWN(G35/$B$10,0) -> #VALUE! | L35: =ROUNDDOWN(F35/$C$10,0) -> #DIV/0! | M35: =(I35*J35)+(MAX((ROUNDDOWN((F35-(I35*$B$10))/$B$10,0)),(ROUNDDOWN((G35-(J35*$C$10))/$B$10,0)))*L35) -> #VALUE! | N35: =(K35*L35)+((MAX((ROUNDDOWN((G35-(K35*$B$10))/$B$10,0)),(ROUNDDOWN((F35-(L35*$C$10))/$B$10,0)))*J35)) -> #VALUE! | O35: =MAX(M35:N35) -> #VALUE! | P35: =H35/O35 -> #VALUE! | R35: =ROUNDUP(Q35/O35,0) -> #VALUE! | AL35: 0 | AM35: 0 | AN35: -0.5 | AO35: -0.5 | AP35: 0 | BA35: =IFERROR(__xludf.DUMMYFUNCTION("SPLIT(AW35,""*"")"),"#VALUE!") -> #VALUE!
I36: =ROUNDDOWN(F36/$B$10,0) -> #VALUE! | J36: =ROUNDDOWN(G36/$C$10,0) -> #DIV/0! | K36: =ROUNDDOWN(G36/$B$10,0) -> #VALUE! | L36: =ROUNDDOWN(F36/$C$10,0) -> #DIV/0! | M36: =(I36*J36)+(MAX((ROUNDDOWN((F36-(I36*$B$10))/$B$10,0)),(ROUNDDOWN((G36-(J36*$C$10))/$B$10,0)))*L36) -> #VALUE! | N36: =(K36*L36)+((MAX((ROUNDDOWN((G36-(K36*$B$10))/$B$10,0)),(ROUNDDOWN((F36-(L36*$C$10))/$B$10,0)))*J36)) -> #VALUE! | O36: =MAX(M36:N36) -> #VALUE! | P36: =H36/O36 -> #VALUE! | R36: =ROUNDUP(Q36/O36,0) -> #VALUE! | AL36: 0 | AM36: 0 | AN36: -0.5 | AO36: -0.5 | AP36: 0 | BA36: =IFERROR(__xludf.DUMMYFUNCTION("SPLIT(AW36,""*"")"),"#VALUE!") -> #VALUE!
I37: =ROUNDDOWN(F37/$B$10,0) -> #VALUE! | J37: =ROUNDDOWN(G37/$C$10,0) -> #DIV/0! | K37: =ROUNDDOWN(G37/$B$10,0) -> #VALUE! | L37: =ROUNDDOWN(F37/$C$10,0) -> #DIV/0! | M37: =(I37*J37)+(MAX((ROUNDDOWN((F37-(I37*$B$10))/$B$10,0)),(ROUNDDOWN((G37-(J37*$C$10))/$B$10,0)))*L37) -> #VALUE! | N37: =(K37*L37)+((MAX((ROUNDDOWN((G37-(K37*$B$10))/$B$10,0)),(ROUNDDOWN((F37-(L37*$C$10))/$B$10,0)))*J37)) -> #VALUE! | O37: =MAX(M37:N37) -> #VALUE! | P37: =H37/O37 -> #VALUE! | R37: =ROUNDUP(Q37/O37,0) -> #VALUE! | AL37: 0 | AM37: 0 | AN37: -0.5 | AO37: -0.5 | AP37: 0 | BA37: =IFERROR(__xludf.DUMMYFUNCTION("SPLIT(AW37,""*"")"),"#VALUE!") -> #VALUE!
I38: =ROUNDDOWN(F38/$B$10,0) -> #VALUE! | J38: =ROUNDDOWN(G38/$C$10,0) -> #DIV/0! | K38: =ROUNDDOWN(G38/$B$10,0) -> #VALUE! | L38: =ROUNDDOWN(F38/$C$10,0) -> #DIV/0! | M38: =(I38*J38)+(MAX((ROUNDDOWN((F38-(I38*$B$10))/$B$10,0)),(ROUNDDOWN((G38-(J38*$C$10))/$B$10,0)))*L38) -> #VALUE! | N38: =(K38*L38)+((MAX((ROUNDDOWN((G38-(K38*$B$10))/$B$10,0)),(ROUNDDOWN((F38-(L38*$C$10))/$B$10,0)))*J38)) -> #VALUE! | O38: =MAX(M38:N38) -> #VALUE! | P38: =H38/O38 -> #VALUE! | R38: =ROUNDUP(Q38/O38,0) -> #VALUE! | AL38: 0 | AM38: 0 | AN38: -0.5 | AO38: -0.5 | AP38: 0 | BA38: =IFERROR(__xludf.DUMMYFUNCTION("SPLIT(AW38,""*"")"),"#VALUE!") -> #VALUE!
I39: =ROUNDDOWN(F39/$B$10,0) -> #VALUE! | J39: =ROUNDDOWN(G39/$C$10,0) -> #DIV/0! | K39: =ROUNDDOWN(G39/$B$10,0) -> #VALUE! | L39: =ROUNDDOWN(F39/$C$10,0) -> #DIV/0! | M39: =(I39*J39)+(MAX((ROUNDDOWN((F39-(I39*$B$10))/$B$10,0)),(ROUNDDOWN((G39-(J39*$C$10))/$B$10,0)))*L39) -> #VALUE! | N39: =(K39*L39)+((MAX((ROUNDDOWN((G39-(K39*$B$10))/$B$10,0)),(ROUNDDOWN((F39-(L39*$C$10))/$B$10,0)))*J39)) -> #VALUE! | O39: =MAX(M39:N39) -> #VALUE! | P39: =H39/O39 -> #VALUE! | R39: =ROUNDUP(Q39/O39,0) -> #VALUE! | AL39: 0 | AM39: 0 | AN39: -0.5 | AO39: -0.5 | AP39: 0 | BA39: =IFERROR(__xludf.DUMMYFUNCTION("SPLIT(AW39,""*"")"),"#VALUE!") -> #VALUE!
I40: =ROUNDDOWN(F40/$B$10,0) -> #VALUE! | J40: =ROUNDDOWN(G40/$C$10,0) -> #DIV/0! | K40: =ROUNDDOWN(G40/$B$10,0) -> #VALUE! | L40: =ROUNDDOWN(F40/$C$10,0) -> #DIV/0! | M40: =(I40*J40)+(MAX((ROUNDDOWN((F40-(I40*$B$10))/$B$10,0)),(ROUNDDOWN((G40-(J40*$C$10))/$B$10,0)))*L40) -> #VALUE! | N40: =(K40*L40)+((MAX((ROUNDDOWN((G40-(K40*$B$10))/$B$10,0)),(ROUNDDOWN((F40-(L40*$C$10))/$B$10,0)))*J40)) -> #VALUE! | O40: =MAX(M40:N40) -> #VALUE! | P40: =H40/O40 -> #VALUE! | R40: =ROUNDUP(Q40/O40,0) -> #VALUE! | AL40: 0 | AM40: 0 | AN40: -0.5 | AO40: -0.5 | AP40: 0 | BA40: =IFERROR(__xludf.DUMMYFUNCTION("SPLIT(AW40,""*"")"),"#VALUE!") -> #VALUE!
I41: =ROUNDDOWN(F41/$B$10,0) -> #VALUE! | J41: =ROUNDDOWN(G41/$C$10,0) -> #DIV/0! | K41: =ROUNDDOWN(G41/$B$10,0) -> #VALUE! | L41: =ROUNDDOWN(F41/$C$10,0) -> #DIV/0! | M41: =(I41*J41)+(MAX((ROUNDDOWN((F41-(I41*$B$10))/$B$10,0)),(ROUNDDOWN((G41-(J41*$C$10))/$B$10,0)))*L41) -> #VALUE! | N41: =(K41*L41)+((MAX((ROUNDDOWN((G41-(K41*$B$10))/$B$10,0)),(ROUNDDOWN((F41-(L41*$C$10))/$B$10,0)))*J41)) -> #VALUE! | O41: =MAX(M41:N41) -> #VALUE! | P41: =H41/O41 -> #VALUE! | R41: =ROUNDUP(Q41/O41,0) -> #VALUE! | AL41: 0 | AM41: 0 | AN41: -0.5 | AO41: -0.5 | AP41: 0 | BA41: =IFERROR(__xludf.DUMMYFUNCTION("SPLIT(AW41,""*"")"),"#VALUE!") -> #VALUE!
I42: =ROUNDDOWN(F42/$B$10,0) -> #VALUE! | J42: =ROUNDDOWN(G42/$C$10,0) -> #DIV/0! | K42: =ROUNDDOWN(G42/$B$10,0) -> #VALUE! | L42: =ROUNDDOWN(F42/$C$10,0) -> #DIV/0! | M42: =(I42*J42)+(MAX((ROUNDDOWN((F42-(I42*$B$10))/$B$10,0)),(ROUNDDOWN((G42-(J42*$C$10))/$B$10,0)))*L42) -> #VALUE! | N42: =(K42*L42)+((MAX((ROUNDDOWN((G42-(K42*$B$10))/$B$10,0)),(ROUNDDOWN((F42-(L42*$C$10))/$B$10,0)))*J42)) -> #VALUE! | O42: =MAX(M42:N42) -> #VALUE! | P42: =H42/O42 -> #VALUE! | R42: =ROUNDUP(Q42/O42,0) -> #VALUE! | AL42: 0 | AM42: 0 | AN42: -0.5 | AO42: -0.5 | AP42: 0 | BA42: =IFERROR(__xludf.DUMMYFUNCTION("SPLIT(AW42,""*"")"),"#VALUE!") -> #VALUE!
I43: =ROUNDDOWN(F43/$B$10,0) -> #VALUE! | J43: =ROUNDDOWN(G43/$C$10,0) -> #DIV/0! | K43: =ROUNDDOWN(G43/$B$10,0) -> #VALUE! | L43: =ROUNDDOWN(F43/$C$10,0) -> #DIV/0! | M43: =(I43*J43)+(MAX((ROUNDDOWN((F43-(I43*$B$10))/$B$10,0)),(ROUNDDOWN((G43-(J43*$C$10))/$B$10,0)))*L43) -> #VALUE! | N43: =(K43*L43)+((MAX((ROUNDDOWN((G43-(K43*$B$10))/$B$10,0)),(ROUNDDOWN((F43-(L43*$C$10))/$B$10,0)))*J43)) -> #VALUE! | O43: =MAX(M43:N43) -> #VALUE! | P43: =H43/O43 -> #VALUE! | R43: =ROUNDUP(Q43/O43,0) -> #VALUE! | AL43: 0 | AM43: 0 | AN43: -0.5 | AO43: -0.5 | AP43: 0 | BA43: =IFERROR(__xludf.DUMMYFUNCTION("SPLIT(AW43,""*"")"),"#VALUE!") -> #VALUE!
I44: =ROUNDDOWN(F44/$B$10,0) -> #VALUE! | J44: =ROUNDDOWN(G44/$C$10,0) -> #DIV/0! | K44: =ROUNDDOWN(G44/$B$10,0) -> #VALUE! | L44: =ROUNDDOWN(F44/$C$10,0) -> #DIV/0! | M44: =(I44*J44)+(MAX((ROUNDDOWN((F44-(I44*$B$10))/$B$10,0)),(ROUNDDOWN((G44-(J44*$C$10))/$B$10,0)))*L44) -> #VALUE! | N44: =(K44*L44)+((MAX((ROUNDDOWN((G44-(K44*$B$10))/$B$10,0)),(ROUNDDOWN((F44-(L44*$C$10))/$B$10,0)))*J44)) -> #VALUE! | O44: =MAX(M44:N44) -> #VALUE! | P44: =H44/O44 -> #VALUE! | R44: =ROUNDUP(Q44/O44,0) -> #VALUE! | AL44: 0 | AM44: 0 | AN44: -0.5 | AO44: -0.5 | AP44: 0 | BA44: =IFERROR(__xludf.DUMMYFUNCTION("SPLIT(AW44,""*"")"),"#VALUE!") -> #VALUE!
I45: =ROUNDDOWN(F45/$B$10,0) -> #VALUE! | J45: =ROUNDDOWN(G45/$C$10,0) -> #DIV/0! | K45: =ROUNDDOWN(G45/$B$10,0) -> #VALUE! | L45: =ROUNDDOWN(F45/$C$10,0) -> #DIV/0! | M45: =(I45*J45)+(MAX((ROUNDDOWN((F45-(I45*$B$10))/$B$10,0)),(ROUNDDOWN((G45-(J45*$C$10))/$B$10,0)))*L45) -> #VALUE! | N45: =(K45*L45)+((MAX((ROUNDDOWN((G45-(K45*$B$10))/$B$10,0)),(ROUNDDOWN((F45-(L45*$C$10))/$B$10,0)))*J45)) -> #VALUE! | O45: =MAX(M45:N45) -> #VALUE! | P45: =H45/O45 -> #VALUE! | R45: =ROUNDUP(Q45/O45,0) -> #VALUE! | AL45: 0 | AM45: 0 | AN45: -0.5 | AO45: -0.5 | AP45: 0 | BA45: =IFERROR(__xludf.DUMMYFUNCTION("SPLIT(AW45,""*"")"),"#VALUE!") -> #VALUE!
I46: =ROUNDDOWN(F46/$B$10,0) -> #VALUE! | J46: =ROUNDDOWN(G46/$C$10,0) -> #DIV/0! | K46: =ROUNDDOWN(G46/$B$10,0) -> #VALUE! | L46: =ROUNDDOWN(F46/$C$10,0) -> #DIV/0! | M46: =(I46*J46)+(MAX((ROUNDDOWN((F46-(I46*$B$10))/$B$10,0)),(ROUNDDOWN((G46-(J46*$C$10))/$B$10,0)))*L46) -> #VALUE! | N46: =(K46*L46)+((MAX((ROUNDDOWN((G46-(K46*$B$10))/$B$10,0)),(ROUNDDOWN((F46-(L46*$C$10))/$B$10,0)))*J46)) -> #VALUE! | O46: =MAX(M46:N46) -> #VALUE! | P46: =H46/O46 -> #VALUE! | R46: =ROUNDUP(Q46/O46,0) -> #VALUE! | T46: =IFERROR(__xludf.DUMMYFUNCTION("QUERY(D10:H629,X8)"),"#VALUE!") -> #VALUE! | AL46: 0 | AM46: 0 | AN46: -0.5 | AO46: -0.5 | AP46: 0 | BA46: =IFERROR(__xludf.DUMMYFUNCTION("SPLIT(AW46,""*"")"),"#VALUE!") -> #VALUE!
I47: =ROUNDDOWN(F47/$B$10,0) -> #VALUE! | J47: =ROUNDDOWN(G47/$C$10,0) -> #DIV/0! | K47: =ROUNDDOWN(G47/$B$10,0) -> #VALUE! | L47: =ROUNDDOWN(F47/$C$10,0) -> #DIV/0! | M47: =(I47*J47)+(MAX((ROUNDDOWN((F47-(I47*$B$10))/$B$10,0)),(ROUNDDOWN((G47-(J47*$C$10))/$B$10,0)))*L47) -> #VALUE! | N47: =(K47*L47)+((MAX((ROUNDDOWN((G47-(K47*$B$10))/$B$10,0)),(ROUNDDOWN((F47-(L47*$C$10))/$B$10,0)))*J47)) -> #VALUE! | O47: =MAX(M47:N47) -> #VALUE! | P47: =H47/O47 -> #VALUE! | R47: =ROUNDUP(Q47/O47,0) -> #VALUE! | AL47: 0 | AM47: 0 | AN47: -0.5 | AO47: -0.5 | AP47: 0 | BA47: =IFERROR(__xludf.DUMMYFUNCTION("SPLIT(AW47,""*"")"),"#VALUE!") -> #VALUE!
I48: =ROUNDDOWN(F48/$B$10,0) -> #VALUE! | J48: =ROUNDDOWN(G48/$C$10,0) -> #DIV/0! | K48: =ROUNDDOWN(G48/$B$10,0) -> #VALUE! | L48: =ROUNDDOWN(F48/$C$10,0) -> #DIV/0! | M48: =(I48*J48)+(MAX((ROUNDDOWN((F48-(I48*$B$10))/$B$10,0)),(ROUNDDOWN((G48-(J48*$C$10))/$B$10,0)))*L48) -> #VALUE! | N48: =(K48*L48)+((MAX((ROUNDDOWN((G48-(K48*$B$10))/$B$10,0)),(ROUNDDOWN((F48-(L48*$C$10))/$B$10,0)))*J48)) -> #VALUE! | O48: =MAX(M48:N48) -> #VALUE! | P48: =H48/O48 -> #VALUE! | R48: =ROUNDUP(Q48/O48,0) -> #VALUE! | AL48: 0 | AM48: 0 | AN48: -0.5 | AO48: -0.5 | AP48: 0 | BA48: =IFERROR(__xludf.DUMMYFUNCTION("SPLIT(AW48,""*"")"),"#VALUE!") -> #VALUE!
I49: =ROUNDDOWN(F49/$B$10,0) -> #VALUE! | J49: =ROUNDDOWN(G49/$C$10,0) -> #DIV/0! | K49: =ROUNDDOWN(G49/$B$10,0) -> #VALUE! | L49: =ROUNDDOWN(F49/$C$10,0) -> #DIV/0! | M49: =(I49*J49)+(MAX((ROUNDDOWN((F49-(I49*$B$10))/$B$10,0)),(ROUNDDOWN((G49-(J49*$C$10))/$B$10,0)))*L49) -> #VALUE! | N49: =(K49*L49)+((MAX((ROUNDDOWN((G49-(K49*$B$10))/$B$10,0)),(ROUNDDOWN((F49-(L49*$C$10))/$B$10,0)))*J49)) -> #VALUE! | O49: =MAX(M49:N49) -> #VALUE! | P49: =H49/O49 -> #VALUE! | R49: =ROUNDUP(Q49/O49,0) -> #VALUE! | AL49: 0 | AM49: 0 | AN49: -0.5 | AO49: -0.5 | AP49: 0 | BA49: =IFERROR(__xludf.DUMMYFUNCTION("SPLIT(AW49,""*"")"),"#VALUE!") -> #VALUE!
I50: =ROUNDDOWN(F50/$B$10,0) -> #VALUE! | J50: =ROUNDDOWN(G50/$C$10,0) -> #DIV/0! | K50: =ROUNDDOWN(G50/$B$10,0) -> #VALUE! | L50: =ROUNDDOWN(F50/$C$10,0) -> #DIV/0! | M50: =(I50*J50)+(MAX((ROUNDDOWN((F50-(I50*$B$10))/$B$10,0)),(ROUNDDOWN((G50-(J50*$C$10))/$B$10,0)))*L50) -> #VALUE! | N50: =(K50*L50)+((MAX((ROUNDDOWN((G50-(K50*$B$10))/$B$10,0)),(ROUNDDOWN((F50-(L50*$C$10))/$B$10,0)))*J50)) -> #VALUE! | O50: =MAX(M50:N50) -> #VALUE! | P50: =H50/O50 -> #VALUE! | R50: =ROUNDUP(Q50/O50,0) -> #VALUE! | AL50: 0 | AM50: 0 | AN50: -0.5 | AO50: -0.5 | AP50: 0 | BA50: =IFERROR(__xludf.DUMMYFUNCTION("SPLIT(AW50,""*"")"),"#VALUE!") -> #VALUE!
I51: =ROUNDDOWN(F51/$B$10,0) -> #VALUE! | J51: =ROUNDDOWN(G51/$C$10,0) -> #DIV/0! | K51: =ROUNDDOWN(G51/$B$10,0) -> #VALUE! | L51: =ROUNDDOWN(F51/$C$10,0) -> #DIV/0! | M51: =(I51*J51)+(MAX((ROUNDDOWN((F51-(I51*$B$10))/$B$10,0)),(ROUNDDOWN((G51-(J51*$C$10))/$B$10,0)))*L51) -> #VALUE! | N51: =(K51*L51)+((MAX((ROUNDDOWN((G51-(K51*$B$10))/$B$10,0)),(ROUNDDOWN((F51-(L51*$C$10))/$B$10,0)))*J51)) -> #VALUE! | O51: =MAX(M51:N51) -> #VALUE! | P51: =H51/O51 -> #VALUE! | R51: =ROUNDUP(Q51/O51,0) -> #VALUE! | AL51: 0 | AM51: 0 | AN51: -0.5 | AO51: -0.5 | AP51: 0 | BA51: =IFERROR(__xludf.DUMMYFUNCTION("SPLIT(AW51,""*"")"),"#VALUE!") -> #VALUE!
I52: =ROUNDDOWN(F52/$B$10,0) -> #VALUE! | J52: =ROUNDDOWN(G52/$C$10,0) -> #DIV/0! | K52: =ROUNDDOWN(G52/$B$10,0) -> #VALUE! | L52: =ROUNDDOWN(F52/$C$10,0) -> #DIV/0! | M52: =(I52*J52)+(MAX((ROUNDDOWN((F52-(I52*$B$10))/$B$10,0)),(ROUNDDOWN((G52-(J52*$C$10))/$B$10,0)))*L52) -> #VALUE! | N52: =(K52*L52)+((MAX((ROUNDDOWN((G52-(K52*$B$10))/$B$10,0)),(ROUNDDOWN((F52-(L52*$C$10))/$B$10,0)))*J52)) -> #VALUE! | O52: =MAX(M52:N52) -> #VALUE! | P52: =H52/O52 -> #VALUE! | R52: =ROUNDUP(Q52/O52,0) -> #VALUE! | AL52: 0 | AM52: 0 | AN52: -0.5 | AO52: -0.5 | AP52: 0 | BA52: =IFERROR(__xludf.DUMMYFUNCTION("SPLIT(AW52,""*"")"),"#VALUE!") -> #VALUE!
I53: =ROUNDDOWN(F53/$B$10,0) -> #VALUE! | J53: =ROUNDDOWN(G53/$C$10,0) -> #DIV/0! | K53: =ROUNDDOWN(G53/$B$10,0) -> #VALUE! | L53: =ROUNDDOWN(F53/$C$10,0) -> #DIV/0! | M53: =(I53*J53)+(MAX((ROUNDDOWN((F53-(I53*$B$10))/$B$10,0)),(ROUNDDOWN((G53-(J53*$C$10))/$B$10,0)))*L53) -> #VALUE! | N53: =(K53*L53)+((MAX((ROUNDDOWN((G53-(K53*$B$10))/$B$10,0)),(ROUNDDOWN((F53-(L53*$C$10))/$B$10,0)))*J53)) -> #VALUE! | O53: =MAX(M53:N53) -> #VALUE! | P53: =H53/O53 -> #VALUE! | R53: =ROUNDUP(Q53/O53,0) -> #VALUE! | AL53: 0 | AM53: 0 | AN53: -0.5 | AO53: -0.5 | AP53: 0 | BA53: =IFERROR(__xludf.DUMMYFUNCTION("SPLIT(AW53,""*"")"),"#VALUE!") -> #VALUE!
I54: =ROUNDDOWN(F54/$B$10,0) -> #VALUE! | J54: =ROUNDDOWN(G54/$C$10,0) -> #DIV/0! | K54: =ROUNDDOWN(G54/$B$10,0) -> #VALUE! | L54: =ROUNDDOWN(F54/$C$10,0) -> #DIV/0! | M54: =(I54*J54)+(MAX((ROUNDDOWN((F54-(I54*$B$10))/$B$10,0)),(ROUNDDOWN((G54-(J54*$C$10))/$B$10,0)))*L54) -> #VALUE! | N54: =(K54*L54)+((MAX((ROUNDDOWN((G54-(K54*$B$10))/$B$10,0)),(ROUNDDOWN((F54-(L54*$C$10))/$B$10,0)))*J54)) -> #VALUE! | O54: =MAX(M54:N54) -> #VALUE! | P54: =H54/O54 -> #VALUE! | R54: =ROUNDUP(Q54/O54,0) -> #VALUE! | AL54: 0 | AM54: 0 | AN54: -0.5 | AO54: -0.5 | AP54: 0 | BA54: =IFERROR(__xludf.DUMMYFUNCTION("SPLIT(AW54,""*"")"),"#VALUE!") -> #VALUE!
I55: =ROUNDDOWN(F55/$B$10,0) -> #VALUE! | J55: =ROUNDDOWN(G55/$C$10,0) -> #DIV/0! | K55: =ROUNDDOWN(G55/$B$10,0) -> #VALUE! | L55: =ROUNDDOWN(F55/$C$10,0) -> #DIV/0! | M55: =(I55*J55)+(MAX((ROUNDDOWN((F55-(I55*$B$10))/$B$10,0)),(ROUNDDOWN((G55-(J55*$C$10))/$B$10,0)))*L55) -> #VALUE! | N55: =(K55*L55)+((MAX((ROUNDDOWN((G55-(K55*$B$10))/$B$10,0)),(ROUNDDOWN((F55-(L55*$C$10))/$B$10,0)))*J55)) -> #VALUE! | O55: =MAX(M55:N55) -> #VALUE! | P55: =H55/O55 -> #VALUE! | R55: =ROUNDUP(Q55/O55,0) -> #VALUE! | AL55: 0 | AM55: 0 | AN55: -0.5 | AO55: -0.5 | AP55: 0 | BA55: =IFERROR(__xludf.DUMMYFUNCTION("SPLIT(AW55,""*"")"),"#VALUE!") -> #VALUE!
I56: =ROUNDDOWN(F56/$B$10,0) -> #VALUE! | J56: =ROUNDDOWN(G56/$C$10,0) -> #DIV/0! | K56: =ROUNDDOWN(G56/$B$10,0) -> #VALUE! | L56: =ROUNDDOWN(F56/$C$10,0) -> #DIV/0! | M56: =(I56*J56)+(MAX((ROUNDDOWN((F56-(I56*$B$10))/$B$10,0)),(ROUNDDOWN((G56-(J56*$C$10))/$B$10,0)))*L56) -> #VALUE! | N56: =(K56*L56)+((MAX((ROUNDDOWN((G56-(K56*$B$10))/$B$10,0)),(ROUNDDOWN((F56-(L56*$C$10))/$B$10,0)))*J56)) -> #VALUE! | O56: =MAX(M56:N56) -> #VALUE! | P56: =H56/O56 -> #VALUE! | R56: =ROUNDUP(Q56/O56,0) -> #VALUE! | AL56: 0 | AM56: 0 | AN56: -0.5 | AO56: -0.5 | AP56: 0 | BA56: =IFERROR(__xludf.DUMMYFUNCTION("SPLIT(AW56,""*"")"),"#VALUE!") -> #VALUE!
I57: =ROUNDDOWN(F57/$B$10,0) -> #VALUE! | J57: =ROUNDDOWN(G57/$C$10,0) -> #DIV/0! | K57: =ROUNDDOWN(G57/$B$10,0) -> #VALUE! | L57: =ROUNDDOWN(F57/$C$10,0) -> #DIV/0! | M57: =(I57*J57)+(MAX((ROUNDDOWN((F57-(I57*$B$10))/$B$10,0)),(ROUNDDOWN((G57-(J57*$C$10))/$B$10,0)))*L57) -> #VALUE! | N57: =(K57*L57)+((MAX((ROUNDDOWN((G57-(K57*$B$10))/$B$10,0)),(ROUNDDOWN((F57-(L57*$C$10))/$B$10,0)))*J57)) -> #VALUE! | O57: =MAX(M57:N57) -> #VALUE! | P57: =H57/O57 -> #VALUE! | R57: =ROUNDUP(Q57/O57,0) -> #VALUE! | AL57: 0 | AM57: 0 | AN57: -0.5 | AO57: -0.5 | AP57: 0 | BA57: =IFERROR(__xludf.DUMMYFUNCTION("SPLIT(AW57,""*"")"),"#VALUE!") -> #VALUE!
I58: =ROUNDDOWN(F58/$B$10,0) -> #VALUE! | J58: =ROUNDDOWN(G58/$C$10,0) -> #DIV/0! | K58: =ROUNDDOWN(G58/$B$10,0) -> #VALUE! | L58: =ROUNDDOWN(F58/$C$10,0) -> #DIV/0! | M58: =(I58*J58)+(MAX((ROUNDDOWN((F58-(I58*$B$10))/$B$10,0)),(ROUNDDOWN((G58-(J58*$C$10))/$B$10,0)))*L58) -> #VALUE! | N58: =(K58*L58)+((MAX((ROUNDDOWN((G58-(K58*$B$10))/$B$10,0)),(ROUNDDOWN((F58-(L58*$C$10))/$B$10,0)))*J58)) -> #VALUE! | O58: =MAX(M58:N58) -> #VALUE! | P58: =H58/O58 -> #VALUE! | R58: =ROUNDUP(Q58/O58,0) -> #VALUE! | AL58: 0 | AM58: 0 | AN58: -0.5 | AO58: -0.5 | AP58: 0 | BA58: =IFERROR(__xludf.DUMMYFUNCTION("SPLIT(AW58,""*"")"),"#VALUE!") -> #VALUE!
I59: =ROUNDDOWN(F59/$B$10,0) -> #VALUE! | J59: =ROUNDDOWN(G59/$C$10,0) -> #DIV/0! | K59: =ROUNDDOWN(G59/$B$10,0) -> #VALUE! | L59: =ROUNDDOWN(F59/$C$10,0) -> #DIV/0! | M59: =(I59*J59)+(MAX((ROUNDDOWN((F59-(I59*$B$10))/$B$10,0)),(ROUNDDOWN((G59-(J59*$C$10))/$B$10,0)))*L59) -> #VALUE! | N59: =(K59*L59)+((MAX((ROUNDDOWN((G59-(K59*$B$10))/$B$10,0)),(ROUNDDOWN((F59-(L59*$C$10))/$B$10,0)))*J59)) -> #VALUE! | O59: =MAX(M59:N59) -> #VALUE! | P59: =H59/O59 -> #VALUE! | R59: =ROUNDUP(Q59/O59,0) -> #VALUE! | AL59: 0 | AM59: 0 | AN59: -0.5 | AO59: -0.5 | AP59: 0 | BA59: =IFERROR(__xludf.DUMMYFUNCTION("SPLIT(AW59,""*"")"),"#VALUE!") -> #VALUE!
I60: =ROUNDDOWN(F60/$B$10,0) -> #VALUE! | J60: =ROUNDDOWN(G60/$C$10,0) -> #DIV/0! | K60: =ROUNDDOWN(G60/$B$10,0) -> #VALUE! | L60: =ROUNDDOWN(F60/$C$10,0) -> #DIV/0! | M60: =(I60*J60)+(MAX((ROUNDDOWN((F60-(I60*$B$10))/$B$10,0)),(ROUNDDOWN((G60-(J60*$C$10))/$B$10,0)))*L60) -> #VALUE! | N60: =(K60*L60)+((MAX((ROUNDDOWN((G60-(K60*$B$10))/$B$10,0)),(ROUNDDOWN((F60-(L60*$C$10))/$B$10,0)))*J60)) -> #VALUE! | O60: =MAX(M60:N60) -> #VALUE! | P60: =H60/O60 -> #VALUE! | R60: =ROUNDUP(Q60/O60,0) -> #VALUE! | AL60: 0 | AM60: 0 | AN60: -0.5 | AO60: -0.5 | AP60: 0 | BA60: =IFERROR(__xludf.DUMMYFUNCTION("SPLIT(AW60,""*"")"),"#VALUE!") -> #VALUE!
I61: =ROUNDDOWN(F61/$B$10,0) -> #VALUE! | J61: =ROUNDDOWN(G61/$C$10,0) -> #DIV/0! | K61: =ROUNDDOWN(G61/$B$10,0) -> #VALUE! | L61: =ROUNDDOWN(F61/$C$10,0) -> #DIV/0! | M61: =(I61*J61)+(MAX((ROUNDDOWN((F61-(I61*$B$10))/$B$10,0)),(ROUNDDOWN((G61-(J61*$C$10))/$B$10,0)))*L61) -> #VALUE! | N61: =(K61*L61)+((MAX((ROUNDDOWN((G61-(K61*$B$10))/$B$10,0)),(ROUNDDOWN((F61-(L61*$C$10))/$B$10,0)))*J61)) -> #VALUE! | O61: =MAX(M61:N61) -> #VALUE! | P61: =H61/O61 -> #VALUE! | R61: =ROUNDUP(Q61/O61,0) -> #VALUE! | AL61: 0 | AM61: 0 | AN61: -0.5 | AO61: -0.5 | AP61: 0 | BA61: =IFERROR(__xludf.DUMMYFUNCTION("SPLIT(AW61,""*"")"),"#VALUE!") -> #VALUE!
I62: =ROUNDDOWN(F62/$B$10,0) -> #VALUE! | J62: =ROUNDDOWN(G62/$C$10,0) -> #DIV/0! | K62: =ROUNDDOWN(G62/$B$10,0) -> #VALUE! | L62: =ROUNDDOWN(F62/$C$10,0) -> #DIV/0! | M62: =(I62*J62)+(MAX((ROUNDDOWN((F62-(I62*$B$10))/$B$10,0)),(ROUNDDOWN((G62-(J62*$C$10))/$B$10,0)))*L62) -> #VALUE! | N62: =(K62*L62)+((MAX((ROUNDDOWN((G62-(K62*$B$10))/$B$10,0)),(ROUNDDOWN((F62-(L62*$C$10))/$B$10,0)))*J62)) -> #VALUE! | O62: =MAX(M62:N62) -> #VALUE! | P62: =H62/O62 -> #VALUE! | R62: =ROUNDUP(Q62/O62,0) -> #VALUE! | AL62: 0 | AM62: 0 | AN62: -0.5 | AO62: -0.5 | AP62: 0 | BA62: =IFERROR(__xludf.DUMMYFUNCTION("SPLIT(AW62,""*"")"),"#VALUE!") -> #VALUE!
I63: =ROUNDDOWN(F63/$B$10,0) -> #VALUE! | J63: =ROUNDDOWN(G63/$C$10,0) -> #DIV/0! | K63: =ROUNDDOWN(G63/$B$10,0) -> #VALUE! | L63: =ROUNDDOWN(F63/$C$10,0) -> #DIV/0! | M63: =(I63*J63)+(MAX((ROUNDDOWN((F63-(I63*$B$10))/$B$10,0)),(ROUNDDOWN((G63-(J63*$C$10))/$B$10,0)))*L63) -> #VALUE! | N63: =(K63*L63)+((MAX((ROUNDDOWN((G63-(K63*$B$10))/$B$10,0)),(ROUNDDOWN((F63-(L63*$C$10))/$B$10,0)))*J63)) -> #VALUE! | O63: =MAX(M63:N63) -> #VALUE! | P63: =H63/O63 -> #VALUE! | R63: =ROUNDUP(Q63/O63,0) -> #VALUE! | AL63: 0 | AM63: 0 | AN63: -0.5 | AO63: -0.5 | AP63: 0 | BA63: =IFERROR(__xludf.DUMMYFUNCTION("SPLIT(AW63,""*"")"),"#VALUE!") -> #VALUE!
I64: =ROUNDDOWN(F64/$B$10,0) -> #VALUE! | J64: =ROUNDDOWN(G64/$C$10,0) -> #DIV/0! | K64: =ROUNDDOWN(G64/$B$10,0) -> #VALUE! | L64: =ROUNDDOWN(F64/$C$10,0) -> #DIV/0! | M64: =(I64*J64)+(MAX((ROUNDDOWN((F64-(I64*$B$10))/$B$10,0)),(ROUNDDOWN((G64-(J64*$C$10))/$B$10,0)))*L64) -> #VALUE! | N64: =(K64*L64)+((MAX((ROUNDDOWN((G64-(K64*$B$10))/$B$10,0)),(ROUNDDOWN((F64-(L64*$C$10))/$B$10,0)))*J64)) -> #VALUE! | O64: =MAX(M64:N64) -> #VALUE! | P64: =H64/O64 -> #VALUE! | R64: =ROUNDUP(Q64/O64,0) -> #VALUE! | AL64: 0 | AM64: 0 | AN64: -0.5 | AO64: -0.5 | AP64: 0 | BA64: =IFERROR(__xludf.DUMMYFUNCTION("SPLIT(AW64,""*"")"),"#VALUE!") -> #VALUE!
I65: =ROUNDDOWN(F65/$B$10,0) -> #VALUE! | J65: =ROUNDDOWN(G65/$C$10,0) -> #DIV/0! | K65: =ROUNDDOWN(G65/$B$10,0) -> #VALUE! | L65: =ROUNDDOWN(F65/$C$10,0) -> #DIV/0! | M65: =(I65*J65)+(MAX((ROUNDDOWN((F65-(I65*$B$10))/$B$10,0)),(ROUNDDOWN((G65-(J65*$C$10))/$B$10,0)))*L65) -> #VALUE! | N65: =(K65*L65)+((MAX((ROUNDDOWN((G65-(K65*$B$10))/$B$10,0)),(ROUNDDOWN((F65-(L65*$C$10))/$B$10,0)))*J65)) -> #VALUE! | O65: =MAX(M65:N65) -> #VALUE! | P65: =H65/O65 -> #VALUE! | R65: =ROUNDUP(Q65/O65,0) -> #VALUE! | AL65: 0 | AM65: 0 | AN65: -0.5 | AO65: -0.5 | AP65: 0 | BA65: =IFERROR(__xludf.DUMMYFUNCTION("SPLIT(AW65,""*"")"),"#VALUE!") -> #VALUE!
I66: =ROUNDDOWN(F66/$B$10,0) -> #VALUE! | J66: =ROUNDDOWN(G66/$C$10,0) -> #DIV/0! | K66: =ROUNDDOWN(G66/$B$10,0) -> #VALUE! | L66: =ROUNDDOWN(F66/$C$10,0) -> #DIV/0! | M66: =(I66*J66)+(MAX((ROUNDDOWN((F66-(I66*$B$10))/$B$10,0)),(ROUNDDOWN((G66-(J66*$C$10))/$B$10,0)))*L66) -> #VALUE! | N66: =(K66*L66)+((MAX((ROUNDDOWN((G66-(K66*$B$10))/$B$10,0)),(ROUNDDOWN((F66-(L66*$C$10))/$B$10,0)))*J66)) -> #VALUE! | O66: =MAX(M66:N66) -> #VALUE! | P66: =H66/O66 -> #VALUE! | R66: =ROUNDUP(Q66/O66,0) -> #VALUE! | AL66: 0 | AM66: 0 | AN66: -0.5 | AO66: -0.5 | AP66: 0 | BA66: =IFERROR(__xludf.DUMMYFUNCTION("SPLIT(AW66,""*"")"),"#VALUE!") -> #VALUE!
I67: =ROUNDDOWN(F67/$B$10,0) -> #VALUE! | J67: =ROUNDDOWN(G67/$C$10,0) -> #DIV/0! | K67: =ROUNDDOWN(G67/$B$10,0) -> #VALUE! | L67: =ROUNDDOWN(F67/$C$10,0) -> #DIV/0! | M67: =(I67*J67)+(MAX((ROUNDDOWN((F67-(I67*$B$10))/$B$10,0)),(ROUNDDOWN((G67-(J67*$C$10))/$B$10,0)))*L67) -> #VALUE! | N67: =(K67*L67)+((MAX((ROUNDDOWN((G67-(K67*$B$10))/$B$10,0)),(ROUNDDOWN((F67-(L67*$C$10))/$B$10,0)))*J67)) -> #VALUE! | O67: =MAX(M67:N67) -> #VALUE! | P67: =H67/O67 -> #VALUE! | R67: =ROUNDUP(Q67/O67,0) -> #VALUE! | AL67: 0 | AM67: 0 | AN67: -0.5 | AO67: -0.5 | AP67: 0 | BA67: =IFERROR(__xludf.DUMMYFUNCTION("SPLIT(AW67,""*"")"),"#VALUE!") -> #VALUE!
I68: =ROUNDDOWN(F68/$B$10,0) -> #VALUE! | J68: =ROUNDDOWN(G68/$C$10,0) -> #DIV/0! | K68: =ROUNDDOWN(G68/$B$10,0) -> #VALUE! | L68: =ROUNDDOWN(F68/$C$10,0) -> #DIV/0! | M68: =(I68*J68)+(MAX((ROUNDDOWN((F68-(I68*$B$10))/$B$10,0)),(ROUNDDOWN((G68-(J68*$C$10))/$B$10,0)))*L68) -> #VALUE! | N68: =(K68*L68)+((MAX((ROUNDDOWN((G68-(K68*$B$10))/$B$10,0)),(ROUNDDOWN((F68-(L68*$C$10))/$B$10,0)))*J68)) -> #VALUE! | O68: =MAX(M68:N68) -> #VALUE! | P68: =H68/O68 -> #VALUE! | R68: =ROUNDUP(Q68/O68,0) -> #VALUE! | AL68: 0 | AM68: 0 | AN68: -0.5 | AO68: -0.5 | AP68: 0 | BA68: =IFERROR(__xludf.DUMMYFUNCTION("SPLIT(AW68,""*"")"),"#VALUE!") -> #VALUE!
I69: =ROUNDDOWN(F69/$B$10,0) -> #VALUE! | J69: =ROUNDDOWN(G69/$C$10,0) -> #DIV/0! | K69: =ROUNDDOWN(G69/$B$10,0) -> #VALUE! | L69: =ROUNDDOWN(F69/$C$10,0) -> #DIV/0! | M69: =(I69*J69)+(MAX((ROUNDDOWN((F69-(I69*$B$10))/$B$10,0)),(ROUNDDOWN((G69-(J69*$C$10))/$B$10,0)))*L69) -> #VALUE! | N69: =(K69*L69)+((MAX((ROUNDDOWN((G69-(K69*$B$10))/$B$10,0)),(ROUNDDOWN((F69-(L69*$C$10))/$B$10,0)))*J69)) -> #VALUE! | O69: =MAX(M69:N69) -> #VALUE! | P69: =H69/O69 -> #VALUE! | R69: =ROUNDUP(Q69/O69,0) -> #VALUE! | AL69: 0 | AM69: 0 | AN69: -0.5 | AO69: -0.5 | AP69: 0 | BA69: =IFERROR(__xludf.DUMMYFUNCTION("SPLIT(AW69,""*"")"),"#VALUE!") -> #VALUE!
AL70: 0 | AM70: 0 | AN70: -0.5 | AO70: -0.5 | AP70: 0 | BA70: =IFERROR(__xludf.DUMMYFUNCTION("SPLIT(AW70,""*"")"),"#VALUE!") -> #VALUE!
AL71: 0 | AM71: 0 | AN71: -0.5 | AO71: -0.5 | AP71: 0 | BA71: =IFERROR(__xludf.DUMMYFUNCTION("SPLIT(AW71,""*"")"),"#VALUE!") -> #VALUE!
AL72: 0 | AM72: 0 | AN72: -0.5 | AO72: -0.5 | AP72: 0 | BA72: =IFERROR(__xludf.DUMMYFUNCTION("SPLIT(AW72,""*"")"),"#VALUE!") -> #VALUE!
AL73: 0 | AM73: 0 | AN73: -0.5 | AO73: -0.5 | AP73: 0 | BA73: =IFERROR(__xludf.DUMMYFUNCTION("SPLIT(AW73,""*"")"),"#VALUE!") -> #VALUE!
AL74: 0 | AM74: 0 | AN74: -0.5 | AO74: -0.5 | AP74: 0 | BA74: =IFERROR(__xludf.DUMMYFUNCTION("SPLIT(AW74,""*"")"),"#VALUE!") -> #VALUE!
AL75: 0 | AM75: 0 | AN75: -0.5 | AO75: -0.5 | AP75: 0 | BA75: =IFERROR(__xludf.DUMMYFUNCTION("SPLIT(AW75,""*"")"),"#VALUE!") -> #VALUE!
AL76: 0 | AM76: 0 | AN76: -0.5 | AO76: -0.5 | AP76: 0 | BA76: =IFERROR(__xludf.DUMMYFUNCTION("SPLIT(AW76,""*"")"),"#VALUE!") -> #VALUE!
AL77: 0 | AM77: 0 | AN77: -0.5 | AO77: -0.5 | AP77: 0 | BA77: =IFERROR(__xludf.DUMMYFUNCTION("SPLIT(AW77,""*"")"),"#VALUE!") -> #VALUE!
AL78: 0 | AM78: 0 | AN78: -0.5 | AO78: -0.5 | AP78: 0 | BA78: =IFERROR(__xludf.DUMMYFUNCTION("SPLIT(AW78,""*"")"),"#VALUE!") -> #VALUE!
AL79: 0 | AM79: 0 | AN79: -0.5 | AO79: -0.5 | AP79: 0 | BA79: =IFERROR(__xludf.DUMMYFUNCTION("SPLIT(AW79,""*"")"),"#VALUE!") -> #VALUE!
AL80: 0 | AM80: 0 | AN80: -0.5 | AO80: -0.5 | AP80: 0 | BA80: =IFERROR(__xludf.DUMMYFUNCTION("SPLIT(AW80,""*"")"),"#VALUE!") -> #VALUE!
AL81: 0 | AM81: 0 | AN81: -0.5 | AO81: -0.5 | AP81: 0 | BA81: =IFERROR(__xludf.DUMMYFUNCTION("SPLIT(AW81,""*"")"),"#VALUE!") -> #VALUE!
AL82: 0 | AM82: 0 | AN82: -0.5 | AO82: -0.5 | AP82: 0 | BA82: =IFERROR(__xludf.DUMMYFUNCTION("SPLIT(AW82,""*"")"),"#VALUE!") -> #VALUE!
AL83: 0 | AM83: 0 | AN83: -0.5 | AO83: -0.5 | AP83: 0 | BA83: =IFERROR(__xludf.DUMMYFUNCTION("SPLIT(AW83,""*"")"),"#VALUE!") -> #VALUE!
AL84: 0 | AM84: 0 | AN84: -0.5 | AO84: -0.5 | AP84: 0 | BA84: =IFERROR(__xludf.DUMMYFUNCTION("SPLIT(AW84,""*"")"),"#VALUE!") -> #VALUE!
AL85: 0 | AM85: 0 | AN85: -0.5 | AO85: -0.5 | AP85: 0 | BA85: =IFERROR(__xludf.DUMMYFUNCTION("SPLIT(AW85,""*"")"),"#VALUE!") -> #VALUE!
AL86: 0 | AM86: 0 | AN86: -0.5 | AO86: -0.5 | AP86: 0 | BA86: =IFERROR(__xludf.DUMMYFUNCTION("SPLIT(AW86,""*"")"),"#VALUE!") -> #VALUE!
AL87: 0 | AM87: 0 | AN87: -0.5 | AO87: -0.5 | AP87: 0 | BA87: =IFERROR(__xludf.DUMMYFUNCTION("SPLIT(AW87,""*"")"),"#VALUE!") -> #VALUE!
AL88: 0 | AM88: 0 | AN88: -0.5 | AO88: -0.5 | AP88: 0 | BA88: =IFERROR(__xludf.DUMMYFUNCTION("SPLIT(AW88,""*"")"),"#VALUE!") -> #VALUE!
AL89: 0 | AM89: 0 | AN89: -0.5 | AO89: -0.5 | AP89: 0 | BA89: =IFERROR(__xludf.DUMMYFUNCTION("SPLIT(AW89,""*"")"),"#VALUE!") -> #VALUE!
AL90: 0 | AM90: 0 | AN90: -0.5 | AO90: -0.5 | AP90: 0 | BA90: =IFERROR(__xludf.DUMMYFUNCTION("SPLIT(AW90,""*"")"),"#VALUE!") -> #VALUE!
AL91: 0 | AM91: 0 | AN91: -0.5 | AO91: -0.5 | AP91: 0 | AR91: =IFERROR(__xludf.DUMMYFUNCTION("SPLIT(AN91,""*"")"),-0.5) -> -0.5 | BA91: =IFERROR(__xludf.DUMMYFUNCTION("SPLIT(AW91,""*"")"),"#VALUE!") -> #VALUE!
AL92: 0 | AM92: 0 | AN92: -0.5 | AO92: -0.5 | AP92: 0 | AR92: =IFERROR(__xludf.DUMMYFUNCTION("SPLIT(AN92,""*"")"),-0.5) -> -0.5 | BA92: =IFERROR(__xludf.DUMMYFUNCTION("SPLIT(AW92,""*"")"),"#VALUE!") -> #VALUE!
AL93: 0 | AM93: 0 | AN93: -0.5 | AO93: -0.5 | AP93: 0 | AR93: =IFERROR(__xludf.DUMMYFUNCTION("SPLIT(AN93,""*"")"),-0.5) -> -0.5 | BA93: =IFERROR(__xludf.DUMMYFUNCTION("SPLIT(AW93,""*"")"),"#VALUE!") -> #VALUE!
